Workbook

Sheet Daily Sales
B1: PERIODE OF June 2026 | C1: =CHOOSE(WEEKDAY(DATE(2026,6,1)+COLUMN()-2.1),"sunday","monday","tuesday","wednesday","thursday","friday","saturday") -> monday | D1: =CHOOSE(WEEKDAY(DATE(2026,6,1)+COLUMN()-2.1),"sunday","monday","tuesday","wednesday","thursday","friday","saturday") -> tuesday | E1: =CHOOSE(WEEKDAY(DATE(2026,6,1)+COLUMN()-2.1),"sunday","monday","tuesday","wednesday","thursday","friday","saturday") -> wednesday | F1: =CHOOSE(WEEKDAY(DATE(2026,6,1)+COLUMN()-2.1),"sunday","monday","tuesday","wednesday","thursday","friday","saturday") -> thursday | G1: =CHOOSE(WEEKDAY(DATE(2026,6,1)+COLUMN()-2.1),"sunday","monday","tuesday","wednesday","thursday","friday","saturday") -> friday | H1: =CHOOSE(WEEKDAY(DATE(2026,6,1)+COLUMN()-2.1),"sunday","monday","tuesday","wednesday","thursday","friday","saturday") -> saturday | I1: =CHOOSE(WEEKDAY(DATE(2026,6,1)+COLUMN()-2.1),"sunday","monday","tuesday","wednesday","thursday","friday","saturday") -> sunday | J1: =CHOOSE(WEEKDAY(DATE(2026,6,1)+COLUMN()-2.1),"sunday","monday","tuesday","wednesday","thursday","friday","saturday") -> monday | ... AF1: =CHOOSE(WEEKDAY(DATE(2026,6,1)+COLUMN()-2.1),"sunday","monday","tuesday","wednesday","thursday","friday","saturday") -> tuesday
B2: DESCRIPTION | C2: 46174 | D2: 46175 | E2: 46176 | F2: 46177 | G2: 46178 | H2: 46179 | I2: 46180 | J2: 46181 | K2: 46182 | L2: 46183 | M2: 46184 | N2: 46185 | O2: 46186 | P2: 46187 | Q2: 46188 | R2: 46189 | S2: 46190 | T2: 46191 | U2: 46192 | V2: 46193 | W2: 46194 | X2: 46195 | Y2: 46196 | Z2: 46197 | AA2: 46198 | AB2: 46199 | AC2: 46200 | AD2: 46201 | AE2: 46202 | AF2: 46203 | AG2: TOTAL
B3: Terrace Revenue: | AG3: =SUM(C3:AF3) -> 0
A4: 4-2100 | B4: Sales Food TERRACE | C4: 4945000 | D4: =3035000+250000+305000 -> 3590000 | E4: 4209000 | F4: 3432500 | G4: 8275000 | H4: 5030000 | I4: 5040000 | J4: 3341000 | K4: 4035000 | L4: 6649000 | M4: 5400000 | N4: =9149000+125000 -> 9274000 | O4: =5485000 -> 5485000 | P4: 5760000 | Q4: 4420000 | R4: 7796750 | S4: 5875875 | T4: =6480000 -> 6480000 | U4: =5535000 -> 5535000 | V4: =6158000 -> 6158000 | W4: =5208000+125000 -> 5333000 | X4: 4850000 | Y4: 5089000 | Z4: =3845000 -> 3845000 | AA4: 4282500 | AB4: 6577500 | AC4: 5328750 | AD4: 3120000 | AE4: 5250000 | AF4: =4598750 -> 4598750 | AG4: =SUM(C4:AF4) -> 159005625
A5: 4-2200 | B5: Sales Beverages TERRACE | C5: 8420000 | D5: =2690000+50000 -> 2740000 | E5: 7993000 | F5: 5855000 | G5: 12875000 | H5: 6765000 | I5: 5610000 | J5: 2674000 | K5: 5815000 | L5: 7545000 | M5: 5150000 | N5: =13090000 -> 13090000 | O5: =10725000 -> 10725000 | P5: 11125000 | Q5: 6690000 | R5: 8883000 | S5: 11605000 | T5: =10075000 -> 10075000 | U5: =11900000 -> 11900000 | V5: =12055000 -> 12055000 | W5: 9126000 | X5: 7930000 | Y5: 8795000 | Z5: =6485000 -> 6485000 | AA5: 6225000 | AB5: =13445000 -> 13445000 | AC5: 10890000 | AD5: 3978000 | AE5: 6645000 | AF5: =7464000 -> 7464000 | AG5: =SUM(C5:AF5) -> 248573000
A6: 4-2400 | B6: Sales Cigarette TERRACE | E6: 259000 | F6: 70000 | G6: 210000 | H6: 140000 | I6: 70000 | J6: 70000 | K6: 70000 | N6: =210000+358000 -> 568000 | O6: =210000 -> 210000 | P6: 420000 | R6: 140000 | S6: 70000 | T6: =140000+358000 -> 498000 | U6: =70000 -> 70000 | V6: =210000 -> 210000 | W6: 280000 | X6: 140000 | Y6: 70000 | Z6: =140000 -> 140000 | AA6: 70000 | AB6: =210000+120000 -> 330000 | AD6: 70000 | AG6: =SUM(C6:AF6) -> 4175000
A7: 4-2300 | B7: Sales Shisa TERRACE | C7: 1500000 | E7: 500000 | G7: 500000 | I7: 250000 | K7: 250000 | O7: =250000 -> 250000 | R7: 250000 | V7: =500000 -> 500000 | Z7: =250000 -> 250000 | AC7: 250000 | AD7: 250000 | AE7: 250000 | AG7: =SUM(C7:AF7) -> 5000000
A8: 4-2602 | B8: Merchandise TERRACE | AG8: =SUM(C8:AF8) -> 0
B9: Total Terrace Revenue | C9: =SUM(C4:C8) -> 14865000 | D9: =SUM(D4:D8) -> 6330000 | E9: =SUM(E4:E8) -> 12961000 | F9: =SUM(F4:F8) -> 9357500 | G9: =SUM(G4:G8) -> 21860000 | H9: =SUM(H4:H8) -> 11935000 | I9: =SUM(I4:I8) -> 10970000 | J9: =SUM(J4:J8) -> 6085000 | ... AG9: =SUM(AG4:AG8) -> 416753625
B10: Spend per Guest | C10: 42 | D10: 23 | E10: 40 | F10: 29 | G10: 61 | H10: 48 | I10: 39 | J10: 23 | K10: 49 | L10: 51 | M10: 40 | N10: 68 | O10: =76 -> 76 | P10: 57 | Q10: 43 | R10: 57 | S10: 50 | T10: =56 -> 56 | U10: =72 -> 72 | V10: 66 | W10: =57 -> 57 | X10: 47 | Y10: 64 | Z10: 45 | AA10: 39 | AB10: 65 | AC10: 61 | AD10: 30 | AE10: 45 | AF10: =40 -> 40 | AG10: =SUM(C10:AF10) -> 1483
B11: Club Revenue: | AG11: =SUM(C11:AF11) -> 0
A12: 4-2200 | B12: Sales Beverages CLUB | C12: 12575000 | D12: 27335000 | E12: 12240000 | F12: =32025000+1725000 -> 33750000 | G12: =6875000+53315000 -> 60190000 | H12: =27995000+66900000 -> 94895000 | I12: =11220000 -> 11220000 | J12: 48200000 | K12: =38654000 -> 38654000 | L12: 30350000 | M12: =3230000+19905000 -> 23135000 | N12: =30405000+2835000 -> 33240000 | O12: =54365000+16860000 -> 71225000 | P12: =9165000+20000 -> 9185000 | Q12: 13455000 | R12: 35500000 | S12: 27260000 | T12: =1420000+14465000 -> 15885000 | U12: 47900000 | V12: =65320000+20010000 -> 85330000 | W12: 13450000 | X12: =450000+12095000 -> 12545000 | Y12: =27903000 -> 27903000 | Z12: 21060000 | AA12: =23050000+1365000 -> 24415000 | AB12: =55390000 -> 55390000 | AC12: =59160000+19995000 -> 79155000 | AD12: 15955000 | AE12: =204000+25845000 -> 26049000 | AF12: =16715000+466752 -> 17181752 | AG12: =SUM(C12:AF12) -> 1024627752
A13: 4-2400 | B13: Sales Cigarette CLUB | D13: =700000+120000 -> 820000 | E13: 420000 | F13: 490000 | G13: =70000+1190000 -> 1260000 | H13: =770000+770000 -> 1540000 | I13: =630000 -> 630000 | J13: 630000 | K13: =840000 -> 840000 | L13: 70000 | M13: =560000 -> 560000 | N13: =1050000 -> 1050000 | O13: =910000+770000 -> 1680000 | P13: 140000 | Q13: 70000 | R13: 560000 | S13: 700000 | T13: =560000 -> 560000 | U13: 770000 | V13: =910000+280000 -> 1190000 | W13: 210000 | Y13: =140000 -> 140000 | Z13: 350000 | AA13: 840000 | AB13: =1330000 -> 1330000 | AC13: =1820000+1260000 -> 3080000 | AE13: =700000 -> 700000 | AF13: 490000 | AG13: =SUM(C13:AF13) -> 21120000
A14: 4-2100 | B14: Sales Food CLUB | C14: 100000 | D14: 350000 | E14: 530000 | F14: =600000+190000 -> 790000 | G14: 1160000 | H14: =500000+990000 -> 1490000 | I14: =245000 -> 245000 | J14: 1040000 | K14: =250000 -> 250000 | M14: =150000+150000 -> 300000 | N14: =1170000 -> 1170000 | O14: =1090000+150000 -> 1240000 | P14: 100000 | Q14: 100000 | R14: 390000 | S14: 100000 | T14: =650000+490000 -> 1140000 | U14: 570000 | V14: =1815000+140000 -> 1955000 | W14: 200000 | X14: =250000 -> 250000 | Y14: =1020000 -> 1020000 | Z14: 690000 | AA14: =280000+100000 -> 380000 | AB14: =600000 -> 600000 | AC14: =1430000+375000 -> 1805000 | AD14: 100000 | AE14: =450000 -> 450000 | AF14: 450000 | AG14: =SUM(C14:AF14) -> 18965000
A15: 4-2300 | B15: Sales Shisa CLUB | D15: 250000 | E15: 750000 | F15: 750000 | G15: 1750000 | H15: =750000 -> 750000 | J15: 500000 | K15: =250000 -> 250000 | N15: =750000 -> 750000 | O15: =500000 -> 500000 | P15: 250000 | Q15: 120000 | R15: 250000 | T15: =250000 -> 250000 | U15: 500000 | V15: 1200000 | AB15: =250000 -> 250000 | AC15: =500000 -> 500000 | AF15: 500000 | AG15: =SUM(C15:AF15) -> 10070000
A16: 4-2601 | B16: Red Room | AG16: =SUM(C16:AF16) -> 0
A17: 4-2601 | B17: Misc | E17: =200000 -> 200000 | G17: 120000 | Z17: 2500000 | AF17: =45000000 -> 45000000 | AG17: =SUM(C17:AF17) -> 47820000
A18: 4-2602 | B18: Merchandise | AG18: =SUM(C18:AF18) -> 0
A19: 4-2500 | B19: Sales Ticket | C19: 12404452 | D19: 6627036 | E19: 13763844 | F19: =12404452+1656759 -> 14061211 | G19: 24936347 | H19: 36321255 | I19: 11214984 | J19: 13593920 | K19: =11639794 -> 11639794 | L19: 10195440 | M19: =1444354+12404452 -> 13848806 | N19: =17842020 -> 17842020 | O19: =31520902 -> 31520902 | P19: 9855592 | Q19: 11045060 | R19: 11384908 | S19: =10705212+200000 -> 10905212 | T19: =1444354+9345820 -> 10790174 | U19: 22175082 | V19: 28674675 | W19: 9515744 | X19: 11554832 | Y19: 17842020 | Z19: 9005972 | AA19: =9685668+2039088 -> 11724756 | AB19: =25616043+3000000 -> 28616043 | AC19: =25913410 -> 25913410 | AD19: 9005972 | AE19: 9685668 | AF19: 11045060 | AG19: =SUM(C19:AF19) -> 466710191
B20: Total Club Revenue | C20: =SUM(C12:C19) -> 25079452 | D20: =SUM(D12:D19) -> 35382036 | E20: =SUM(E12:E19) -> 27903844 | F20: =SUM(F12:F19) -> 49841211 | G20: =SUM(G12:G19) -> 89416347 | H20: =SUM(H12:H19) -> 134996255 | I20: =SUM(I12:I19) -> 23309984 | J20: =SUM(J12:J19) -> 63963920 | ... AG20: =SUM(AG12:AG19) -> 1589312943
B21: Spend per Guest | C21: 51 | D21: 76 | E21: 73 | F21: =113+13 -> 126 | G21: =40+123 -> 163 | H21: =75+113 -> 188 | I21: 63 | J21: 95 | K21: =103 -> 103 | L21: 51 | M21: =5+80 -> 85 | N21: =70 -> 70 | O21: =128+62 -> 190 | P21: 30 | Q21: 54 | R21: 92 | S21: 68 | T21: =9+60 -> 69 | U21: =151 -> 151 | V21: =135+67 -> 202 | W21: =68 -> 68 | X21: =70 -> 70 | Y21: =136 -> 136 | Z21: 33 | AA21: 56 | AB21: =177 -> 177 | AC21: =134+70 -> 204 | AD21: 52 | AE21: =52 -> 52 | AF21: =61 -> 61 | AG21: =SUM(C21:AF21) -> 2909
B22: Deduction: | AG22: =SUM(C22:AF22) -> 0
A23: 4-5110 | B23: Discount | C23: =SUM(C24:C26) -> 626500 | D23: =SUM(D24:D26) -> 902500 | E23: =SUM(E24:E26) -> 374000 | F23: =SUM(F24:F26) -> 1759000 | G23: =SUM(G24:G26) -> 1352000 | H23: =SUM(H24:H26) -> 2866000 | I23: =SUM(I24:I26) -> 787000 | J23: =SUM(J24:J26) -> 691500 | ... AG23: =SUM(AG24:AG26) -> 30762000
B24: Disc 10-15% | H24: =250000+260000 -> 510000 | O24: =700000 -> 700000 | R24: =1400000 -> 1400000 | AG24: =SUM(C24:AF24) -> 2610000
B25: Disc 20-30% | C25: 19000 | E25: 54000 | F25: 1034000 | G25: =252000+750000 -> 1002000 | H25: =66000 -> 66000 | I25: =12000+35000 -> 47000 | J25: =514000 -> 514000 | M25: =17000 -> 17000 | N25: =750000+90000+36000 -> 876000 | O25: =650000+195000 -> 845000 | P25: =24000+24000 -> 48000 | Q25: =64000+20000 -> 84000 | R25: 64000 | S25: =29000+122000 -> 151000 | T25: =39000+49000 -> 88000 | U25: =129000+58000 -> 187000 | V25: =650000+190000+18000 -> 858000 | W25: =15000+40000 -> 55000 | X25: =48000 -> 48000 | Y25: =10000 -> 10000 | AA25: 26000 | AB25: =750000 -> 750000 | AC25: =30000+650000+43000+20000 -> 743000 | AE25: =135000 -> 135000 | AF25: =58000+203000 -> 261000 | AG25: =SUM(C25:AF25) -> 7982000
B26: Disc 50% | C26: 607500 | D26: 902500 | E26: 320000 | F26: 725000 | G26: =317500+32500 -> 350000 | H26: =442500+1627500+220000 -> 2290000 | I26: =75000+665000 -> 740000 | J26: =25000+152500 -> 177500 | K26: 785000 | L26: 160000 | M26: =362500 -> 362500 | N26: =36000+440000+24000 -> 500000 | O26: =412500+392500+192500 -> 997500 | P26: =137500 -> 137500 | Q26: =302500 -> 302500 | R26: =250000+540000 -> 790000 | S26: =250000 -> 250000 | T26: =302500+50000 -> 352500 | U26: =485000+437500 -> 922500 | V26: =1162500+350000 -> 1512500 | W26: =412500 -> 412500 | X26: =50000+560000 -> 610000 | Y26: =495000+137500 -> 632500 | Z26: =85000+230000 -> 315000 | AA26: =335000 -> 335000 | AB26: =130000 -> 130000 | AC26: =175000+482500+152500 -> 810000 | AD26: =340000+1195000 -> 1535000 | AE26: =1625000+15000 -> 1640000 | AF26: =497500+67500 -> 565000 | AG26: =SUM(C26:AF26) -> 20170000
C27: =C9+C20-C23 -> 39317952 | D27: =D9+D20-D23 -> 40809536 | E27: =E9+E20-E23 -> 40490844 | F27: =F9+F20-F23 -> 57439711 | G27: =G9+G20-G23 -> 109924347 | H27: =H9+H20-H23 -> 144065255 | I27: =I9+I20-I23 -> 33492984 | J27: =J9+J20-J23 -> 69357420 | ... AG27: =AG9+AG20-AG23 -> 1975304568
A28: 2-2106 | B28: Service Charges 7% | C28: =C27*7% -> 2752256.6 | D28: =D27*7% -> 2856667.5 | E28: 2820359.1 | F28: =F27*7% -> 4020779.8 | G28: =G27*7% -> 7694704.3 | H28: =H27*7% -> 10084568 | I28: =I27*7% -> 2344508.9 | J28: =J27*7% -> 4855019.4 | K28: =K27*7% -> 4271315.6 | L28: =L27*7% -> 3825460.8 | M28: =M27*7% -> 3361001.4 | ... Q28: =Q27*7% -> 2485949.2 | R28: 4360364 | S28: 3818095 | T28: =T27*7% -> 3166637.2 | U28: =U27*7% -> 6181740.7 | V28: =V27*7% -> 9443152.2 | W28: =W27*7% -> 2635307.1 | X28: =X27*7% -> 2562828.2 | Y28: =Y27*7% -> 4215156.4 | Z28: 2905768 | AA28: =AA27*7% -> 3330337.9 | AB28: 7186098 | AC28: =AC27*7% -> 8775841.2 | AD28: =AD27*7% -> 2166078 | AE28: =AE27*7%-14280 -> 3293546.8 | AF28: 2830576.7 | AG28: =SUM(C28:AF28) -> 1.3452272e+08
A29: 2-3101 | B29: Tax PB1 10% | C29: =SUM(C27:C28)*10% -> 4207020.9 | D29: =SUM(D27:D28)*10% -> 4366620.4 | E29: 4311120.3 | F29: =SUM(F27:F28)*10% -> 6146049.1 | G29: =SUM(G27:G28)*10% -> 11761905 | H29: =SUM(H27:H28)*10% -> 15414982 | I29: =SUM(I27:I28)*10% -> 3583749.3 | J29: =SUM(J27:J28)*10% -> 7421243.9 | K29: =SUM(K27:K28)*10% -> 6529011 | L29: =SUM(L27:L28)*10% -> 5847490.1 | M29: =SUM(M27:M28)*10% -> 5137530.7 | ... Q29: =SUM(Q27:Q28)*10% -> 3799950.9 | R29: 6665127 | S29: 5836232 | T29: =SUM(T27:T28)*10% -> 4840431.1 | U29: =SUM(U27:U28)*10% -> 9449232.3 | V29: =SUM(V27:V28)*10% -> 14434533 | W29: =SUM(W27:W28)*10% -> 4028255.1 | X29: =SUM(X27:X28)*10% -> 3917466 | Y29: =SUM(Y27:Y28)*10% -> 6443167.6 | Z29: 4441674 | AA29: =SUM(AA27:AA28)*10% -> 5090659.4 | AB29: 10984464 | AC29: =SUM(AC27:AC28)*10% -> 13414500 | AD29: =SUM(AD27:AD28)*10% -> 3311005 | AE29: =SUM(AE27:AE28)*10%-20400 -> 5034421.5 | AF29: 4326738.7 | AG29: =SUM(C29:AF29) -> 2.0562759e+08
B30: Total All Income | C30: =C27+C28+C29 -> 46277230 | D30: =D27+D28+D29 -> 48032824 | E30: =E27+E28+E29 -> 47622323 | F30: =F27+F28+F29 -> 67606540 | G30: =G27+G28+G29 -> 1.2938096e+08 | H30: =H27+H28+H29 -> 1.6956481e+08 | I30: =I27+I28+I29 -> 39421242 | J30: =J27+J28+J29 -> 81633683 | ... AG30: =AG27+AG28+AG29 -> 2.3154549e+09
AG31: =SUM(C31:AF31) -> 0
A32: 1-1119 | B32: Cash IDR | C32: =6002700+4500000 -> 10502700 | D32: 7081180 | E32: 9760327 | F32: 6021430 | G32: =818015+6900080+4825700+3808495 -> 16352290 | H32: =1700765+941600+9250117+6755980 -> 18648462 | I32: =1863191+4600036+294250 -> 6757477 | J32: =1821408+712085+3800043 -> 6333536 | K32: =641465+3100038+3174958 -> 6916461 | L32: =3800033+900405+3819365 -> 8519803 | M32: =597175+4600040+394295+1930280 -> 7521790 | N32: =2450057+2053285+523765+3800533 -> 8827640 | O32: =5965504+1047530+9350102+4684280 -> 21047416 | P32: =4835975+595562+2600031 -> 8031568 | Q32: =47080+5049331+2400060 -> 7496471 | R32: =4600037+788545+5034280 -> 10422862 | S32: =3200035+4631495+1400180 -> 9231710 | T32: =700005+4800030+6638280+847440 -> 12985755 | U32: =5237605+973725+5500072 -> 11711402 | V32: =2191470+682660+4596185+8750092 -> 16220407 | W32: =2200031+323675+2542320 -> 5066026 | X32: =1600037+388410+6979610 -> 8968057 | Y32: =2365770+894520+5200057 -> 8460347 | Z32: =2698273+3800029+4599128 -> 11097430 | AA32: =3595735+6860560+3200032+550006 -> 14206333 | AB32: =5000083+5371413+6020355 -> 16391851 | AC32: =3931180+622425+6250084+617925 -> 11421614 | AD32: =1324125+3600029+300135 -> 5224289 | AE32: =459030+5720220+3400032 -> 9579282 | AF32: =5049330+2377540+3800035 -> 11226905 | AG32: =SUM(C32:AF32) -> 312032821 | AH32: =SUM(AG32:AG45)+AG48+AG49 -> 2300913831 | AI32: total
A33: 1-1217 | B33: Bank transfer | H33: =1000000+7000000 -> 8000000 | O33: =6997490 -> 6997490 | V33: =3000000 -> 3000000 | AB33: =2967390 -> 2967390 | AE33: =204000 -> 204000 | AF33: =45000000 -> 45000000 | AG33: =SUM(C33:AF33) -> 66168880
B34: Credit Cards: | AG34: =SUM(C34:AF34) -> 0
A35: 1-1216 | B35: Cim Niaga TBB | G35: =1000450 -> 1000450 | H35: 23967805 | K35: 4731541 | L35: 0 | N35: =5117700 -> 5117700 | O35: =7431474 -> 7431474 | P35: =5296500 -> 5296500 | Q35: =117700 -> 117700 | U35: =9273410 -> 9273410 | V35: =14008585 -> 14008585 | AA35: =3848790 -> 3848790 | AB35: =4265320 -> 4265320 | AC35: =1553640 -> 1553640 | AG35: =SUM(C35:AF35) -> 80612915 | AH35: =AG35 -> 80612915 | AI35: cimb
A36: 1-1213 | B36: Mandiri Debet | C36: 258490 | D36: 0 | E36: 515526 | F36: 4896050 | G36: =2315185 -> 2315185 | H36: 1000000 | I36: =200000 -> 200000 | J36: 623810 | K36: 2244878 | L36: =200000 -> 200000 | M36: 3295600 | N36: =250000 -> 250000 | O36: =947260 -> 947260 | P36: =658850 -> 658850 | Q36: =0 -> 0 | R36: =41195 -> 41195 | S36: =200000 -> 200000 | T36: =600000 -> 600000 | U36: =644933 -> 644933 | V36: =0 -> 0 | W36: =188320 -> 188320 | X36: =3260290 -> 3260290 | Y36: =70620 -> 70620 | Z36: 788320 | AA36: =0 -> 0 | AB36: =7992220 -> 7992220 | AC36: =5950090 -> 5950090 | AD36: =1259390 -> 1259390 | AE36: =182435 -> 182435 | AF36: =4319500 -> 4319500 | AG36: =SUM(C36:AF36) -> 42902962
A37: 1-1213 | B37: Mandiri CC | C37: 24448395 | D37: 23991345 | E37: 24441385 | F37: 34067990 | G37: =70510841 -> 70510841 | H37: 58769985 | I37: =21889110 -> 21889110 | J37: 39201170 | K37: 39943800 | L37: =48217543 -> 48217543 | M37: 27850285 | N37: =42195762 -> 42195762 | O37: =47519425 -> 47519425 | P37: =21388735 -> 21388735 | Q37: =26950969 -> 26950969 | R37: =31067502 -> 31067502 | S37: =43515705 -> 43515705 | T37: =33303956 -> 33303956 | U37: =39179617 -> 39179617 | V37: =51650340 -> 51650340 | W37: =23978930 -> 23978930 | X37: =23665505 -> 23665505 | Y37: =26241603 -> 26241603 | Z37: 22489950 | AA37: =29125110 -> 29125110 | AB37: =47648231 -> 47648231 | AC37: =50239425 -> 50239425 | AD37: =12721030 -> 12721030 | AE37: =14985620 -> 14985620 | AF37: =13302648 -> 13302648 | AG37: =SUM(C37:AF37) -> 1014501912
A38: 1-1213 | B38: Mandiri NPG | C38: 1435490 | D38: 1106380 | E38: 1923855 | F38: 2159255 | G38: =4352295 -> 4352295 | H38: 5641915 | I38: =3330460 -> 3330460 | J38: 694160 | K38: 7755800 | L38: =1547485 -> 1547485 | M38: 3544925 | N38: =5301650 -> 5301650 | O38: =17629570 -> 17629570 | P38: =2025900 -> 2025900 | Q38: =1029515 -> 1029515 | R38: =4496185 -> 4496185 | S38: =4231675 -> 4231675 | T38: =1247620 -> 1247620 | U38: =9220045 -> 9220045 | V38: =13661962 -> 13661962 | W38: =4342860 -> 4342860 | X38: =1553280 -> 1553280 | Y38: =4748475 -> 4748475 | Z38: 5049330 | AA38: =3833268 -> 3833268 | AB38: =6993985 -> 6993985 | AC38: =27384420 -> 27384420 | AD38: =1247350 -> 1247350 | AE38: =16624315 -> 16624315 | AF38: =6260920 -> 6260920 | AG38: =SUM(C38:AF38) -> 170374345
A39: 1-1213 | B39: Mandiri QR | C39: 2350833 | D39: 15065331 | E39: 1947755 | F39: 15820360 | G39: =6931023 -> 6931023 | H39: 20328480 | I39: =4392433 -> 4392433 | J39: 9768560 | K39: 3579576 | L39: =3942590 -> 3942590 | M39: 10374944 | N39: =8631698 -> 8631698 | O39: =20905847 -> 20905847 | P39: =1435670 -> 1435670 | Q39: =4383335 -> 4383335 | R39: =1665365 -> 1665365 | S39: =5494056 -> 5494056 | T39: =3470703 -> 3470703 | U39: =19802615 -> 19802615 | V39: =28701598 -> 28701598 | W39: =8849691 -> 8849691 | X39: =2868169 -> 2868169 | Y39: =23593748 -> 23593748 | Z39: 5621723 | AA39: =4671918 -> 4671918 | AB39: =20505918 -> 20505918 | AC39: =32008437 -> 32008437 | AD39: =9962765 -> 9962765 | AE39: =8409485 -> 8409485 | AF39: =10319943 -> 10319943 | AG39: =SUM(C39:AF39) -> 315804569 | AH39: =SUM(AG36:AG39)+AG49 -> 1543805788 | AI39: mandiri
A40: 1-1217 | B40: BCA CC | C40: 6579340 | D40: 70620 | E40: 7497490 | F40: 1571295 | G40: =11755980 -> 11755980 | H40: 16559213 | I40: =1412400 -> 1412400 | J40: 19067400 | K40: 5267075 | L40: =1218195 -> 1218195 | M40: 2061670 | N40: =14708542 -> 14708542 | O40: =11698030 -> 11698030 | P40: =2100945 -> 2100945 | Q40: =759165 -> 759165 | R40: =2410865 -> 2410865 | S40: =1094610 -> 1094610 | T40: =1259390 -> 1259390 | U40: =7438640 -> 7438640 | V40: =17273825 -> 17273825 | W40: =1014565 -> 1014565 | X40: =2006783 -> 2006783 | Y40: =2241008 -> 2241008 | Z40: 5649600 | AB40: =4849090 -> 4849090 | AC40: =8074220 -> 8074220 | AD40: =1842005 -> 1842005 | AE40: =3330910 -> 3330910 | AF40: =564960 -> 564960 | AG40: =SUM(C40:AF40) -> 161377831
A41: 1-1217 | B41: BCA debt | C41: 164780 | D41: 0 | E41: 364870 | F41: 1535985 | G41: =3531000 -> 3531000 | H41: 3236750 | I41: =765050 -> 765050 | J41: 5090525 | K41: 570845 | L41: 0 | M41: 1382975 | N41: =3719320 -> 3719320 | O41: =682660 -> 682660 | P41: 0 | Q41: 0 | R41: =20491570 -> 20491570 | S41: 0 | T41: 0 | U41: =812130 -> 812130 | V41: =3585315 -> 3585315 | W41: 0 | X41: 0 | Y41: =547305 -> 547305 | Z41: 235400 | AB41: =541420 -> 541420 | AC41: =847440 -> 847440 | AD41: =1041645 -> 1041645 | AE41: =1100495 -> 1100495 | AF41: =617925 -> 617925 | AG41: =SUM(C41:AF41) -> 50865405
A42: 1-1217 | B42: BCA QR | C42: 294250 | D42: 0 | E42: 105930 | F42: 694430 | G42: =13970990 -> 13970990 | H42: 13332883 | I42: =164780 -> 164780 | J42: 235400 | K42: 164780 | L42: =170665 -> 170665 | M42: 211860 | N42: 0 | O42: =4810295 -> 4810295 | P42: 0 | Q42: =729470 -> 729470 | R42: =2014655 -> 2014655 | S42: 0 | T42: =138886 -> 138886 | U42: =6965590 -> 6965590 | V42: =9078305 -> 9078305 | W42: =306020 -> 306020 | X42: 0 | Y42: =4271333 -> 4271333 | Z42: 158895 | AB42: =8169730 -> 8169730 | AC42: =7379790 -> 7379790 | AD42: =1021048 -> 1021048 | AE42: =1165230 -> 1165230 | AF42: 0 | AG42: =SUM(C42:AF42) -> 75555215 | AH42: =SUM(AG40:AG42)+AG33 -> 353967331 | AI42: bca
A43: 1-1214 | B43: Bank BRI DEBET | E43: 0 | G43: 0 | H43: 0 | L43: 0 | M43: 0 | O43: 0 | P43: =0 -> 0 | Q43: =282480 -> 282480 | R43: 0 | S43: 0 | U43: =276595 -> 276595 | X43: 0 | Y43: 0 | Z43: 0 | AG43: =SUM(C43:AF43) -> 559075
A44: 1-1214 | B44: Bank BRI CC | E44: 247170 | G44: =506110 -> 506110 | H44: 476685 | L44: =317790 -> 317790 | M44: 141240 | O44: =1012220 -> 1012220 | P44: =1783166 -> 1783166 | Q44: 0 | R44: =70620 -> 70620 | S44: =136532 -> 136532 | X44: =138288 -> 138288 | Y44: =117700 -> 117700 | Z44: 223630 | AG44: =SUM(C44:AF44) -> 5171151
A45: 1-1214 | B45: Bank BRI QR | E45: 0 | G45: =147125 -> 147125 | H45: 0 | L45: 0 | M45: 0 | O45: 0 | P45: 0 | Q45: 0 | R45: 0 | S45: 0 | Y45: 0 | Z45: 0 | AG45: =SUM(C45:AF45) -> 147125 | AH45: =SUM(AG43:AG45) -> 5877351 | AI45: bri
A46: 1-1202 | B46: Ledger | C46: 242462 | D46: 717971 | E46: 415481 | F46: 736802 | G46: =373698+141240 -> 514938 | H46: =303078+123585 -> 426663 | I46: =509054 -> 509054 | J46: =65912+111816 -> 177728 | K46: =644408 -> 644408 | L46: =188320 -> 188320 | M46: =170665 -> 170665 | N46: =282481 -> 282481 | O46: =680306+314848 -> 995154 | P46: =35310 -> 35310 | Q46: =73563 -> 73563 | R46: 635580 | S46: =294251+200000 -> 494251 | T46: =308963 -> 308963 | U46: =570846+2717382 -> 3288228 | V46: =2815973+344273 -> 3160246 | W46: =273654 -> 273654 | X46: =58850+435491 -> 494341 | Y46: =582615 -> 582615 | Z46: =44138 -> 44138 | AA46: 179493 | AB46: =3000000 -> 3000000 | AC46: =44138+2477585 -> 2521723 | AD46: =61793+1318240 -> 1380033 | AF46: =585558+79448+466752 -> 1131758 | AG46: =SUM(C46:AF46) -> 23626023
A47: 1-1129 | B47: Star Points | E47: 141240 | P47: =382525 -> 382525 | U47: =329560 -> 329560 | X47: =135355 -> 135355 | AB47: =253055 -> 253055 | AD47: =382525 -> 382525 | AF47: =147125 -> 147125 | AG47: =SUM(C47:AF47) -> 1771385
A48: 1-1215 | B48: Ovo | F48: 187500 | J48: 805000 | R48: 609750 | S48: 1370875 | V48: =168000 -> 168000 | W48: =264000 -> 264000 | AA48: 112500 | AB48: =244500 -> 244500 | AC48: =413750 -> 413750 | AD48: 298000 | AF48: =143750 -> 143750 | AG48: =SUM(C48:AF48) -> 4617625
A49: 1-1211 | B49: Gopay | E49: 222000 | AG49: =SUM(C49:AF49) -> 222000
A50: 2-2110 | B50: Cash Short/Over | C50: =490-0.5 -> 489.5 | D50: =-3-0.13 -> -3.13 | E50: =39294+0.39 -> 39294.39 | F50: =-84512-45-0.15 -> -84557.15 | G50: =-0.581000000238419-2507270 -> -2507270.6 | H50: =-0.865000009536743-3635-820400 -> -824035.87 | I50: =-1.8319999948144+480 -> 478.168 | J50: =142484-506090+0.34 -> -363605.66 | K50: =-2-40-1-0.46 -> -43.46 | L50: =-0.12 -> -0.12 | M50: =-1-43115+0.16 -> -43115.84 | N50: =-1-22862-21290-0.46 -> -44153.46 | O50: =-2-33960-57545+0.15 -> -91506.85 | P50: =-11-2000+0.28 -> -2010.72 | Q50: =374-23582+0.12 -> -23207.88 | T50: =-1-70530+0.3 -> -70530.7 | U50: =-2-1208-5000000+0.01 -> -5001210 | V50: =29735-44830-44830-1327760-327310-13728-0.03 -> -1728723 | W50: =46725-20000+15+0.19 -> 26740.19 | X50: =-2+10+2+2048+0.26 -> 2058.26 | Y50: =90+0.04 -> 90.04 | Z50: =-2+0.04 -> -1.96 | AA50: =19911-70+0.31 -> 19841.31 | AB50: =43275-36880+0.11 -> 6395.11 | AC50: =73232-51615-68370-38945-51615-55700-33960-8075+0.32 -> -235047.68 | AD50: =52745-11770+0.04 -> 40975.04 | AE50: =-0.76+865 -> 864.24 | AF50: =25443.37 -> 25443.37 | AG50: =SUM(C50:AF50) -> -10856354
B51: Total All Payments | C51: =SUM(C32:C50) -> 46277230 | D51: =SUM(D32:D50) -> 48032824 | E51: =SUM(E32:E50) -> 47622323 | F51: =SUM(F32:F50) -> 67606540 | G51: =SUM(G32:G50) -> 1.2938096e+08 | H51: =SUM(H32:H50) -> 1.6956481e+08 | I51: =SUM(I32:I50) -> 39421242 | J51: =SUM(J32:J50) -> 81633683 | ... AG51: =SUM(AG32:AG50) -> 2.3154549e+09
B52: Balancing | C52: =C51-C30 -> -0.0040000007 | D52: =D51-D30 -> -0.0020000041 | E52: =E51-E30 -> 0.0020000041 | F52: =F51-F30 -> 0.0029999912 | G52: =G51-G30 -> 0 | H52: =H51-H30 -> 0 | I52: =I51-I30 -> 0 | J52: =J51-J30 -> 0 | ... AG52: =AG51-AG30 -> -0.025000095
C53: 48000 | D53: 48000 | E53: 22000 | F53: 48000 | G53: 20000 | H53: 20000 | I53: 180000 | J53: 48000 | K53: 65000 | L53: 328000 | M53: 48000 | N53: 43000 | O53: 4000000 | P53: 120000 | Q53: 22000 | R53: 19000 | S53: 20000 | T53: 48000 | U53: 7000000 | V53: 48000 | W53: 48000 | X53: 48000 | Y53: 48000 | Z53: 456000 | AA53: 48000 | AB53: 27000 | AC53: 144000 | AD53: 48000 | AE53: 48000 | AF53: 1387000
C54: 90000 | D54: 23000 | E54: 1036000 | F54: 39600 | G54: 32000 | H54: 36000 | I54: 8000 | J54: 462912 | K54: 27000 | L54: 10000 | M54: 130000 | N54: 48000 | O54: 25000 | P54: 18000 | Q54: 1554000 | R54: 140000 | S54: 282000 | T54: 57000 | U54: 100000 | V54: 264000 | W54: 45000 | X54: 451720 | Y54: 22000 | Z54: 278098 | AA54: 120000 | AB54: 35000 | AC54: 1905000 | AD54: 22000 | AE54: 497970 | AF54: 61800
C55: 120000 | D55: 108000 | E55: 48000 | F55: 168000 | G55: 144000 | H55: 145000 | I55: 48000 | K55: 24000 | L55: 30000 | M55: 25000 | N55: 3000000 | O55: 193000 | P55: 24000 | Q55: 15000 | R55: 48000 | S55: 70000 | T55: 120000 | U55: 90000 | V55: 176000 | W55: 242000 | X55: 1554000 | Y55: 50000 | Z55: 48000 | AA55: 310000 | AB55: 48000 | AC55: 129000 | AD55: 168000 | AE55: 7000 | AF55: 12000
C56: 128000 | D56: 25344 | E56: 90000 | F56: 60000 | G56: 29000 | H56: 24000 | I56: 1387000 | K56: 150000 | L56: 20000 | M56: 22000 | O56: 85000 | P56: 180000 | Q56: 48000 | R56: 22000 | S56: 120000 | T56: 21000 | U56: 61900 | V56: 555430 | W56: 120000 | X56: 43500 | Y56: 22000 | Z56: 33500 | AB56: 45000 | AC56: 48000 | AD56: 13000 | AE56: 15000 | AF56: 5000
D57: 288000 | E57: 32500 | G57: 551604 | H57: 32000 | K57: 60000 | L57: 282000 | M57: 1909000 | O57: 48000 | P57: 22000 | Q57: 54000 | R57: 87000 | S57: 64000 | U57: 48000 | V57: 305000 | X57: 180000 | Y57: 37000 | AB57: 1554000 | AC57: 27000 | AD57: 48000 | AE57: 327000 | AF57: 120000
G58: 48000 | H58: 27000 | L58: 3000000 | M58: 368500 | O58: 32000 | P58: 330000 | R58: 180000 | U58: 22000 | V58: 10000000 | AC58: 55000 | AD58: 60000 | AE58: 60000 | AF58: 48000
G59: 4000000 | H59: 22000 | L59: 150000 | M59: 28000 | O59: 22000 | P59: 26000 | U59: 1387000 | AC59: 707622 | AD59: 37000
G60: 93500 | H60: 48000 | L60: 45500 | M60: 21800 | O60: 23000 | P60: 48000 | U60: 60000
H61: 170267 | L61: 56000 | M61: 71200 | O61: 483066 | P61: 120000
H62: 372000 | L62: 410497 | O62: 5000000 | P62: 52000
H63: 200000 | L63: 23900 | O63: 1451000
H64: 10000000
H65: 1036000
C67: =SUM(C53:C62) -> 386000 | D67: =SUM(D53:D62) -> 492344 | E67: =SUM(E53:E62) -> 1228500 | F67: =SUM(F53:F62) -> 315600 | G67: =SUM(G53:G62) -> 4918104 | H67: =SUM(H53:H66) -> 12132267 | I67: =SUM(I53:I62) -> 1623000 | J67: =SUM(J53:J62) -> 510912 | K67: =SUM(K53:K62) -> 326000 | L67: =SUM(L53:L66) -> 4355897 | M67: =SUM(M53:M66) -> 2623500 | N67: =SUM(N53:N66) -> 3091000 | O67: =SUM(O53:O66) -> 11362066 | P67: =SUM(P53:P66) -> 940000 | Q67: =SUM(Q53:Q66) -> 1693000 | R67: =SUM(R53:R66) -> 496000 | S67: =SUM(S53:S66) -> 556000 | ... AF67: =SUM(AF53:AF66) -> 1633800
C68: =C32-C67 -> 10116700 | D68: =D32-D67 -> 6588836 | E68: =E32-E67 -> 8531827 | F68: =F32-F67 -> 5705830 | G68: =G32-G67 -> 11434186 | H68: =H32-H67 -> 6516195 | I68: =I32-I67 -> 5134477 | J68: =J32-J67 -> 5822624 | ... AF68: =AF32-AF67 -> 9593105 | AG68: =SUM(AE68:AF68) -> 18217417
C70: =-10000000*1 -> -10000000 | T70: =-10000000*1 -> -10000000 | AB70: =-10000000*1 -> -10000000
C71: =-100000*1 -> -100000 | D71: =-100000*61 -> -6100000 | E71: =-100000*75 -> -7500000 | F71: =-100000*57 -> -5700000 | G71: -11000000 | H71: -6000000 | I71: -5000000 | J71: =-100000*58 -> -5800000 | K71: =-100000*65 -> -6500000 | L71: =-100000*41 -> -4100000 | M71: =-100000*48 -> -4800000 | N71: =-100000*52 -> -5200000 | O71: =-100000*95 -> -9500000 | P71: =-100000*70 -> -7000000 | Q71: =-100000*47 -> -4700000 | R71: =-100000*99 -> -9900000 | S71: =-100000*86 -> -8600000 | T71: =-100000*27 -> -2700000 | U71: =-100000*29 -> -2900000 | V71: =-100000*45 -> -4500000 | W71: =-100000*45 -> -4500000 | X71: =-100000*66 -> -6600000 | Y71: =-100000*67 -> -6700000 | Z71: =-100000*92 -> -9200000 | AB71: =-100000*46 -> -4600000 | AC71: =-100000*84 -> -8400000 | AD71: =-100000*48 -> -4800000 | AE71: =-100000*86 -> -8600000 | AF71: =-100000*75 -> -7500000 | AG71: =SUM(AE71:AF71) -> -16100000
D72: =-50000*9 -> -450000 | E72: =-50000*20 -> -1000000 | G72: -400000 | H72: -450000 | I72: -135000 | K72: =-50000*1 -> -50000 | M72: =-50000*1 -> -50000 | N72: =-50000*10 -> -500000 | O72: =-50000*3 -> -150000 | P72: =-50000*1 -> -50000 | Q72: =-50000*21 -> -1050000 | S72: =-50000*1 -> -50000 | V72: =-50000*6 -> -300000 | W72: =-50000*1 -> -50000 | X72: =-50000*1 -> -50000 | Y72: =-50000*31 -> -1550000 | Z72: =-50000*21 -> -1050000 | AB72: =-50000*1 -> -50000 | AF72: =-50000*41 -> -2050000 | AG72: =SUM(AE72:AF72) -> -2050000
D73: =-20000*2 -> -40000 | G73: -35000 | H73: -65000 | J73: =-20000*1 -> -20000 | K73: =-20000*1 -> -20000 | L73: =-20000*3 -> -60000 | M73: =-20000*1 -> -20000 | Q73: =-20000*2 -> -40000 | T73: =-20000*1 -> -20000 | V73: =-20000*3 -> -60000 | W73: =-20000*2 -> -40000 | X73: =-20000*1 -> -20000 | Z73: =-20000*1 -> -20000 | AB73: =-20000*1 -> -20000 | AE73: =-20000*1 -> -20000 | AF73: =-20000*1 -> -20000 | AG73: =SUM(AE73:AF73) -> -40000
C74: =-10000*1 -> -10000 | E74: =-10000*1 -> -10000 | K74: =-10000*1 -> -10000 | M74: =-10000*2 -> -20000 | N74: =-10000*1 -> -10000 | O74: =-10000*3 -> -30000 | P74: =-10000*4 -> -40000 | Q74: =-10000*1 -> -10000 | R74: =-10000*2 -> -20000 | S74: =-10000*2 -> -20000 | T74: =-10000*2 -> -20000 | U74: =-10000*2 -> -20000 | V74: =-10000*1 -> -10000 | W74: =-10000*1 -> -10000 | X74: =-10000*2 -> -20000 | Y74: =-10000*1 -> -10000 | AB74: =-10000*1 -> -10000 | AD74: =-10000*2 -> -20000 | AF74: =-10000*2 -> -20000 | AG74: =SUM(AE74:AF74) -> -20000
E75: =-5000*4 -> -20000 | F75: =-5000*1 -> -5000 | K75: =-5000*1 -> -5000 | N75: =-5000*2 -> -10000 | O75: =-5000*1 -> -5000 | R75: =-5000*1 -> -5000 | S75: =-5000*1 -> -5000 | U75: =-5000*4 -> -20000 | W75: =-5000*1 -> -5000 | Y75: =-5000*4 -> -20000 | Z75: =-5000*2 -> -10000 | AB75: =-5000*1 -> -5000 | AC75: =-5000*1 -> -5000 | AD75: =-5000*1 -> -5000 | AE75: =-5000*1 -> -5000 | AF75: =-5000*1 -> -5000 | AG75: =SUM(AE75:AF75) -> -10000
C76: =-2000*3 -> -6000 | J76: =-2000*2 -> -4000 | K76: =-2000*3 -> -6000 | L76: =-2000*3 -> -6000 | M76: =-2000*2 -> -4000 | N76: =-2000*8 -> -16000 | P76: =-2000*1 -> -2000 | Q76: =-2000*2 -> -4000 | R76: =-2000*1 -> -2000 | U76: =-2000*1 -> -2000 | V76: =-2000*1 -> -2000 | W76: =-2000*3 -> -6000 | X76: =-2000*1 -> -2000 | Y76: =-2000*1 -> -2000 | Z76: =-2000*1 -> -2000 | AD76: =-2000*2 -> -4000
C77: =-1000*1 -> -1000 | E77: =-1000*2 -> -2000 | F77: =-1000*1 -> -1000 | S77: =-1000*1 -> -1000 | AC77: =-1000*1 -> -1000
AA78: -13728333
C79: =SUM(C70:C78) -> -10117000 | D79: =SUM(D70:D78) -> -6590000 | E79: =SUM(E70:E78) -> -8532000 | F79: =SUM(F70:F78) -> -5706000 | G79: =SUM(G70:G78) -> -11435000 | H79: =SUM(H70:H78) -> -6515000 | I79: =SUM(I70:I78) -> -5135000 | J79: =SUM(J70:J78) -> -5824000 | ... AG79: =SUM(AG70:AG78) -> -18220000
C80: =C68+C79 -> -300 | D80: =D68+D79 -> -1164 | E80: =E68+E79 -> -173 | F80: =F68+F79 -> -170 | G80: =G68+G79 -> -814 | H80: =H68+H79 -> 1195 | I80: =I68+I79 -> -523 | J80: =J68+J79 -> -1376 | ... AG80: =AG68+AG79 -> -2583
H81: =-SUM(G79:I79)-5000000 -> 18085000
U83: BCA | X83: MANDIRI | AB83: BRI | AE83: CIMB NIAGA
U84: CC | V84: DEBT | W84: QR | X84: DEBT | Y84: CC | Z84: NPG | AA84: QR | AB84: DEBT | AC84: CC | AD84: QR
V85: 617925 | X85: 82390 | Y85: 3695780 | Z85: 82390 | AA85: 1200540
U86: 564960 | X86: 506110 | Y86: 847440 | Z86: 223630 | AA86: 1144044
Y87: 2082113 | AA87: 1744314
Y88: 1877315 | Z88: 706200
Z89: 117700 | AA89: 353100
X90: 200000 | Y90: 3800000 | Z90: 600000 | AA90: 600000
Y91: 400000 | Z91: 200000 | AA91: 200000
Z92: 800000 | AA92: 200000
Y93: 600000 | AA93: 1600000
X94: 3531000 | AA94: 3060200
Z95: 3531000 | AA95: 141240
AA96: 76505
U104: =SUM(U85:U103) -> 564960 | V104: =SUM(V85:V103) -> 617925 | W104: =SUM(W85:W103) -> 0 | X104: =SUM(X85:X103) -> 4319500 | Y104: =SUM(Y85:Y103) -> 13302648 | Z104: =SUM(Z85:Z103) -> 6260920 | AA104: =SUM(AA85:AA103) -> 10319943 | AB104: =SUM(AB85:AB103) -> 0 | ... AE104: =SUM(AE85:AE103) -> 0
W105: =SUM(U104:W104) -> 1182885 | AA105: =SUM(X104:AA104) -> 34203011 | AD105: =SUM(AB104:AC104) -> 0 | AE105: =AB35 -> 4265320
W106: =AF40 -> 564960 | AA106: =AF36 -> 4319500 | AD106: =Z43 -> 0 | AE106: =AE104-AE105 -> -4265320
W107: =W105-W106 -> 617925 | AA107: =AA105-AA106 -> 29883511

Sheet GL
I1: PT TAMAN BINTANG BALI
I2: GENERAL LEDGER
I3: MONTH OF June 2026
H4: =SUBTOTAL(9,H6:H6119) -> 1.0865818e+10 | I4: =SUBTOTAL(9,I6:I6119) -> 1.0865818e+10 | J4: =H4-I4 -> 0.38249969
B5: DATE | C5: REFF# | E5: ACCT NAME | F5: DESCRIPTION | G5: QTY | H5: TRANSACTION IN RP
E6: =TRIM(VLOOKUP(D6,TB!$B$9:$C$1500,2,FALSE)) -> #N/A | J6: =H6-I6 -> 0
A7: =IF(E7="","",MATCH(E7,'Daily Sales'!B$4:B$51,0)+3) -> 4 | B7: 46174 | C7: DS26-0601 | D7: {=IF($A7="","",INDEX('Daily Sales'!A:A,$A7))} -> 4-2100 | E7: Sales Food TERRACE | F7: =E7 -> Sales Food TERRACE | H7: {=IF($A7="","", IF( OR( $A7=23, AND($A7>=32,$A7<=50) ), IFERROR( INDEX('Daily Sales'!$C:$AG, $A7, MATCH(TEXT($B7,"0"),TEXT('Daily Sales'!$C$2:$AG$2,"0"),0) ), ""), "") )} | I7: {=IF($A7="","", IF( OR( AND($A7>=4,$A7<=8), AND($A7>=12,$A7<=19), AND($A7>=28,$A7<=29) ), IFERROR( INDEX('Daily Sales'!$C:$AG, $A7, MATCH(TEXT($B7,"0"),TEXT('Daily Sales'!$C$2:$AG$2,"0"),0) ), ""), "") )} -> 4945000 | J7: =J6+H7-I7 -> #VALUE!
A8: =IF(E8="","",MATCH(E8,'Daily Sales'!B$4:B$51,0)+3) -> 5 | B8: 46174 | C8: DS26-0601 | D8: {=IF($A8="","",INDEX('Daily Sales'!A:A,$A8))} -> 4-2200 | E8: Sales Beverages TERRACE | F8: =E8 -> Sales Beverages TERRACE | H8: {=IF($A8="","", IF( OR( $A8=23, AND($A8>=32,$A8<=50) ), IFERROR( INDEX('Daily Sales'!$C:$AG, $A8, MATCH(TEXT($B8,"0"),TEXT('Daily Sales'!$C$2:$AG$2,"0"),0) ), ""), "") )} | I8: {=IF($A8="","", IF( OR( AND($A8>=4,$A8<=8), AND($A8>=12,$A8<=19), AND($A8>=28,$A8<=29) ), IFERROR( INDEX('Daily Sales'!$C:$AG, $A8, MATCH(TEXT($B8,"0"),TEXT('Daily Sales'!$C$2:$AG$2,"0"),0) ), ""), "") )} -> 8420000 | J8: =J7+H8-I8 -> #VALUE!
A9: =IF(E9="","",MATCH(E9,'Daily Sales'!B$4:B$51,0)+3) -> 6 | B9: 46174 | C9: DS26-0601 | D9: {=IF($A9="","",INDEX('Daily Sales'!A:A,$A9))} -> 4-2400 | E9: Sales Cigarette TERRACE | F9: =E9 -> Sales Cigarette TERRACE | H9: {=IF($A9="","", IF( OR( $A9=23, AND($A9>=32,$A9<=50) ), IFERROR( INDEX('Daily Sales'!$C:$AG, $A9, MATCH(TEXT($B9,"0"),TEXT('Daily Sales'!$C$2:$AG$2,"0"),0) ), ""), "") )} | I9: {=IF($A9="","", IF( OR( AND($A9>=4,$A9<=8), AND($A9>=12,$A9<=19), AND($A9>=28,$A9<=29) ), IFERROR( INDEX('Daily Sales'!$C:$AG, $A9, MATCH(TEXT($B9,"0"),TEXT('Daily Sales'!$C$2:$AG$2,"0"),0) ), ""), "") )} -> 0 | J9: =J8+H9-I9 -> #VALUE!
A10: =IF(E10="","",MATCH(E10,'Daily Sales'!B$4:B$51,0)+3) -> 7 | B10: 46174 | C10: DS26-0601 | D10: {=IF($A10="","",INDEX('Daily Sales'!A:A,$A10))} -> 4-2300 | E10: Sales Shisa TERRACE | F10: =E10 -> Sales Shisa TERRACE | H10: {=IF($A10="","", IF( OR( $A10=23, AND($A10>=32,$A10<=50) ), IFERROR( INDEX('Daily Sales'!$C:$AG, $A10, MATCH(TEXT($B10,"0"),TEXT('Daily Sales'!$C$2:$AG$2,"0"),0) ), ""), "") )} | I10: {=IF($A10="","", IF( OR( AND($A10>=4,$A10<=8), AND($A10>=12,$A10<=19), AND($A10>=28,$A10<=29) ), IFERROR( INDEX('Daily Sales'!$C:$AG, $A10, MATCH(TEXT($B10,"0"),TEXT('Daily Sales'!$C$2:$AG$2,"0"),0) ), ""), "") )} -> 1500000 | J10: =J9+H10-I10 -> #VALUE!
A11: =IF(E11="","",MATCH(E11,'Daily Sales'!B$4:B$51,0)+3) -> 12 | B11: 46174 | C11: DS26-0601 | D11: {=IF($A11="","",INDEX('Daily Sales'!A:A,$A11))} -> 4-2200 | E11: Sales Beverages CLUB | F11: =E11 -> Sales Beverages CLUB | H11: {=IF($A11="","", IF( OR( $A11=23, AND($A11>=32,$A11<=50) ), IFERROR( INDEX('Daily Sales'!$C:$AG, $A11, MATCH(TEXT($B11,"0"),TEXT('Daily Sales'!$C$2:$AG$2,"0"),0) ), ""), "") )} | I11: {=IF($A11="","", IF( OR( AND($A11>=4,$A11<=8), AND($A11>=12,$A11<=19), AND($A11>=28,$A11<=29) ), IFERROR( INDEX('Daily Sales'!$C:$AG, $A11, MATCH(TEXT($B11,"0"),TEXT('Daily Sales'!$C$2:$AG$2,"0"),0) ), ""), "") )} -> 12575000 | J11: =J10+H11-I11 -> #VALUE!
A12: =IF(E12="","",MATCH(E12,'Daily Sales'!B$4:B$51,0)+3) -> 13 | B12: 46174 | C12: DS26-0601 | D12: {=IF($A12="","",INDEX('Daily Sales'!A:A,$A12))} -> 4-2400 | E12: Sales Cigarette CLUB | F12: =E12 -> Sales Cigarette CLUB | H12: {=IF($A12="","", IF( OR( $A12=23, AND($A12>=32,$A12<=50) ), IFERROR( INDEX('Daily Sales'!$C:$AG, $A12, MATCH(TEXT($B12,"0"),TEXT('Daily Sales'!$C$2:$AG$2,"0"),0) ), ""), "") )} | I12: {=IF($A12="","", IF( OR( AND($A12>=4,$A12<=8), AND($A12>=12,$A12<=19), AND($A12>=28,$A12<=29) ), IFERROR( INDEX('Daily Sales'!$C:$AG, $A12, MATCH(TEXT($B12,"0"),TEXT('Daily Sales'!$C$2:$AG$2,"0"),0) ), ""), "") )} -> 0 | J12: =J11+H12-I12 -> #VALUE!
A13: =IF(E13="","",MATCH(E13,'Daily Sales'!B$4:B$51,0)+3) -> 14 | B13: 46174 | C13: DS26-0601 | D13: {=IF($A13="","",INDEX('Daily Sales'!A:A,$A13))} -> 4-2100 | E13: Sales Food CLUB | F13: =E13 -> Sales Food CLUB | H13: {=IF($A13="","", IF( OR( $A13=23, AND($A13>=32,$A13<=50) ), IFERROR( INDEX('Daily Sales'!$C:$AG, $A13, MATCH(TEXT($B13,"0"),TEXT('Daily Sales'!$C$2:$AG$2,"0"),0) ), ""), "") )} | I13: {=IF($A13="","", IF( OR( AND($A13>=4,$A13<=8), AND($A13>=12,$A13<=19), AND($A13>=28,$A13<=29) ), IFERROR( INDEX('Daily Sales'!$C:$AG, $A13, MATCH(TEXT($B13,"0"),TEXT('Daily Sales'!$C$2:$AG$2,"0"),0) ), ""), "") )} -> 100000 | J13: =J12+H13-I13 -> #VALUE!
A14: =IF(E14="","",MATCH(E14,'Daily Sales'!B$4:B$51,0)+3) -> 15 | B14: 46174 | C14: DS26-0601 | D14: {=IF($A14="","",INDEX('Daily Sales'!A:A,$A14))} -> 4-2300 | E14: Sales Shisa CLUB | F14: =E14 -> Sales Shisa CLUB | H14: {=IF($A14="","", IF( OR( $A14=23, AND($A14>=32,$A14<=50) ), IFERROR( INDEX('Daily Sales'!$C:$AG, $A14, MATCH(TEXT($B14,"0"),TEXT('Daily Sales'!$C$2:$AG$2,"0"),0) ), ""), "") )} | I14: {=IF($A14="","", IF( OR( AND($A14>=4,$A14<=8), AND($A14>=12,$A14<=19), AND($A14>=28,$A14<=29) ), IFERROR( INDEX('Daily Sales'!$C:$AG, $A14, MATCH(TEXT($B14,"0"),TEXT('Daily Sales'!$C$2:$AG$2,"0"),0) ), ""), "") )} -> 0 | J14: =J13+H14-I14 -> #VALUE!
A15: =IF(E15="","",MATCH(E15,'Daily Sales'!B$4:B$51,0)+3) -> 17 | B15: 46174 | C15: DS26-0601 | D15: {=IF($A15="","",INDEX('Daily Sales'!A:A,$A15))} -> 4-2601 | E15: Misc | F15: =E15 -> Misc | H15: {=IF($A15="","", IF( OR( $A15=23, AND($A15>=32,$A15<=50) ), IFERROR( INDEX('Daily Sales'!$C:$AG, $A15, MATCH(TEXT($B15,"0"),TEXT('Daily Sales'!$C$2:$AG$2,"0"),0) ), ""), "") )} | I15: {=IF($A15="","", IF( OR( AND($A15>=4,$A15<=8), AND($A15>=12,$A15<=19), AND($A15>=28,$A15<=29) ), IFERROR( INDEX('Daily Sales'!$C:$AG, $A15, MATCH(TEXT($B15,"0"),TEXT('Daily Sales'!$C$2:$AG$2,"0"),0) ), ""), "") )} -> 0 | J15: =J14+H15-I15 -> #VALUE!
A16: =IF(E16="","",MATCH(E16,'Daily Sales'!B$4:B$51,0)+3) -> 19 | B16: 46174 | C16: DS26-0601 | D16: {=IF($A16="","",INDEX('Daily Sales'!A:A,$A16))} -> 4-2500 | E16: Sales Ticket | F16: =E16 -> Sales Ticket | H16: {=IF($A16="","", IF( OR( $A16=23, AND($A16>=32,$A16<=50) ), IFERROR( INDEX('Daily Sales'!$C:$AG, $A16, MATCH(TEXT($B16,"0"),TEXT('Daily Sales'!$C$2:$AG$2,"0"),0) ), ""), "") )} | I16: {=IF($A16="","", IF( OR( AND($A16>=4,$A16<=8), AND($A16>=12,$A16<=19), AND($A16>=28,$A16<=29) ), IFERROR( INDEX('Daily Sales'!$C:$AG, $A16, MATCH(TEXT($B16,"0"),TEXT('Daily Sales'!$C$2:$AG$2,"0"),0) ), ""), "") )} -> 12404452 | J16: =J15+H16-I16 -> #VALUE!
A17: =IF(E17="","",MATCH(E17,'Daily Sales'!B$4:B$51,0)+3) -> 28 | B17: 46174 | C17: DS26-0601 | D17: {=IF($A17="","",INDEX('Daily Sales'!A:A,$A17))} -> 2-2106 | E17: Service Charges 7% | F17: =E17 -> Service Charges 7% | H17: {=IF($A17="","", IF( OR( $A17=23, AND($A17>=32,$A17<=50) ), IFERROR( INDEX('Daily Sales'!$C:$AG, $A17, MATCH(TEXT($B17,"0"),TEXT('Daily Sales'!$C$2:$AG$2,"0"),0) ), ""), "") )} | I17: {=IF($A17="","", IF( OR( AND($A17>=4,$A17<=8), AND($A17>=12,$A17<=19), AND($A17>=28,$A17<=29) ), IFERROR( INDEX('Daily Sales'!$C:$AG, $A17, MATCH(TEXT($B17,"0"),TEXT('Daily Sales'!$C$2:$AG$2,"0"),0) ), ""), "") )} -> 2752256.6 | J17: =J16+H17-I17 -> #VALUE!
A18: =IF(E18="","",MATCH(E18,'Daily Sales'!B$4:B$51,0)+3) -> 29 | B18: 46174 | C18: DS26-0601 | D18: {=IF($A18="","",INDEX('Daily Sales'!A:A,$A18))} -> 2-3101 | E18: Tax PB1 10% | F18: =E18 -> Tax PB1 10% | H18: {=IF($A18="","", IF( OR( $A18=23, AND($A18>=32,$A18<=50) ), IFERROR( INDEX('Daily Sales'!$C:$AG, $A18, MATCH(TEXT($B18,"0"),TEXT('Daily Sales'!$C$2:$AG$2,"0"),0) ), ""), "") )} | I18: {=IF($A18="","", IF( OR( AND($A18>=4,$A18<=8), AND($A18>=12,$A18<=19), AND($A18>=28,$A18<=29) ), IFERROR( INDEX('Daily Sales'!$C:$AG, $A18, MATCH(TEXT($B18,"0"),TEXT('Daily Sales'!$C$2:$AG$2,"0"),0) ), ""), "") )} -> 4207020.9 | J18: =J17+H18-I18 -> #VALUE!
A19: =IF(E19="","",MATCH(E19,'Daily Sales'!B$4:B$51,0)+3) -> 23 | B19: 46174 | C19: DS26-0601 | D19: {=IF($A19="","",INDEX('Daily Sales'!A:A,$A19))} -> 4-5110 | E19: Discount | F19: =E19 -> Discount | H19: {=IF($A19="","", IF( OR( $A19=23, AND($A19>=32,$A19<=50) ), IFERROR( INDEX('Daily Sales'!$C:$AG, $A19, MATCH(TEXT($B19,"0"),TEXT('Daily Sales'!$C$2:$AG$2,"0"),0) ), ""), "") )} -> 626500 | J19: =J18+H19-I19 -> #VALUE!
A20: =IF(E20="","",MATCH(E20,'Daily Sales'!B$4:B$51,0)+3) -> 32 | B20: 46174 | C20: DS26-0601 | D20: {=IF($A20="","",INDEX('Daily Sales'!A:A,$A20))} -> 1-1119 | E20: Cash IDR | F20: =E20 -> Cash IDR | H20: {=IF($A20="","", IF( OR( $A20=23, AND($A20>=32,$A20<=50) ), IFERROR( INDEX('Daily Sales'!$C:$AG, $A20, MATCH(TEXT($B20,"0"),TEXT('Daily Sales'!$C$2:$AG$2,"0"),0) ), ""), "") )} -> 10502700 | I20: {=IF($A20="","", IF( OR( AND($A20>=4,$A20<=8), AND($A20>=12,$A20<=19), AND($A20>=28,$A20<=29) ), IFERROR( INDEX('Daily Sales'!$C:$AG, $A20, MATCH(TEXT($B20,"0"),TEXT('Daily Sales'!$C$2:$AG$2,"0"),0) ), ""), "") )} | J20: =J19+H20-I20 -> #VALUE!
A21: =IF(E21="","",MATCH(E21,'Daily Sales'!B$4:B$51,0)+3) -> 33 | B21: 46174 | C21: DS26-0601 | D21: {=IF($A21="","",INDEX('Daily Sales'!A:A,$A21))} -> 1-1217 | E21: Bank transfer | F21: =E21 -> Bank transfer | H21: {=IF($A21="","", IF( OR( $A21=23, AND($A21>=32,$A21<=50) ), IFERROR( INDEX('Daily Sales'!$C:$AG, $A21, MATCH(TEXT($B21,"0"),TEXT('Daily Sales'!$C$2:$AG$2,"0"),0) ), ""), "") )} -> 0 | I21: {=IF($A21="","", IF( OR( AND($A21>=4,$A21<=8), AND($A21>=12,$A21<=19), AND($A21>=28,$A21<=29) ), IFERROR( INDEX('Daily Sales'!$C:$AG, $A21, MATCH(TEXT($B21,"0"),TEXT('Daily Sales'!$C$2:$AG$2,"0"),0) ), ""), "") )} | J21: =J20+H21-I21 -> #VALUE!
A22: =IF(E22="","",MATCH(E22,'Daily Sales'!B$4:B$51,0)+3) -> 35 | B22: 46174 | C22: DS26-0601 | D22: {=IF($A22="","",INDEX('Daily Sales'!A:A,$A22))} -> 1-1216 | E22: Cim Niaga TBB | F22: =E22 -> Cim Niaga TBB | H22: {=IF($A22="","", IF( OR( $A22=23, AND($A22>=32,$A22<=50) ), IFERROR( INDEX('Daily Sales'!$C:$AG, $A22, MATCH(TEXT($B22,"0"),TEXT('Daily Sales'!$C$2:$AG$2,"0"),0) ), ""), "") )} -> 0 | I22: {=IF($A22="","", IF( OR( AND($A22>=4,$A22<=8), AND($A22>=12,$A22<=19), AND($A22>=28,$A22<=29) ), IFERROR( INDEX('Daily Sales'!$C:$AG, $A22, MATCH(TEXT($B22,"0"),TEXT('Daily Sales'!$C$2:$AG$2,"0"),0) ), ""), "") )} | J22: =J21+H22-I22 -> #VALUE!
A23: =IF(E23="","",MATCH(E23,'Daily Sales'!B$4:B$51,0)+3) -> 36 | B23: 46174 | C23: DS26-0601 | D23: {=IF($A23="","",INDEX('Daily Sales'!A:A,$A23))} -> 1-1213 | E23: Mandiri Debet | F23: =E23 -> Mandiri Debet | H23: {=IF($A23="","", IF( OR( $A23=23, AND($A23>=32,$A23<=50) ), IFERROR( INDEX('Daily Sales'!$C:$AG, $A23, MATCH(TEXT($B23,"0"),TEXT('Daily Sales'!$C$2:$AG$2,"0"),0) ), ""), "") )} -> 258490 | I23: {=IF($A23="","", IF( OR( AND($A23>=4,$A23<=8), AND($A23>=12,$A23<=19), AND($A23>=28,$A23<=29) ), IFERROR( INDEX('Daily Sales'!$C:$AG, $A23, MATCH(TEXT($B23,"0"),TEXT('Daily Sales'!$C$2:$AG$2,"0"),0) ), ""), "") )} | J23: =J22+H23-I23 -> #VALUE!
A24: =IF(E24="","",MATCH(E24,'Daily Sales'!B$4:B$51,0)+3) -> 37 | B24: 46174 | C24: DS26-0601 | D24: {=IF($A24="","",INDEX('Daily Sales'!A:A,$A24))} -> 1-1213 | E24: Mandiri CC | F24: =E24 -> Mandiri CC | H24: {=IF($A24="","", IF( OR( $A24=23, AND($A24>=32,$A24<=50) ), IFERROR( INDEX('Daily Sales'!$C:$AG, $A24, MATCH(TEXT($B24,"0"),TEXT('Daily Sales'!$C$2:$AG$2,"0"),0) ), ""), "") )} -> 24448395 | I24: {=IF($A24="","", IF( OR( AND($A24>=4,$A24<=8), AND($A24>=12,$A24<=19), AND($A24>=28,$A24<=29) ), IFERROR( INDEX('Daily Sales'!$C:$AG, $A24, MATCH(TEXT($B24,"0"),TEXT('Daily Sales'!$C$2:$AG$2,"0"),0) ), ""), "") )} | J24: =J23+H24-I24 -> #VALUE!
A25: =IF(E25="","",MATCH(E25,'Daily Sales'!B$4:B$51,0)+3) -> 38 | B25: 46174 | C25: DS26-0601 | D25: {=IF($A25="","",INDEX('Daily Sales'!A:A,$A25))} -> 1-1213 | E25: Mandiri NPG | F25: =E25 -> Mandiri NPG | H25: {=IF($A25="","", IF( OR( $A25=23, AND($A25>=32,$A25<=50) ), IFERROR( INDEX('Daily Sales'!$C:$AG, $A25, MATCH(TEXT($B25,"0"),TEXT('Daily Sales'!$C$2:$AG$2,"0"),0) ), ""), "") )} -> 1435490 | I25: {=IF($A25="","", IF( OR( AND($A25>=4,$A25<=8), AND($A25>=12,$A25<=19), AND($A25>=28,$A25<=29) ), IFERROR( INDEX('Daily Sales'!$C:$AG, $A25, MATCH(TEXT($B25,"0"),TEXT('Daily Sales'!$C$2:$AG$2,"0"),0) ), ""), "") )} | J25: =J24+H25-I25 -> #VALUE!
A26: =IF(E26="","",MATCH(E26,'Daily Sales'!B$4:B$51,0)+3) -> 39 | B26: 46174 | C26: DS26-0601 | D26: {=IF($A26="","",INDEX('Daily Sales'!A:A,$A26))} -> 1-1213 | E26: Mandiri QR | F26: =E26 -> Mandiri QR | H26: {=IF($A26="","", IF( OR( $A26=23, AND($A26>=32,$A26<=50) ), IFERROR( INDEX('Daily Sales'!$C:$AG, $A26, MATCH(TEXT($B26,"0"),TEXT('Daily Sales'!$C$2:$AG$2,"0"),0) ), ""), "") )} -> 2350833 | I26: {=IF($A26="","", IF( OR( AND($A26>=4,$A26<=8), AND($A26>=12,$A26<=19), AND($A26>=28,$A26<=29) ), IFERROR( INDEX('Daily Sales'!$C:$AG, $A26, MATCH(TEXT($B26,"0"),TEXT('Daily Sales'!$C$2:$AG$2,"0"),0) ), ""), "") )} | J26: =J25+H26-I26 -> #VALUE!
A27: =IF(E27="","",MATCH(E27,'Daily Sales'!B$4:B$51,0)+3) -> 40 | B27: 46174 | C27: DS26-0601 | D27: {=IF($A27="","",INDEX('Daily Sales'!A:A,$A27))} -> 1-1217 | E27: BCA CC | F27: =E27 -> BCA CC | H27: {=IF($A27="","", IF( OR( $A27=23, AND($A27>=32,$A27<=50) ), IFERROR( INDEX('Daily Sales'!$C:$AG, $A27, MATCH(TEXT($B27,"0"),TEXT('Daily Sales'!$C$2:$AG$2,"0"),0) ), ""), "") )} -> 6579340 | I27: {=IF($A27="","", IF( OR( AND($A27>=4,$A27<=8), AND($A27>=12,$A27<=19), AND($A27>=28,$A27<=29) ), IFERROR( INDEX('Daily Sales'!$C:$AG, $A27, MATCH(TEXT($B27,"0"),TEXT('Daily Sales'!$C$2:$AG$2,"0"),0) ), ""), "") )} | J27: =J26+H27-I27 -> #VALUE!
A28: =IF(E28="","",MATCH(E28,'Daily Sales'!B$4:B$51,0)+3) -> 41 | B28: 46174 | C28: DS26-0601 | D28: {=IF($A28="","",INDEX('Daily Sales'!A:A,$A28))} -> 1-1217 | E28: BCA debt | F28: =E28 -> BCA debt | H28: {=IF($A28="","", IF( OR( $A28=23, AND($A28>=32,$A28<=50) ), IFERROR( INDEX('Daily Sales'!$C:$AG, $A28, MATCH(TEXT($B28,"0"),TEXT('Daily Sales'!$C$2:$AG$2,"0"),0) ), ""), "") )} -> 164780 | I28: {=IF($A28="","", IF( OR( AND($A28>=4,$A28<=8), AND($A28>=12,$A28<=19), AND($A28>=28,$A28<=29) ), IFERROR( INDEX('Daily Sales'!$C:$AG, $A28, MATCH(TEXT($B28,"0"),TEXT('Daily Sales'!$C$2:$AG$2,"0"),0) ), ""), "") )} | J28: =J27+H28-I28 -> #VALUE!
A29: =IF(E29="","",MATCH(E29,'Daily Sales'!B$4:B$51,0)+3) -> 42 | B29: 46174 | C29: DS26-0601 | D29: {=IF($A29="","",INDEX('Daily Sales'!A:A,$A29))} -> 1-1217 | E29: BCA QR | F29: =E29 -> BCA QR | H29: {=IF($A29="","", IF( OR( $A29=23, AND($A29>=32,$A29<=50) ), IFERROR( INDEX('Daily Sales'!$C:$AG, $A29, MATCH(TEXT($B29,"0"),TEXT('Daily Sales'!$C$2:$AG$2,"0"),0) ), ""), "") )} -> 294250 | I29: {=IF($A29="","", IF( OR( AND($A29>=4,$A29<=8), AND($A29>=12,$A29<=19), AND($A29>=28,$A29<=29) ), IFERROR( INDEX('Daily Sales'!$C:$AG, $A29, MATCH(TEXT($B29,"0"),TEXT('Daily Sales'!$C$2:$AG$2,"0"),0) ), ""), "") )} | J29: =J28+H29-I29 -> #VALUE!
A30: =IF(E30="","",MATCH(E30,'Daily Sales'!B$4:B$51,0)+3) -> 43 | B30: 46174 | C30: DS26-0601 | D30: {=IF($A30="","",INDEX('Daily Sales'!A:A,$A30))} -> 1-1214 | E30: Bank BRI DEBET | F30: =E30 -> Bank BRI DEBET | H30: {=IF($A30="","", IF( OR( $A30=23, AND($A30>=32,$A30<=50) ), IFERROR( INDEX('Daily Sales'!$C:$AG, $A30, MATCH(TEXT($B30,"0"),TEXT('Daily Sales'!$C$2:$AG$2,"0"),0) ), ""), "") )} -> 0 | I30: {=IF($A30="","", IF( OR( AND($A30>=4,$A30<=8), AND($A30>=12,$A30<=19), AND($A30>=28,$A30<=29) ), IFERROR( INDEX('Daily Sales'!$C:$AG, $A30, MATCH(TEXT($B30,"0"),TEXT('Daily Sales'!$C$2:$AG$2,"0"),0) ), ""), "") )} | J30: =J29+H30-I30 -> #VALUE!
A31: =IF(E31="","",MATCH(E31,'Daily Sales'!B$4:B$51,0)+3) -> 44 | B31: 46174 | C31: DS26-0601 | D31: {=IF($A31="","",INDEX('Daily Sales'!A:A,$A31))} -> 1-1214 | E31: Bank BRI CC | F31: =E31 -> Bank BRI CC | H31: {=IF($A31="","", IF( OR( $A31=23, AND($A31>=32,$A31<=50) ), IFERROR( INDEX('Daily Sales'!$C:$AG, $A31, MATCH(TEXT($B31,"0"),TEXT('Daily Sales'!$C$2:$AG$2,"0"),0) ), ""), "") )} -> 0 | I31: {=IF($A31="","", IF( OR( AND($A31>=4,$A31<=8), AND($A31>=12,$A31<=19), AND($A31>=28,$A31<=29) ), IFERROR( INDEX('Daily Sales'!$C:$AG, $A31, MATCH(TEXT($B31,"0"),TEXT('Daily Sales'!$C$2:$AG$2,"0"),0) ), ""), "") )} | J31: =J30+H31-I31 -> #VALUE!
... A37: =IF(E37="","",MATCH(E37,'Daily Sales'!B$4:B$51,0)+3) -> 50 | B37: 46174 | C37: DS26-0601 | D37: {=IF($A37="","",INDEX('Daily Sales'!A:A,$A37))} -> 2-2110 | E37: Cash Short/Over | F37: =E37 -> Cash Short/Over | H37: {=IF($A37="","", IF( OR( $A37=23, AND($A37>=32,$A37<=50) ), IFERROR( INDEX('Daily Sales'!$C:$AG, $A37, MATCH(TEXT($B37,"0"),TEXT('Daily Sales'!$C$2:$AG$2,"0"),0) ), ""), "") )} -> 489.5 | I37: {=IF($A37="","", IF( OR( AND($A37>=4,$A37<=8), AND($A37>=12,$A37<=19), AND($A37>=28,$A37<=29) ), IFERROR( INDEX('Daily Sales'!$C:$AG, $A37, MATCH(TEXT($B37,"0"),TEXT('Daily Sales'!$C$2:$AG$2,"0"),0) ), ""), "") )} | J37: =J36+H37-I37 -> #VALUE!
A38: =IF(E38="","",MATCH(E38,'Daily Sales'!B$4:B$51,0)+3) | D38: {=IF($A38="","",INDEX('Daily Sales'!A:A,$A38))} | F38: =E38 -> 0 | H38: {=IF($A38="","", IF( OR( $A38=23, AND($A38>=32,$A38<=50) ), IFERROR( INDEX('Daily Sales'!$C:$AG, $A38, MATCH(TEXT($B38,"0"),TEXT('Daily Sales'!$C$2:$AG$2,"0"),0) ), ""), "") )} | I38: {=IF($A38="","", IF( OR( AND($A38>=4,$A38<=8), AND($A38>=12,$A38<=19), AND($A38>=28,$A38<=29) ), IFERROR( INDEX('Daily Sales'!$C:$AG, $A38, MATCH(TEXT($B38,"0"),TEXT('Daily Sales'!$C$2:$AG$2,"0"),0) ), ""), "") )} | J38: =J37+H38-I38 -> #VALUE!
A39: =IF(E39="","",MATCH(E39,'Daily Sales'!B$4:B$51,0)+3) -> 4 | B39: 46175 | C39: DS26-0602 | D39: {=IF($A39="","",INDEX('Daily Sales'!A:A,$A39))} -> 4-2100 | E39: Sales Food TERRACE | F39: =E39 -> Sales Food TERRACE | H39: {=IF($A39="","", IF( OR( $A39=23, AND($A39>=32,$A39<=50) ), IFERROR( INDEX('Daily Sales'!$C:$AG, $A39, MATCH(TEXT($B39,"0"),TEXT('Daily Sales'!$C$2:$AG$2,"0"),0) ), ""), "") )} | I39: {=IF($A39="","", IF( OR( AND($A39>=4,$A39<=8), AND($A39>=12,$A39<=19), AND($A39>=28,$A39<=29) ), IFERROR( INDEX('Daily Sales'!$C:$AG, $A39, MATCH(TEXT($B39,"0"),TEXT('Daily Sales'!$C$2:$AG$2,"0"),0) ), ""), "") )} -> 3590000 | J39: =J38+H39-I39 -> #VALUE!
A40: =IF(E40="","",MATCH(E40,'Daily Sales'!B$4:B$51,0)+3) -> 5 | B40: 46175 | C40: DS26-0602 | D40: {=IF($A40="","",INDEX('Daily Sales'!A:A,$A40))} -> 4-2200 | E40: Sales Beverages TERRACE | F40: =E40 -> Sales Beverages TERRACE | H40: {=IF($A40="","", IF( OR( $A40=23, AND($A40>=32,$A40<=50) ), IFERROR( INDEX('Daily Sales'!$C:$AG, $A40, MATCH(TEXT($B40,"0"),TEXT('Daily Sales'!$C$2:$AG$2,"0"),0) ), ""), "") )} | I40: {=IF($A40="","", IF( OR( AND($A40>=4,$A40<=8), AND($A40>=12,$A40<=19), AND($A40>=28,$A40<=29) ), IFERROR( INDEX('Daily Sales'!$C:$AG, $A40, MATCH(TEXT($B40,"0"),TEXT('Daily Sales'!$C$2:$AG$2,"0"),0) ), ""), "") )} -> 2740000 | J40: =J39+H40-I40 -> #VALUE!
A41: =IF(E41="","",MATCH(E41,'Daily Sales'!B$4:B$51,0)+3) -> 6 | B41: 46175 | C41: DS26-0602 | D41: {=IF($A41="","",INDEX('Daily Sales'!A:A,$A41))} -> 4-2400 | E41: Sales Cigarette TERRACE | F41: =E41 -> Sales Cigarette TERRACE | H41: {=IF($A41="","", IF( OR( $A41=23, AND($A41>=32,$A41<=50) ), IFERROR( INDEX('Daily Sales'!$C:$AG, $A41, MATCH(TEXT($B41,"0"),TEXT('Daily Sales'!$C$2:$AG$2,"0"),0) ), ""), "") )} | I41: {=IF($A41="","", IF( OR( AND($A41>=4,$A41<=8), AND($A41>=12,$A41<=19), AND($A41>=28,$A41<=29) ), IFERROR( INDEX('Daily Sales'!$C:$AG, $A41, MATCH(TEXT($B41,"0"),TEXT('Daily Sales'!$C$2:$AG$2,"0"),0) ), ""), "") )} -> 0 | J41: =J40+H41-I41 -> #VALUE!
A42: =IF(E42="","",MATCH(E42,'Daily Sales'!B$4:B$51,0)+3) -> 7 | B42: 46175 | C42: DS26-0602 | D42: {=IF($A42="","",INDEX('Daily Sales'!A:A,$A42))} -> 4-2300 | E42: Sales Shisa TERRACE | F42: =E42 -> Sales Shisa TERRACE | H42: {=IF($A42="","", IF( OR( $A42=23, AND($A42>=32,$A42<=50) ), IFERROR( INDEX('Daily Sales'!$C:$AG, $A42, MATCH(TEXT($B42,"0"),TEXT('Daily Sales'!$C$2:$AG$2,"0"),0) ), ""), "") )} | I42: {=IF($A42="","", IF( OR( AND($A42>=4,$A42<=8), AND($A42>=12,$A42<=19), AND($A42>=28,$A42<=29) ), IFERROR( INDEX('Daily Sales'!$C:$AG, $A42, MATCH(TEXT($B42,"0"),TEXT('Daily Sales'!$C$2:$AG$2,"0"),0) ), ""), "") )} -> 0 | J42: =J41+H42-I42 -> #VALUE!
A43: =IF(E43="","",MATCH(E43,'Daily Sales'!B$4:B$51,0)+3) -> 12 | B43: 46175 | C43: DS26-0602 | D43: {=IF($A43="","",INDEX('Daily Sales'!A:A,$A43))} -> 4-2200 | E43: Sales Beverages CLUB | F43: =E43 -> Sales Beverages CLUB | H43: {=IF($A43="","", IF( OR( $A43=23, AND($A43>=32,$A43<=50) ), IFERROR( INDEX('Daily Sales'!$C:$AG, $A43, MATCH(TEXT($B43,"0"),TEXT('Daily Sales'!$C$2:$AG$2,"0"),0) ), ""), "") )} | I43: {=IF($A43="","", IF( OR( AND($A43>=4,$A43<=8), AND($A43>=12,$A43<=19), AND($A43>=28,$A43<=29) ), IFERROR( INDEX('Daily Sales'!$C:$AG, $A43, MATCH(TEXT($B43,"0"),TEXT('Daily Sales'!$C$2:$AG$2,"0"),0) ), ""), "") )} -> 27335000 | J43: =J42+H43-I43 -> #VALUE!
A44: =IF(E44="","",MATCH(E44,'Daily Sales'!B$4:B$51,0)+3) -> 13 | B44: 46175 | C44: DS26-0602 | D44: {=IF($A44="","",INDEX('Daily Sales'!A:A,$A44))} -> 4-2400 | E44: Sales Cigarette CLUB | F44: =E44 -> Sales Cigarette CLUB | H44: {=IF($A44="","", IF( OR( $A44=23, AND($A44>=32,$A44<=50) ), IFERROR( INDEX('Daily Sales'!$C:$AG, $A44, MATCH(TEXT($B44,"0"),TEXT('Daily Sales'!$C$2:$AG$2,"0"),0) ), ""), "") )} | I44: {=IF($A44="","", IF( OR( AND($A44>=4,$A44<=8), AND($A44>=12,$A44<=19), AND($A44>=28,$A44<=29) ), IFERROR( INDEX('Daily Sales'!$C:$AG, $A44, MATCH(TEXT($B44,"0"),TEXT('Daily Sales'!$C$2:$AG$2,"0"),0) ), ""), "") )} -> 820000 | J44: =J43+H44-I44 -> #VALUE!
A45: =IF(E45="","",MATCH(E45,'Daily Sales'!B$4:B$51,0)+3) -> 14 | B45: 46175 | C45: DS26-0602 | D45: {=IF($A45="","",INDEX('Daily Sales'!A:A,$A45))} -> 4-2100 | E45: Sales Food CLUB | F45: =E45 -> Sales Food CLUB | H45: {=IF($A45="","", IF( OR( $A45=23, AND($A45>=32,$A45<=50) ), IFERROR( INDEX('Daily Sales'!$C:$AG, $A45, MATCH(TEXT($B45,"0"),TEXT('Daily Sales'!$C$2:$AG$2,"0"),0) ), ""), "") )} | I45: {=IF($A45="","", IF( OR( AND($A45>=4,$A45<=8), AND($A45>=12,$A45<=19), AND($A45>=28,$A45<=29) ), IFERROR( INDEX('Daily Sales'!$C:$AG, $A45, MATCH(TEXT($B45,"0"),TEXT('Daily Sales'!$C$2:$AG$2,"0"),0) ), ""), "") )} -> 350000 | J45: =J44+H45-I45 -> #VALUE!
A46: =IF(E46="","",MATCH(E46,'Daily Sales'!B$4:B$51,0)+3) -> 15 | B46: 46175 | C46: DS26-0602 | D46: {=IF($A46="","",INDEX('Daily Sales'!A:A,$A46))} -> 4-2300 | E46: Sales Shisa CLUB | F46: =E46 -> Sales Shisa CLUB | H46: {=IF($A46="","", IF( OR( $A46=23, AND($A46>=32,$A46<=50) ), IFERROR( INDEX('Daily Sales'!$C:$AG, $A46, MATCH(TEXT($B46,"0"),TEXT('Daily Sales'!$C$2:$AG$2,"0"),0) ), ""), "") )} | I46: {=IF($A46="","", IF( OR( AND($A46>=4,$A46<=8), AND($A46>=12,$A46<=19), AND($A46>=28,$A46<=29) ), IFERROR( INDEX('Daily Sales'!$C:$AG, $A46, MATCH(TEXT($B46,"0"),TEXT('Daily Sales'!$C$2:$AG$2,"0"),0) ), ""), "") )} -> 250000 | J46: =J45+H46-I46 -> #VALUE!
A47: =IF(E47="","",MATCH(E47,'Daily Sales'!B$4:B$51,0)+3) -> 17 | B47: 46175 | C47: DS26-0602 | D47: {=IF($A47="","",INDEX('Daily Sales'!A:A,$A47))} -> 4-2601 | E47: Misc | F47: =E47 -> Misc | H47: {=IF($A47="","", IF( OR( $A47=23, AND($A47>=32,$A47<=50) ), IFERROR( INDEX('Daily Sales'!$C:$AG, $A47, MATCH(TEXT($B47,"0"),TEXT('Daily Sales'!$C$2:$AG$2,"0"),0) ), ""), "") )} | I47: {=IF($A47="","", IF( OR( AND($A47>=4,$A47<=8), AND($A47>=12,$A47<=19), AND($A47>=28,$A47<=29) ), IFERROR( INDEX('Daily Sales'!$C:$AG, $A47, MATCH(TEXT($B47,"0"),TEXT('Daily Sales'!$C$2:$AG$2,"0"),0) ), ""), "") )} -> 0 | J47: =J46+H47-I47 -> #VALUE!
A48: =IF(E48="","",MATCH(E48,'Daily Sales'!B$4:B$51,0)+3) -> 19 | B48: 46175 | C48: DS26-0602 | D48: {=IF($A48="","",INDEX('Daily Sales'!A:A,$A48))} -> 4-2500 | E48: Sales Ticket | F48: =E48 -> Sales Ticket | H48: {=IF($A48="","", IF( OR( $A48=23, AND($A48>=32,$A48<=50) ), IFERROR( INDEX('Daily Sales'!$C:$AG, $A48, MATCH(TEXT($B48,"0"),TEXT('Daily Sales'!$C$2:$AG$2,"0"),0) ), ""), "") )} | I48: {=IF($A48="","", IF( OR( AND($A48>=4,$A48<=8), AND($A48>=12,$A48<=19), AND($A48>=28,$A48<=29) ), IFERROR( INDEX('Daily Sales'!$C:$AG, $A48, MATCH(TEXT($B48,"0"),TEXT('Daily Sales'!$C$2:$AG$2,"0"),0) ), ""), "") )} -> 6627036 | J48: =J47+H48-I48 -> #VALUE!
A49: =IF(E49="","",MATCH(E49,'Daily Sales'!B$4:B$51,0)+3) -> 28 | B49: 46175 | C49: DS26-0602 | D49: {=IF($A49="","",INDEX('Daily Sales'!A:A,$A49))} -> 2-2106 | E49: Service Charges 7% | F49: =E49 -> Service Charges 7% | H49: {=IF($A49="","", IF( OR( $A49=23, AND($A49>=32,$A49<=50) ), IFERROR( INDEX('Daily Sales'!$C:$AG, $A49, MATCH(TEXT($B49,"0"),TEXT('Daily Sales'!$C$2:$AG$2,"0"),0) ), ""), "") )} | I49: {=IF($A49="","", IF( OR( AND($A49>=4,$A49<=8), AND($A49>=12,$A49<=19), AND($A49>=28,$A49<=29) ), IFERROR( INDEX('Daily Sales'!$C:$AG, $A49, MATCH(TEXT($B49,"0"),TEXT('Daily Sales'!$C$2:$AG$2,"0"),0) ), ""), "") )} -> 2856667.5 | J49: =J48+H49-I49 -> #VALUE!
A50: =IF(E50="","",MATCH(E50,'Daily Sales'!B$4:B$51,0)+3) -> 29 | B50: 46175 | C50: DS26-0602 | D50: {=IF($A50="","",INDEX('Daily Sales'!A:A,$A50))} -> 2-3101 | E50: Tax PB1 10% | F50: =E50 -> Tax PB1 10% | H50: {=IF($A50="","", IF( OR( $A50=23, AND($A50>=32,$A50<=50) ), IFERROR( INDEX('Daily Sales'!$C:$AG, $A50, MATCH(TEXT($B50,"0"),TEXT('Daily Sales'!$C$2:$AG$2,"0"),0) ), ""), "") )} | I50: {=IF($A50="","", IF( OR( AND($A50>=4,$A50<=8), AND($A50>=12,$A50<=19), AND($A50>=28,$A50<=29) ), IFERROR( INDEX('Daily Sales'!$C:$AG, $A50, MATCH(TEXT($B50,"0"),TEXT('Daily Sales'!$C$2:$AG$2,"0"),0) ), ""), "") )} -> 4366620.4 | J50: =J49+H50-I50 -> #VALUE!
... A69: =IF(E69="","",MATCH(E69,'Daily Sales'!B$4:B$51,0)+3) -> 50 | B69: 46175 | C69: DS26-0602 | D69: {=IF($A69="","",INDEX('Daily Sales'!A:A,$A69))} -> 2-2110 | E69: Cash Short/Over | F69: =E69 -> Cash Short/Over | H69: {=IF($A69="","", IF( OR( $A69=23, AND($A69>=32,$A69<=50) ), IFERROR( INDEX('Daily Sales'!$C:$AG, $A69, MATCH(TEXT($B69,"0"),TEXT('Daily Sales'!$C$2:$AG$2,"0"),0) ), ""), "") )} -> -3.13 | I69: {=IF($A69="","", IF( OR( AND($A69>=4,$A69<=8), AND($A69>=12,$A69<=19), AND($A69>=28,$A69<=29) ), IFERROR( INDEX('Daily Sales'!$C:$AG, $A69, MATCH(TEXT($B69,"0"),TEXT('Daily Sales'!$C$2:$AG$2,"0"),0) ), ""), "") )} | J69: =J68+H69-I69 -> #VALUE!
A70: =IF(E70="","",MATCH(E70,'Daily Sales'!B$4:B$51,0)+3) | F70: =E70 -> 0 | H70: {=IF($A70="","", IF( OR( $A70=23, AND($A70>=32,$A70<=50) ), IFERROR( INDEX('Daily Sales'!$C:$AG, $A70, MATCH(TEXT($B70,"0"),TEXT('Daily Sales'!$C$2:$AG$2,"0"),0) ), ""), "") )} | I70: {=IF($A70="","", IF( OR( AND($A70>=4,$A70<=8), AND($A70>=12,$A70<=19), AND($A70>=28,$A70<=29) ), IFERROR( INDEX('Daily Sales'!$C:$AG, $A70, MATCH(TEXT($B70,"0"),TEXT('Daily Sales'!$C$2:$AG$2,"0"),0) ), ""), "") )} | J70: =J69+H70-I70 -> #VALUE!
A71: =IF(E71="","",MATCH(E71,'Daily Sales'!B$4:B$51,0)+3) -> 4 | B71: 46176 | C71: DS26-0603 | D71: {=IF($A71="","",INDEX('Daily Sales'!A:A,$A71))} -> 4-2100 | E71: Sales Food TERRACE | F71: =E71 -> Sales Food TERRACE | H71: {=IF($A71="","", IF( OR( $A71=23, AND($A71>=32,$A71<=50) ), IFERROR( INDEX('Daily Sales'!$C:$AG, $A71, MATCH(TEXT($B71,"0"),TEXT('Daily Sales'!$C$2:$AG$2,"0"),0) ), ""), "") )} | I71: {=IF($A71="","", IF( OR( AND($A71>=4,$A71<=8), AND($A71>=12,$A71<=19), AND($A71>=28,$A71<=29) ), IFERROR( INDEX('Daily Sales'!$C:$AG, $A71, MATCH(TEXT($B71,"0"),TEXT('Daily Sales'!$C$2:$AG$2,"0"),0) ), ""), "") )} -> 4209000 | J71: =J70+H71-I71 -> #VALUE!
A72: =IF(E72="","",MATCH(E72,'Daily Sales'!B$4:B$51,0)+3) -> 5 | B72: 46176 | C72: DS26-0603 | D72: {=IF($A72="","",INDEX('Daily Sales'!A:A,$A72))} -> 4-2200 | E72: Sales Beverages TERRACE | F72: =E72 -> Sales Beverages TERRACE | H72: {=IF($A72="","", IF( OR( $A72=23, AND($A72>=32,$A72<=50) ), IFERROR( INDEX('Daily Sales'!$C:$AG, $A72, MATCH(TEXT($B72,"0"),TEXT('Daily Sales'!$C$2:$AG$2,"0"),0) ), ""), "") )} | I72: {=IF($A72="","", IF( OR( AND($A72>=4,$A72<=8), AND($A72>=12,$A72<=19), AND($A72>=28,$A72<=29) ), IFERROR( INDEX('Daily Sales'!$C:$AG, $A72, MATCH(TEXT($B72,"0"),TEXT('Daily Sales'!$C$2:$AG$2,"0"),0) ), ""), "") )} -> 7993000 | J72: =J71+H72-I72 -> #VALUE!
A73: =IF(E73="","",MATCH(E73,'Daily Sales'!B$4:B$51,0)+3) -> 6 | B73: 46176 | C73: DS26-0603 | D73: {=IF($A73="","",INDEX('Daily Sales'!A:A,$A73))} -> 4-2400 | E73: Sales Cigarette TERRACE | F73: =E73 -> Sales Cigarette TERRACE | H73: {=IF($A73="","", IF( OR( $A73=23, AND($A73>=32,$A73<=50) ), IFERROR( INDEX('Daily Sales'!$C:$AG, $A73, MATCH(TEXT($B73,"0"),TEXT('Daily Sales'!$C$2:$AG$2,"0"),0) ), ""), "") )} | I73: {=IF($A73="","", IF( OR( AND($A73>=4,$A73<=8), AND($A73>=12,$A73<=19), AND($A73>=28,$A73<=29) ), IFERROR( INDEX('Daily Sales'!$C:$AG, $A73, MATCH(TEXT($B73,"0"),TEXT('Daily Sales'!$C$2:$AG$2,"0"),0) ), ""), "") )} -> 259000 | J73: =J72+H73-I73 -> #VALUE!
A74: =IF(E74="","",MATCH(E74,'Daily Sales'!B$4:B$51,0)+3) -> 7 | B74: 46176 | C74: DS26-0603 | D74: {=IF($A74="","",INDEX('Daily Sales'!A:A,$A74))} -> 4-2300 | E74: Sales Shisa TERRACE | F74: =E74 -> Sales Shisa TERRACE | H74: {=IF($A74="","", IF( OR( $A74=23, AND($A74>=32,$A74<=50) ), IFERROR( INDEX('Daily Sales'!$C:$AG, $A74, MATCH(TEXT($B74,"0"),TEXT('Daily Sales'!$C$2:$AG$2,"0"),0) ), ""), "") )} | I74: {=IF($A74="","", IF( OR( AND($A74>=4,$A74<=8), AND($A74>=12,$A74<=19), AND($A74>=28,$A74<=29) ), IFERROR( INDEX('Daily Sales'!$C:$AG, $A74, MATCH(TEXT($B74,"0"),TEXT('Daily Sales'!$C$2:$AG$2,"0"),0) ), ""), "") )} -> 500000 | J74: =J73+H74-I74 -> #VALUE!
A75: =IF(E75="","",MATCH(E75,'Daily Sales'!B$4:B$51,0)+3) -> 12 | B75: 46176 | C75: DS26-0603 | D75: {=IF($A75="","",INDEX('Daily Sales'!A:A,$A75))} -> 4-2200 | E75: Sales Beverages CLUB | F75: =E75 -> Sales Beverages CLUB | H75: {=IF($A75="","", IF( OR( $A75=23, AND($A75>=32,$A75<=50) ), IFERROR( INDEX('Daily Sales'!$C:$AG, $A75, MATCH(TEXT($B75,"0"),TEXT('Daily Sales'!$C$2:$AG$2,"0"),0) ), ""), "") )} | I75: {=IF($A75="","", IF( OR( AND($A75>=4,$A75<=8), AND($A75>=12,$A75<=19), AND($A75>=28,$A75<=29) ), IFERROR( INDEX('Daily Sales'!$C:$AG, $A75, MATCH(TEXT($B75,"0"),TEXT('Daily Sales'!$C$2:$AG$2,"0"),0) ), ""), "") )} -> 12240000 | J75: =J74+H75-I75 -> #VALUE!
A76: =IF(E76="","",MATCH(E76,'Daily Sales'!B$4:B$51,0)+3) -> 13 | B76: 46176 | C76: DS26-0603 | D76: {=IF($A76="","",INDEX('Daily Sales'!A:A,$A76))} -> 4-2400 | E76: Sales Cigarette CLUB | F76: =E76 -> Sales Cigarette CLUB | H76: {=IF($A76="","", IF( OR( $A76=23, AND($A76>=32,$A76<=50) ), IFERROR( INDEX('Daily Sales'!$C:$AG, $A76, MATCH(TEXT($B76,"0"),TEXT('Daily Sales'!$C$2:$AG$2,"0"),0) ), ""), "") )} | I76: {=IF($A76="","", IF( OR( AND($A76>=4,$A76<=8), AND($A76>=12,$A76<=19), AND($A76>=28,$A76<=29) ), IFERROR( INDEX('Daily Sales'!$C:$AG, $A76, MATCH(TEXT($B76,"0"),TEXT('Daily Sales'!$C$2:$AG$2,"0"),0) ), ""), "") )} -> 420000 | J76: =J75+H76-I76 -> #VALUE!
A77: =IF(E77="","",MATCH(E77,'Daily Sales'!B$4:B$51,0)+3) -> 14 | B77: 46176 | C77: DS26-0603 | D77: {=IF($A77="","",INDEX('Daily Sales'!A:A,$A77))} -> 4-2100 | E77: Sales Food CLUB | F77: =E77 -> Sales Food CLUB | H77: {=IF($A77="","", IF( OR( $A77=23, AND($A77>=32,$A77<=50) ), IFERROR( INDEX('Daily Sales'!$C:$AG, $A77, MATCH(TEXT($B77,"0"),TEXT('Daily Sales'!$C$2:$AG$2,"0"),0) ), ""), "") )} | I77: {=IF($A77="","", IF( OR( AND($A77>=4,$A77<=8), AND($A77>=12,$A77<=19), AND($A77>=28,$A77<=29) ), IFERROR( INDEX('Daily Sales'!$C:$AG, $A77, MATCH(TEXT($B77,"0"),TEXT('Daily Sales'!$C$2:$AG$2,"0"),0) ), ""), "") )} -> 530000 | J77: =J76+H77-I77 -> #VALUE!
A78: =IF(E78="","",MATCH(E78,'Daily Sales'!B$4:B$51,0)+3) -> 15 | B78: 46176 | C78: DS26-0603 | D78: {=IF($A78="","",INDEX('Daily Sales'!A:A,$A78))} -> 4-2300 | E78: Sales Shisa CLUB | F78: =E78 -> Sales Shisa CLUB | H78: {=IF($A78="","", IF( OR( $A78=23, AND($A78>=32,$A78<=50) ), IFERROR( INDEX('Daily Sales'!$C:$AG, $A78, MATCH(TEXT($B78,"0"),TEXT('Daily Sales'!$C$2:$AG$2,"0"),0) ), ""), "") )} | I78: {=IF($A78="","", IF( OR( AND($A78>=4,$A78<=8), AND($A78>=12,$A78<=19), AND($A78>=28,$A78<=29) ), IFERROR( INDEX('Daily Sales'!$C:$AG, $A78, MATCH(TEXT($B78,"0"),TEXT('Daily Sales'!$C$2:$AG$2,"0"),0) ), ""), "") )} -> 750000 | J78: =J77+H78-I78 -> #VALUE!
A79: =IF(E79="","",MATCH(E79,'Daily Sales'!B$4:B$51,0)+3) -> 17 | B79: 46176 | C79: DS26-0603 | D79: {=IF($A79="","",INDEX('Daily Sales'!A:A,$A79))} -> 4-2601 | E79: Misc | F79: =E79 -> Misc | H79: {=IF($A79="","", IF( OR( $A79=23, AND($A79>=32,$A79<=50) ), IFERROR( INDEX('Daily Sales'!$C:$AG, $A79, MATCH(TEXT($B79,"0"),TEXT('Daily Sales'!$C$2:$AG$2,"0"),0) ), ""), "") )} | I79: {=IF($A79="","", IF( OR( AND($A79>=4,$A79<=8), AND($A79>=12,$A79<=19), AND($A79>=28,$A79<=29) ), IFERROR( INDEX('Daily Sales'!$C:$AG, $A79, MATCH(TEXT($B79,"0"),TEXT('Daily Sales'!$C$2:$AG$2,"0"),0) ), ""), "") )} -> 200000 | J79: =J78+H79-I79 -> #VALUE!
A80: =IF(E80="","",MATCH(E80,'Daily Sales'!B$4:B$51,0)+3) -> 19 | B80: 46176 | C80: DS26-0603 | D80: {=IF($A80="","",INDEX('Daily Sales'!A:A,$A80))} -> 4-2500 | E80: Sales Ticket | F80: =E80 -> Sales Ticket | H80: {=IF($A80="","", IF( OR( $A80=23, AND($A80>=32,$A80<=50) ), IFERROR( INDEX('Daily Sales'!$C:$AG, $A80, MATCH(TEXT($B80,"0"),TEXT('Daily Sales'!$C$2:$AG$2,"0"),0) ), ""), "") )} | I80: {=IF($A80="","", IF( OR( AND($A80>=4,$A80<=8), AND($A80>=12,$A80<=19), AND($A80>=28,$A80<=29) ), IFERROR( INDEX('Daily Sales'!$C:$AG, $A80, MATCH(TEXT($B80,"0"),TEXT('Daily Sales'!$C$2:$AG$2,"0"),0) ), ""), "") )} -> 13763844 | J80: =J79+H80-I80 -> #VALUE!
A81: =IF(E81="","",MATCH(E81,'Daily Sales'!B$4:B$51,0)+3) -> 28 | B81: 46176 | C81: DS26-0603 | D81: {=IF($A81="","",INDEX('Daily Sales'!A:A,$A81))} -> 2-2106 | E81: Service Charges 7% | F81: =E81 -> Service Charges 7% | H81: {=IF($A81="","", IF( OR( $A81=23, AND($A81>=32,$A81<=50) ), IFERROR( INDEX('Daily Sales'!$C:$AG, $A81, MATCH(TEXT($B81,"0"),TEXT('Daily Sales'!$C$2:$AG$2,"0"),0) ), ""), "") )} | I81: {=IF($A81="","", IF( OR( AND($A81>=4,$A81<=8), AND($A81>=12,$A81<=19), AND($A81>=28,$A81<=29) ), IFERROR( INDEX('Daily Sales'!$C:$AG, $A81, MATCH(TEXT($B81,"0"),TEXT('Daily Sales'!$C$2:$AG$2,"0"),0) ), ""), "") )} -> 2820359.1 | J81: =J80+H81-I81 -> #VALUE!
A82: =IF(E82="","",MATCH(E82,'Daily Sales'!B$4:B$51,0)+3) -> 29 | B82: 46176 | C82: DS26-0603 | D82: {=IF($A82="","",INDEX('Daily Sales'!A:A,$A82))} -> 2-3101 | E82: Tax PB1 10% | F82: =E82 -> Tax PB1 10% | H82: {=IF($A82="","", IF( OR( $A82=23, AND($A82>=32,$A82<=50) ), IFERROR( INDEX('Daily Sales'!$C:$AG, $A82, MATCH(TEXT($B82,"0"),TEXT('Daily Sales'!$C$2:$AG$2,"0"),0) ), ""), "") )} | I82: {=IF($A82="","", IF( OR( AND($A82>=4,$A82<=8), AND($A82>=12,$A82<=19), AND($A82>=28,$A82<=29) ), IFERROR( INDEX('Daily Sales'!$C:$AG, $A82, MATCH(TEXT($B82,"0"),TEXT('Daily Sales'!$C$2:$AG$2,"0"),0) ), ""), "") )} -> 4311120.3 | J82: =J81+H82-I82 -> #VALUE!
... A101: =IF(E101="","",MATCH(E101,'Daily Sales'!B$4:B$51,0)+3) -> 50 | B101: 46176 | C101: DS26-0603 | D101: {=IF($A101="","",INDEX('Daily Sales'!A:A,$A101))} -> 2-2110 | E101: Cash Short/Over | F101: =E101 -> Cash Short/Over | H101: {=IF($A101="","", IF( OR( $A101=23, AND($A101>=32,$A101<=50) ), IFERROR( INDEX('Daily Sales'!$C:$AG, $A101, MATCH(TEXT($B101,"0"),TEXT('Daily Sales'!$C$2:$AG$2,"0"),0) ), ""), "") )} -> 39294.39 | I101: {=IF($A101="","", IF( OR( AND($A101>=4,$A101<=8), AND($A101>=12,$A101<=19), AND($A101>=28,$A101<=29) ), IFERROR( INDEX('Daily Sales'!$C:$AG, $A101, MATCH(TEXT($B101,"0"),TEXT('Daily Sales'!$C$2:$AG$2,"0"),0) ), ""), "") )} | J101: =J100+H101-I101 -> #VALUE!
A102: =IF(E102="","",MATCH(E102,'Daily Sales'!B$4:B$51,0)+3) | D102: {=IF($A102="","",INDEX('Daily Sales'!A:A,$A102))} | F102: =E102 -> 0 | H102: {=IF($A102="","", IF( OR( $A102=23, AND($A102>=32,$A102<=50) ), IFERROR( INDEX('Daily Sales'!$C:$AG, $A102, MATCH(TEXT($B102,"0"),TEXT('Daily Sales'!$C$2:$AG$2,"0"),0) ), ""), "") )} | I102: {=IF($A102="","", IF( OR( AND($A102>=4,$A102<=8), AND($A102>=12,$A102<=19), AND($A102>=28,$A102<=29) ), IFERROR( INDEX('Daily Sales'!$C:$AG, $A102, MATCH(TEXT($B102,"0"),TEXT('Daily Sales'!$C$2:$AG$2,"0"),0) ), ""), "") )} | J102: =J101+H102-I102 -> #VALUE!
A103: =IF(E103="","",MATCH(E103,'Daily Sales'!B$4:B$51,0)+3) -> 4 | B103: 46177 | C103: DS26-0604 | D103: {=IF($A103="","",INDEX('Daily Sales'!A:A,$A103))} -> 4-2100 | E103: Sales Food TERRACE | F103: =E103 -> Sales Food TERRACE | H103: {=IF($A103="","", IF( OR( $A103=23, AND($A103>=32,$A103<=50) ), IFERROR( INDEX('Daily Sales'!$C:$AG, $A103, MATCH(TEXT($B103,"0"),TEXT('Daily Sales'!$C$2:$AG$2,"0"),0) ), ""), "") )} | I103: {=IF($A103="","", IF( OR( AND($A103>=4,$A103<=8), AND($A103>=12,$A103<=19), AND($A103>=28,$A103<=29) ), IFERROR( INDEX('Daily Sales'!$C:$AG, $A103, MATCH(TEXT($B103,"0"),TEXT('Daily Sales'!$C$2:$AG$2,"0"),0) ), ""), "") )} -> 3432500 | J103: =J102+H103-I103 -> #VALUE!
A104: =IF(E104="","",MATCH(E104,'Daily Sales'!B$4:B$51,0)+3) -> 5 | B104: 46177 | C104: DS26-0604 | D104: {=IF($A104="","",INDEX('Daily Sales'!A:A,$A104))} -> 4-2200 | E104: Sales Beverages TERRACE | F104: =E104 -> Sales Beverages TERRACE | H104: {=IF($A104="","", IF( OR( $A104=23, AND($A104>=32,$A104<=50) ), IFERROR( INDEX('Daily Sales'!$C:$AG, $A104, MATCH(TEXT($B104,"0"),TEXT('Daily Sales'!$C$2:$AG$2,"0"),0) ), ""), "") )} | I104: {=IF($A104="","", IF( OR( AND($A104>=4,$A104<=8), AND($A104>=12,$A104<=19), AND($A104>=28,$A104<=29) ), IFERROR( INDEX('Daily Sales'!$C:$AG, $A104, MATCH(TEXT($B104,"0"),TEXT('Daily Sales'!$C$2:$AG$2,"0"),0) ), ""), "") )} -> 5855000 | J104: =J103+H104-I104 -> #VALUE!
A105: =IF(E105="","",MATCH(E105,'Daily Sales'!B$4:B$51,0)+3) -> 6 | B105: 46177 | C105: DS26-0604 | D105: {=IF($A105="","",INDEX('Daily Sales'!A:A,$A105))} -> 4-2400 | E105: Sales Cigarette TERRACE | F105: =E105 -> Sales Cigarette TERRACE | H105: {=IF($A105="","", IF( OR( $A105=23, AND($A105>=32,$A105<=50) ), IFERROR( INDEX('Daily Sales'!$C:$AG, $A105, MATCH(TEXT($B105,"0"),TEXT('Daily Sales'!$C$2:$AG$2,"0"),0) ), ""), "") )} | I105: {=IF($A105="","", IF( OR( AND($A105>=4,$A105<=8), AND($A105>=12,$A105<=19), AND($A105>=28,$A105<=29) ), IFERROR( INDEX('Daily Sales'!$C:$AG, $A105, MATCH(TEXT($B105,"0"),TEXT('Daily Sales'!$C$2:$AG$2,"0"),0) ), ""), "") )} -> 70000 | J105: =J104+H105-I105 -> #VALUE!
A106: =IF(E106="","",MATCH(E106,'Daily Sales'!B$4:B$51,0)+3) -> 7 | B106: 46177 | C106: DS26-0604 | D106: {=IF($A106="","",INDEX('Daily Sales'!A:A,$A106))} -> 4-2300 | E106: Sales Shisa TERRACE | F106: =E106 -> Sales Shisa TERRACE | H106: {=IF($A106="","", IF( OR( $A106=23, AND($A106>=32,$A106<=50) ), IFERROR( INDEX('Daily Sales'!$C:$AG, $A106, MATCH(TEXT($B106,"0"),TEXT('Daily Sales'!$C$2:$AG$2,"0"),0) ), ""), "") )} | I106: {=IF($A106="","", IF( OR( AND($A106>=4,$A106<=8), AND($A106>=12,$A106<=19), AND($A106>=28,$A106<=29) ), IFERROR( INDEX('Daily Sales'!$C:$AG, $A106, MATCH(TEXT($B106,"0"),TEXT('Daily Sales'!$C$2:$AG$2,"0"),0) ), ""), "") )} -> 0 | J106: =J105+H106-I106 -> #VALUE!
A107: =IF(E107="","",MATCH(E107,'Daily Sales'!B$4:B$51,0)+3) -> 12 | B107: 46177 | C107: DS26-0604 | D107: {=IF($A107="","",INDEX('Daily Sales'!A:A,$A107))} -> 4-2200 | E107: Sales Beverages CLUB | F107: =E107 -> Sales Beverages CLUB | H107: {=IF($A107="","", IF( OR( $A107=23, AND($A107>=32,$A107<=50) ), IFERROR( INDEX('Daily Sales'!$C:$AG, $A107, MATCH(TEXT($B107,"0"),TEXT('Daily Sales'!$C$2:$AG$2,"0"),0) ), ""), "") )} | I107: {=IF($A107="","", IF( OR( AND($A107>=4,$A107<=8), AND($A107>=12,$A107<=19), AND($A107>=28,$A107<=29) ), IFERROR( INDEX('Daily Sales'!$C:$AG, $A107, MATCH(TEXT($B107,"0"),TEXT('Daily Sales'!$C$2:$AG$2,"0"),0) ), ""), "") )} -> 33750000 | J107: =J106+H107-I107 -> #VALUE!
A108: =IF(E108="","",MATCH(E108,'Daily Sales'!B$4:B$51,0)+3) -> 13 | B108: 46177 | C108: DS26-0604 | D108: {=IF($A108="","",INDEX('Daily Sales'!A:A,$A108))} -> 4-2400 | E108: Sales Cigarette CLUB | F108: =E108 -> Sales Cigarette CLUB | H108: {=IF($A108="","", IF( OR( $A108=23, AND($A108>=32,$A108<=50) ), IFERROR( INDEX('Daily Sales'!$C:$AG, $A108, MATCH(TEXT($B108,"0"),TEXT('Daily Sales'!$C$2:$AG$2,"0"),0) ), ""), "") )} | I108: {=IF($A108="","", IF( OR( AND($A108>=4,$A108<=8), AND($A108>=12,$A108<=19), AND($A108>=28,$A108<=29) ), IFERROR( INDEX('Daily Sales'!$C:$AG, $A108, MATCH(TEXT($B108,"0"),TEXT('Daily Sales'!$C$2:$AG$2,"0"),0) ), ""), "") )} -> 490000 | J108: =J107+H108-I108 -> #VALUE!
A109: =IF(E109="","",MATCH(E109,'Daily Sales'!B$4:B$51,0)+3) -> 14 | B109: 46177 | C109: DS26-0604 | D109: {=IF($A109="","",INDEX('Daily Sales'!A:A,$A109))} -> 4-2100 | E109: Sales Food CLUB | F109: =E109 -> Sales Food CLUB | H109: {=IF($A109="","", IF( OR( $A109=23, AND($A109>=32,$A109<=50) ), IFERROR( INDEX('Daily Sales'!$C:$AG, $A109, MATCH(TEXT($B109,"0"),TEXT('Daily Sales'!$C$2:$AG$2,"0"),0) ), ""), "") )} | I109: {=IF($A109="","", IF( OR( AND($A109>=4,$A109<=8), AND($A109>=12,$A109<=19), AND($A109>=28,$A109<=29) ), IFERROR( INDEX('Daily Sales'!$C:$AG, $A109, MATCH(TEXT($B109,"0"),TEXT('Daily Sales'!$C$2:$AG$2,"0"),0) ), ""), "") )} -> 790000 | J109: =J108+H109-I109 -> #VALUE!
A110: =IF(E110="","",MATCH(E110,'Daily Sales'!B$4:B$51,0)+3) -> 15 | B110: 46177 | C110: DS26-0604 | D110: {=IF($A110="","",INDEX('Daily Sales'!A:A,$A110))} -> 4-2300 | E110: Sales Shisa CLUB | F110: =E110 -> Sales Shisa CLUB | H110: {=IF($A110="","", IF( OR( $A110=23, AND($A110>=32,$A110<=50) ), IFERROR( INDEX('Daily Sales'!$C:$AG, $A110, MATCH(TEXT($B110,"0"),TEXT('Daily Sales'!$C$2:$AG$2,"0"),0) ), ""), "") )} | I110: {=IF($A110="","", IF( OR( AND($A110>=4,$A110<=8), AND($A110>=12,$A110<=19), AND($A110>=28,$A110<=29) ), IFERROR( INDEX('Daily Sales'!$C:$AG, $A110, MATCH(TEXT($B110,"0"),TEXT('Daily Sales'!$C$2:$AG$2,"0"),0) ), ""), "") )} -> 750000 | J110: =J109+H110-I110 -> #VALUE!
A111: =IF(E111="","",MATCH(E111,'Daily Sales'!B$4:B$51,0)+3) -> 17 | B111: 46177 | C111: DS26-0604 | D111: {=IF($A111="","",INDEX('Daily Sales'!A:A,$A111))} -> 4-2601 | E111: Misc | F111: =E111 -> Misc | H111: {=IF($A111="","", IF( OR( $A111=23, AND($A111>=32,$A111<=50) ), IFERROR( INDEX('Daily Sales'!$C:$AG, $A111, MATCH(TEXT($B111,"0"),TEXT('Daily Sales'!$C$2:$AG$2,"0"),0) ), ""), "") )} | I111: {=IF($A111="","", IF( OR( AND($A111>=4,$A111<=8), AND($A111>=12,$A111<=19), AND($A111>=28,$A111<=29) ), IFERROR( INDEX('Daily Sales'!$C:$AG, $A111, MATCH(TEXT($B111,"0"),TEXT('Daily Sales'!$C$2:$AG$2,"0"),0) ), ""), "") )} -> 0 | J111: =J110+H111-I111 -> #VALUE!
A112: =IF(E112="","",MATCH(E112,'Daily Sales'!B$4:B$51,0)+3) -> 19 | B112: 46177 | C112: DS26-0604 | D112: {=IF($A112="","",INDEX('Daily Sales'!A:A,$A112))} -> 4-2500 | E112: Sales Ticket | F112: =E112 -> Sales Ticket | H112: {=IF($A112="","", IF( OR( $A112=23, AND($A112>=32,$A112<=50) ), IFERROR( INDEX('Daily Sales'!$C:$AG, $A112, MATCH(TEXT($B112,"0"),TEXT('Daily Sales'!$C$2:$AG$2,"0"),0) ), ""), "") )} | I112: {=IF($A112="","", IF( OR( AND($A112>=4,$A112<=8), AND($A112>=12,$A112<=19), AND($A112>=28,$A112<=29) ), IFERROR( INDEX('Daily Sales'!$C:$AG, $A112, MATCH(TEXT($B112,"0"),TEXT('Daily Sales'!$C$2:$AG$2,"0"),0) ), ""), "") )} -> 14061211 | J112: =J111+H112-I112 -> #VALUE!
A113: =IF(E113="","",MATCH(E113,'Daily Sales'!B$4:B$51,0)+3) -> 28 | B113: 46177 | C113: DS26-0604 | D113: {=IF($A113="","",INDEX('Daily Sales'!A:A,$A113))} -> 2-2106 | E113: Service Charges 7% | F113: =E113 -> Service Charges 7% | H113: {=IF($A113="","", IF( OR( $A113=23, AND($A113>=32,$A113<=50) ), IFERROR( INDEX('Daily Sales'!$C:$AG, $A113, MATCH(TEXT($B113,"0"),TEXT('Daily Sales'!$C$2:$AG$2,"0"),0) ), ""), "") )} | I113: {=IF($A113="","", IF( OR( AND($A113>=4,$A113<=8), AND($A113>=12,$A113<=19), AND($A113>=28,$A113<=29) ), IFERROR( INDEX('Daily Sales'!$C:$AG, $A113, MATCH(TEXT($B113,"0"),TEXT('Daily Sales'!$C$2:$AG$2,"0"),0) ), ""), "") )} -> 4020779.8 | J113: =J112+H113-I113 -> #VALUE!
A114: =IF(E114="","",MATCH(E114,'Daily Sales'!B$4:B$51,0)+3) -> 29 | B114: 46177 | C114: DS26-0604 | D114: {=IF($A114="","",INDEX('Daily Sales'!A:A,$A114))} -> 2-3101 | E114: Tax PB1 10% | F114: =E114 -> Tax PB1 10% | H114: {=IF($A114="","", IF( OR( $A114=23, AND($A114>=32,$A114<=50) ), IFERROR( INDEX('Daily Sales'!$C:$AG, $A114, MATCH(TEXT($B114,"0"),TEXT('Daily Sales'!$C$2:$AG$2,"0"),0) ), ""), "") )} | I114: {=IF($A114="","", IF( OR( AND($A114>=4,$A114<=8), AND($A114>=12,$A114<=19), AND($A114>=28,$A114<=29) ), IFERROR( INDEX('Daily Sales'!$C:$AG, $A114, MATCH(TEXT($B114,"0"),TEXT('Daily Sales'!$C$2:$AG$2,"0"),0) ), ""), "") )} -> 6146049.1 | J114: =J113+H114-I114 -> #VALUE!
... A133: =IF(E133="","",MATCH(E133,'Daily Sales'!B$4:B$51,0)+3) -> 50 | B133: 46177 | C133: DS26-0604 | D133: {=IF($A133="","",INDEX('Daily Sales'!A:A,$A133))} -> 2-2110 | E133: Cash Short/Over | F133: =E133 -> Cash Short/Over | H133: {=IF($A133="","", IF( OR( $A133=23, AND($A133>=32,$A133<=50) ), IFERROR( INDEX('Daily Sales'!$C:$AG, $A133, MATCH(TEXT($B133,"0"),TEXT('Daily Sales'!$C$2:$AG$2,"0"),0) ), ""), "") )} -> -84557.15 | I133: {=IF($A133="","", IF( OR( AND($A133>=4,$A133<=8), AND($A133>=12,$A133<=19), AND($A133>=28,$A133<=29) ), IFERROR( INDEX('Daily Sales'!$C:$AG, $A133, MATCH(TEXT($B133,"0"),TEXT('Daily Sales'!$C$2:$AG$2,"0"),0) ), ""), "") )} | J133: =J132+H133-I133 -> #VALUE!
A134: =IF(E134="","",MATCH(E134,'Daily Sales'!B$4:B$51,0)+3) | D134: {=IF($A134="","",INDEX('Daily Sales'!A:A,$A134))} | F134: =E134 -> 0 | H134: {=IF($A134="","", IF( OR( $A134=23, AND($A134>=32,$A134<=50) ), IFERROR( INDEX('Daily Sales'!$C:$AG, $A134, MATCH(TEXT($B134,"0"),TEXT('Daily Sales'!$C$2:$AG$2,"0"),0) ), ""), "") )} | I134: {=IF($A134="","", IF( OR( AND($A134>=4,$A134<=8), AND($A134>=12,$A134<=19), AND($A134>=28,$A134<=29) ), IFERROR( INDEX('Daily Sales'!$C:$AG, $A134, MATCH(TEXT($B134,"0"),TEXT('Daily Sales'!$C$2:$AG$2,"0"),0) ), ""), "") )} | J134: =J133+H134-I134 -> #VALUE!
A135: =IF(E135="","",MATCH(E135,'Daily Sales'!B$4:B$51,0)+3) -> 4 | B135: 46178 | C135: DS26-0605 | D135: {=IF($A135="","",INDEX('Daily Sales'!A:A,$A135))} -> 4-2100 | E135: Sales Food TERRACE | F135: =E135 -> Sales Food TERRACE | H135: {=IF($A135="","", IF( OR( $A135=23, AND($A135>=32,$A135<=50) ), IFERROR( INDEX('Daily Sales'!$C:$AG, $A135, MATCH(TEXT($B135,"0"),TEXT('Daily Sales'!$C$2:$AG$2,"0"),0) ), ""), "") )} | I135: {=IF($A135="","", IF( OR( AND($A135>=4,$A135<=8), AND($A135>=12,$A135<=19), AND($A135>=28,$A135<=29) ), IFERROR( INDEX('Daily Sales'!$C:$AG, $A135, MATCH(TEXT($B135,"0"),TEXT('Daily Sales'!$C$2:$AG$2,"0"),0) ), ""), "") )} -> 8275000 | J135: =J134+H135-I135 -> #VALUE!
A136: =IF(E136="","",MATCH(E136,'Daily Sales'!B$4:B$51,0)+3) -> 5 | B136: 46178 | C136: DS26-0605 | D136: {=IF($A136="","",INDEX('Daily Sales'!A:A,$A136))} -> 4-2200 | E136: Sales Beverages TERRACE | F136: =E136 -> Sales Beverages TERRACE | H136: {=IF($A136="","", IF( OR( $A136=23, AND($A136>=32,$A136<=50) ), IFERROR( INDEX('Daily Sales'!$C:$AG, $A136, MATCH(TEXT($B136,"0"),TEXT('Daily Sales'!$C$2:$AG$2,"0"),0) ), ""), "") )} | I136: {=IF($A136="","", IF( OR( AND($A136>=4,$A136<=8), AND($A136>=12,$A136<=19), AND($A136>=28,$A136<=29) ), IFERROR( INDEX('Daily Sales'!$C:$AG, $A136, MATCH(TEXT($B136,"0"),TEXT('Daily Sales'!$C$2:$AG$2,"0"),0) ), ""), "") )} -> 12875000 | J136: =J135+H136-I136 -> #VALUE!
A137: =IF(E137="","",MATCH(E137,'Daily Sales'!B$4:B$51,0)+3) -> 6 | B137: 46178 | C137: DS26-0605 | D137: {=IF($A137="","",INDEX('Daily Sales'!A:A,$A137))} -> 4-2400 | E137: Sales Cigarette TERRACE | F137: =E137 -> Sales Cigarette TERRACE | H137: {=IF($A137="","", IF( OR( $A137=23, AND($A137>=32,$A137<=50) ), IFERROR( INDEX('Daily Sales'!$C:$AG, $A137, MATCH(TEXT($B137,"0"),TEXT('Daily Sales'!$C$2:$AG$2,"0"),0) ), ""), "") )} | I137: {=IF($A137="","", IF( OR( AND($A137>=4,$A137<=8), AND($A137>=12,$A137<=19), AND($A137>=28,$A137<=29) ), IFERROR( INDEX('Daily Sales'!$C:$AG, $A137, MATCH(TEXT($B137,"0"),TEXT('Daily Sales'!$C$2:$AG$2,"0"),0) ), ""), "") )} -> 210000 | J137: =J136+H137-I137 -> #VALUE!
A138: =IF(E138="","",MATCH(E138,'Daily Sales'!B$4:B$51,0)+3) -> 7 | B138: 46178 | C138: DS26-0605 | D138: {=IF($A138="","",INDEX('Daily Sales'!A:A,$A138))} -> 4-2300 | E138: Sales Shisa TERRACE | F138: =E138 -> Sales Shisa TERRACE | H138: {=IF($A138="","", IF( OR( $A138=23, AND($A138>=32,$A138<=50) ), IFERROR( INDEX('Daily Sales'!$C:$AG, $A138, MATCH(TEXT($B138,"0"),TEXT('Daily Sales'!$C$2:$AG$2,"0"),0) ), ""), "") )} | I138: {=IF($A138="","", IF( OR( AND($A138>=4,$A138<=8), AND($A138>=12,$A138<=19), AND($A138>=28,$A138<=29) ), IFERROR( INDEX('Daily Sales'!$C:$AG, $A138, MATCH(TEXT($B138,"0"),TEXT('Daily Sales'!$C$2:$AG$2,"0"),0) ), ""), "") )} -> 500000 | J138: =J137+H138-I138 -> #VALUE!
A139: =IF(E139="","",MATCH(E139,'Daily Sales'!B$4:B$51,0)+3) -> 12 | B139: 46178 | C139: DS26-0605 | D139: {=IF($A139="","",INDEX('Daily Sales'!A:A,$A139))} -> 4-2200 | E139: Sales Beverages CLUB | F139: =E139 -> Sales Beverages CLUB | H139: {=IF($A139="","", IF( OR( $A139=23, AND($A139>=32,$A139<=50) ), IFERROR( INDEX('Daily Sales'!$C:$AG, $A139, MATCH(TEXT($B139,"0"),TEXT('Daily Sales'!$C$2:$AG$2,"0"),0) ), ""), "") )} | I139: {=IF($A139="","", IF( OR( AND($A139>=4,$A139<=8), AND($A139>=12,$A139<=19), AND($A139>=28,$A139<=29) ), IFERROR( INDEX('Daily Sales'!$C:$AG, $A139, MATCH(TEXT($B139,"0"),TEXT('Daily Sales'!$C$2:$AG$2,"0"),0) ), ""), "") )} -> 60190000 | J139: =J138+H139-I139 -> #VALUE!
A140: =IF(E140="","",MATCH(E140,'Daily Sales'!B$4:B$51,0)+3) -> 13 | B140: 46178 | C140: DS26-0605 | D140: {=IF($A140="","",INDEX('Daily Sales'!A:A,$A140))} -> 4-2400 | E140: Sales Cigarette CLUB | F140: =E140 -> Sales Cigarette CLUB | H140: {=IF($A140="","", IF( OR( $A140=23, AND($A140>=32,$A140<=50) ), IFERROR( INDEX('Daily Sales'!$C:$AG, $A140, MATCH(TEXT($B140,"0"),TEXT('Daily Sales'!$C$2:$AG$2,"0"),0) ), ""), "") )} | I140: {=IF($A140="","", IF( OR( AND($A140>=4,$A140<=8), AND($A140>=12,$A140<=19), AND($A140>=28,$A140<=29) ), IFERROR( INDEX('Daily Sales'!$C:$AG, $A140, MATCH(TEXT($B140,"0"),TEXT('Daily Sales'!$C$2:$AG$2,"0"),0) ), ""), "") )} -> 1260000 | J140: =J139+H140-I140 -> #VALUE!
A141: =IF(E141="","",MATCH(E141,'Daily Sales'!B$4:B$51,0)+3) -> 14 | B141: 46178 | C141: DS26-0605 | D141: {=IF($A141="","",INDEX('Daily Sales'!A:A,$A141))} -> 4-2100 | E141: Sales Food CLUB | F141: =E141 -> Sales Food CLUB | H141: {=IF($A141="","", IF( OR( $A141=23, AND($A141>=32,$A141<=50) ), IFERROR( INDEX('Daily Sales'!$C:$AG, $A141, MATCH(TEXT($B141,"0"),TEXT('Daily Sales'!$C$2:$AG$2,"0"),0) ), ""), "") )} | I141: {=IF($A141="","", IF( OR( AND($A141>=4,$A141<=8), AND($A141>=12,$A141<=19), AND($A141>=28,$A141<=29) ), IFERROR( INDEX('Daily Sales'!$C:$AG, $A141, MATCH(TEXT($B141,"0"),TEXT('Daily Sales'!$C$2:$AG$2,"0"),0) ), ""), "") )} -> 1160000 | J141: =J140+H141-I141 -> #VALUE!
A142: =IF(E142="","",MATCH(E142,'Daily Sales'!B$4:B$51,0)+3) -> 15 | B142: 46178 | C142: DS26-0605 | D142: {=IF($A142="","",INDEX('Daily Sales'!A:A,$A142))} -> 4-2300 | E142: Sales Shisa CLUB | F142: =E142 -> Sales Shisa CLUB | H142: {=IF($A142="","", IF( OR( $A142=23, AND($A142>=32,$A142<=50) ), IFERROR( INDEX('Daily Sales'!$C:$AG, $A142, MATCH(TEXT($B142,"0"),TEXT('Daily Sales'!$C$2:$AG$2,"0"),0) ), ""), "") )} | I142: {=IF($A142="","", IF( OR( AND($A142>=4,$A142<=8), AND($A142>=12,$A142<=19), AND($A142>=28,$A142<=29) ), IFERROR( INDEX('Daily Sales'!$C:$AG, $A142, MATCH(TEXT($B142,"0"),TEXT('Daily Sales'!$C$2:$AG$2,"0"),0) ), ""), "") )} -> 1750000 | J142: =J141+H142-I142 -> #VALUE!
A143: =IF(E143="","",MATCH(E143,'Daily Sales'!B$4:B$51,0)+3) -> 17 | B143: 46178 | C143: DS26-0605 | D143: {=IF($A143="","",INDEX('Daily Sales'!A:A,$A143))} -> 4-2601 | E143: Misc | F143: =E143 -> Misc | H143: {=IF($A143="","", IF( OR( $A143=23, AND($A143>=32,$A143<=50) ), IFERROR( INDEX('Daily Sales'!$C:$AG, $A143, MATCH(TEXT($B143,"0"),TEXT('Daily Sales'!$C$2:$AG$2,"0"),0) ), ""), "") )} | I143: {=IF($A143="","", IF( OR( AND($A143>=4,$A143<=8), AND($A143>=12,$A143<=19), AND($A143>=28,$A143<=29) ), IFERROR( INDEX('Daily Sales'!$C:$AG, $A143, MATCH(TEXT($B143,"0"),TEXT('Daily Sales'!$C$2:$AG$2,"0"),0) ), ""), "") )} -> 120000 | J143: =J142+H143-I143 -> #VALUE!
A144: =IF(E144="","",MATCH(E144,'Daily Sales'!B$4:B$51,0)+3) -> 19 | B144: 46178 | C144: DS26-0605 | D144: {=IF($A144="","",INDEX('Daily Sales'!A:A,$A144))} -> 4-2500 | E144: Sales Ticket | F144: =E144 -> Sales Ticket | H144: {=IF($A144="","", IF( OR( $A144=23, AND($A144>=32,$A144<=50) ), IFERROR( INDEX('Daily Sales'!$C:$AG, $A144, MATCH(TEXT($B144,"0"),TEXT('Daily Sales'!$C$2:$AG$2,"0"),0) ), ""), "") )} | I144: {=IF($A144="","", IF( OR( AND($A144>=4,$A144<=8), AND($A144>=12,$A144<=19), AND($A144>=28,$A144<=29) ), IFERROR( INDEX('Daily Sales'!$C:$AG, $A144, MATCH(TEXT($B144,"0"),TEXT('Daily Sales'!$C$2:$AG$2,"0"),0) ), ""), "") )} -> 24936347 | J144: =J143+H144-I144 -> #VALUE!
A145: =IF(E145="","",MATCH(E145,'Daily Sales'!B$4:B$51,0)+3) -> 28 | B145: 46178 | C145: DS26-0605 | D145: {=IF($A145="","",INDEX('Daily Sales'!A:A,$A145))} -> 2-2106 | E145: Service Charges 7% | F145: =E145 -> Service Charges 7% | H145: {=IF($A145="","", IF( OR( $A145=23, AND($A145>=32,$A145<=50) ), IFERROR( INDEX('Daily Sales'!$C:$AG, $A145, MATCH(TEXT($B145,"0"),TEXT('Daily Sales'!$C$2:$AG$2,"0"),0) ), ""), "") )} | I145: {=IF($A145="","", IF( OR( AND($A145>=4,$A145<=8), AND($A145>=12,$A145<=19), AND($A145>=28,$A145<=29) ), IFERROR( INDEX('Daily Sales'!$C:$AG, $A145, MATCH(TEXT($B145,"0"),TEXT('Daily Sales'!$C$2:$AG$2,"0"),0) ), ""), "") )} -> 7694704.3 | J145: =J144+H145-I145 -> #VALUE!
A146: =IF(E146="","",MATCH(E146,'Daily Sales'!B$4:B$51,0)+3) -> 29 | B146: 46178 | C146: DS26-0605 | D146: {=IF($A146="","",INDEX('Daily Sales'!A:A,$A146))} -> 2-3101 | E146: Tax PB1 10% | F146: =E146 -> Tax PB1 10% | H146: {=IF($A146="","", IF( OR( $A146=23, AND($A146>=32,$A146<=50) ), IFERROR( INDEX('Daily Sales'!$C:$AG, $A146, MATCH(TEXT($B146,"0"),TEXT('Daily Sales'!$C$2:$AG$2,"0"),0) ), ""), "") )} | I146: {=IF($A146="","", IF( OR( AND($A146>=4,$A146<=8), AND($A146>=12,$A146<=19), AND($A146>=28,$A146<=29) ), IFERROR( INDEX('Daily Sales'!$C:$AG, $A146, MATCH(TEXT($B146,"0"),TEXT('Daily Sales'!$C$2:$AG$2,"0"),0) ), ""), "") )} -> 11761905 | J146: =J145+H146-I146 -> #VALUE!
... A165: =IF(E165="","",MATCH(E165,'Daily Sales'!B$4:B$51,0)+3) -> 50 | B165: 46178 | C165: DS26-0605 | D165: {=IF($A165="","",INDEX('Daily Sales'!A:A,$A165))} -> 2-2110 | E165: Cash Short/Over | F165: =E165 -> Cash Short/Over | H165: {=IF($A165="","", IF( OR( $A165=23, AND($A165>=32,$A165<=50) ), IFERROR( INDEX('Daily Sales'!$C:$AG, $A165, MATCH(TEXT($B165,"0"),TEXT('Daily Sales'!$C$2:$AG$2,"0"),0) ), ""), "") )} -> -2507270.6 | I165: {=IF($A165="","", IF( OR( AND($A165>=4,$A165<=8), AND($A165>=12,$A165<=19), AND($A165>=28,$A165<=29) ), IFERROR( INDEX('Daily Sales'!$C:$AG, $A165, MATCH(TEXT($B165,"0"),TEXT('Daily Sales'!$C$2:$AG$2,"0"),0) ), ""), "") )} | J165: =J164+H165-I165 -> #VALUE!
A166: =IF(E166="","",MATCH(E166,'Daily Sales'!B$4:B$51,0)+3) | D166: {=IF($A166="","",INDEX('Daily Sales'!A:A,$A166))} | F166: =E166 -> 0 | H166: {=IF($A166="","", IF( OR( $A166=23, AND($A166>=32,$A166<=50) ), IFERROR( INDEX('Daily Sales'!$C:$AG, $A166, MATCH(TEXT($B166,"0"),TEXT('Daily Sales'!$C$2:$AG$2,"0"),0) ), ""), "") )} | I166: {=IF($A166="","", IF( OR( AND($A166>=4,$A166<=8), AND($A166>=12,$A166<=19), AND($A166>=28,$A166<=29) ), IFERROR( INDEX('Daily Sales'!$C:$AG, $A166, MATCH(TEXT($B166,"0"),TEXT('Daily Sales'!$C$2:$AG$2,"0"),0) ), ""), "") )} | J166: =J165+H166-I166 -> #VALUE!
A167: =IF(E167="","",MATCH(E167,'Daily Sales'!B$4:B$51,0)+3) -> 4 | B167: 46179 | C167: DS26-0606 | D167: {=IF($A167="","",INDEX('Daily Sales'!A:A,$A167))} -> 4-2100 | E167: Sales Food TERRACE | F167: =E167 -> Sales Food TERRACE | H167: {=IF($A167="","", IF( OR( $A167=23, AND($A167>=32,$A167<=50) ), IFERROR( INDEX('Daily Sales'!$C:$AG, $A167, MATCH(TEXT($B167,"0"),TEXT('Daily Sales'!$C$2:$AG$2,"0"),0) ), ""), "") )} | I167: {=IF($A167="","", IF( OR( AND($A167>=4,$A167<=8), AND($A167>=12,$A167<=19), AND($A167>=28,$A167<=29) ), IFERROR( INDEX('Daily Sales'!$C:$AG, $A167, MATCH(TEXT($B167,"0"),TEXT('Daily Sales'!$C$2:$AG$2,"0"),0) ), ""), "") )} -> 5030000 | J167: =J166+H167-I167 -> #VALUE!
A168: =IF(E168="","",MATCH(E168,'Daily Sales'!B$4:B$51,0)+3) -> 5 | B168: 46179 | C168: DS26-0606 | D168: {=IF($A168="","",INDEX('Daily Sales'!A:A,$A168))} -> 4-2200 | E168: Sales Beverages TERRACE | F168: =E168 -> Sales Beverages TERRACE | H168: {=IF($A168="","", IF( OR( $A168=23, AND($A168>=32,$A168<=50) ), IFERROR( INDEX('Daily Sales'!$C:$AG, $A168, MATCH(TEXT($B168,"0"),TEXT('Daily Sales'!$C$2:$AG$2,"0"),0) ), ""), "") )} | I168: {=IF($A168="","", IF( OR( AND($A168>=4,$A168<=8), AND($A168>=12,$A168<=19), AND($A168>=28,$A168<=29) ), IFERROR( INDEX('Daily Sales'!$C:$AG, $A168, MATCH(TEXT($B168,"0"),TEXT('Daily Sales'!$C$2:$AG$2,"0"),0) ), ""), "") )} -> 6765000 | J168: =J167+H168-I168 -> #VALUE!
A169: =IF(E169="","",MATCH(E169,'Daily Sales'!B$4:B$51,0)+3) -> 6 | B169: 46179 | C169: DS26-0606 | D169: {=IF($A169="","",INDEX('Daily Sales'!A:A,$A169))} -> 4-2400 | E169: Sales Cigarette TERRACE | F169: =E169 -> Sales Cigarette TERRACE | H169: {=IF($A169="","", IF( OR( $A169=23, AND($A169>=32,$A169<=50) ), IFERROR( INDEX('Daily Sales'!$C:$AG, $A169, MATCH(TEXT($B169,"0"),TEXT('Daily Sales'!$C$2:$AG$2,"0"),0) ), ""), "") )} | I169: {=IF($A169="","", IF( OR( AND($A169>=4,$A169<=8), AND($A169>=12,$A169<=19), AND($A169>=28,$A169<=29) ), IFERROR( INDEX('Daily Sales'!$C:$AG, $A169, MATCH(TEXT($B169,"0"),TEXT('Daily Sales'!$C$2:$AG$2,"0"),0) ), ""), "") )} -> 140000 | J169: =J168+H169-I169 -> #VALUE!
A170: =IF(E170="","",MATCH(E170,'Daily Sales'!B$4:B$51,0)+3) -> 7 | B170: 46179 | C170: DS26-0606 | D170: {=IF($A170="","",INDEX('Daily Sales'!A:A,$A170))} -> 4-2300 | E170: Sales Shisa TERRACE | F170: =E170 -> Sales Shisa TERRACE | H170: {=IF($A170="","", IF( OR( $A170=23, AND($A170>=32,$A170<=50) ), IFERROR( INDEX('Daily Sales'!$C:$AG, $A170, MATCH(TEXT($B170,"0"),TEXT('Daily Sales'!$C$2:$AG$2,"0"),0) ), ""), "") )} | I170: {=IF($A170="","", IF( OR( AND($A170>=4,$A170<=8), AND($A170>=12,$A170<=19), AND($A170>=28,$A170<=29) ), IFERROR( INDEX('Daily Sales'!$C:$AG, $A170, MATCH(TEXT($B170,"0"),TEXT('Daily Sales'!$C$2:$AG$2,"0"),0) ), ""), "") )} -> 0 | J170: =J169+H170-I170 -> #VALUE!
A171: =IF(E171="","",MATCH(E171,'Daily Sales'!B$4:B$51,0)+3) -> 12 | B171: 46179 | C171: DS26-0606 | D171: {=IF($A171="","",INDEX('Daily Sales'!A:A,$A171))} -> 4-2200 | E171: Sales Beverages CLUB | F171: =E171 -> Sales Beverages CLUB | H171: {=IF($A171="","", IF( OR( $A171=23, AND($A171>=32,$A171<=50) ), IFERROR( INDEX('Daily Sales'!$C:$AG, $A171, MATCH(TEXT($B171,"0"),TEXT('Daily Sales'!$C$2:$AG$2,"0"),0) ), ""), "") )} | I171: {=IF($A171="","", IF( OR( AND($A171>=4,$A171<=8), AND($A171>=12,$A171<=19), AND($A171>=28,$A171<=29) ), IFERROR( INDEX('Daily Sales'!$C:$AG, $A171, MATCH(TEXT($B171,"0"),TEXT('Daily Sales'!$C$2:$AG$2,"0"),0) ), ""), "") )} -> 94895000 | J171: =J170+H171-I171 -> #VALUE!
A172: =IF(E172="","",MATCH(E172,'Daily Sales'!B$4:B$51,0)+3) -> 13 | B172: 46179 | C172: DS26-0606 | D172: {=IF($A172="","",INDEX('Daily Sales'!A:A,$A172))} -> 4-2400 | E172: Sales Cigarette CLUB | F172: =E172 -> Sales Cigarette CLUB | H172: {=IF($A172="","", IF( OR( $A172=23, AND($A172>=32,$A172<=50) ), IFERROR( INDEX('Daily Sales'!$C:$AG, $A172, MATCH(TEXT($B172,"0"),TEXT('Daily Sales'!$C$2:$AG$2,"0"),0) ), ""), "") )} | I172: {=IF($A172="","", IF( OR( AND($A172>=4,$A172<=8), AND($A172>=12,$A172<=19), AND($A172>=28,$A172<=29) ), IFERROR( INDEX('Daily Sales'!$C:$AG, $A172, MATCH(TEXT($B172,"0"),TEXT('Daily Sales'!$C$2:$AG$2,"0"),0) ), ""), "") )} -> 1540000 | J172: =J171+H172-I172 -> #VALUE!
A173: =IF(E173="","",MATCH(E173,'Daily Sales'!B$4:B$51,0)+3) -> 14 | B173: 46179 | C173: DS26-0606 | D173: {=IF($A173="","",INDEX('Daily Sales'!A:A,$A173))} -> 4-2100 | E173: Sales Food CLUB | F173: =E173 -> Sales Food CLUB | H173: {=IF($A173="","", IF( OR( $A173=23, AND($A173>=32,$A173<=50) ), IFERROR( INDEX('Daily Sales'!$C:$AG, $A173, MATCH(TEXT($B173,"0"),TEXT('Daily Sales'!$C$2:$AG$2,"0"),0) ), ""), "") )} | I173: {=IF($A173="","", IF( OR( AND($A173>=4,$A173<=8), AND($A173>=12,$A173<=19), AND($A173>=28,$A173<=29) ), IFERROR( INDEX('Daily Sales'!$C:$AG, $A173, MATCH(TEXT($B173,"0"),TEXT('Daily Sales'!$C$2:$AG$2,"0"),0) ), ""), "") )} -> 1490000 | J173: =J172+H173-I173 -> #VALUE!
A174: =IF(E174="","",MATCH(E174,'Daily Sales'!B$4:B$51,0)+3) -> 15 | B174: 46179 | C174: DS26-0606 | D174: {=IF($A174="","",INDEX('Daily Sales'!A:A,$A174))} -> 4-2300 | E174: Sales Shisa CLUB | F174: =E174 -> Sales Shisa CLUB | H174: {=IF($A174="","", IF( OR( $A174=23, AND($A174>=32,$A174<=50) ), IFERROR( INDEX('Daily Sales'!$C:$AG, $A174, MATCH(TEXT($B174,"0"),TEXT('Daily Sales'!$C$2:$AG$2,"0"),0) ), ""), "") )} | I174: {=IF($A174="","", IF( OR( AND($A174>=4,$A174<=8), AND($A174>=12,$A174<=19), AND($A174>=28,$A174<=29) ), IFERROR( INDEX('Daily Sales'!$C:$AG, $A174, MATCH(TEXT($B174,"0"),TEXT('Daily Sales'!$C$2:$AG$2,"0"),0) ), ""), "") )} -> 750000 | J174: =J173+H174-I174 -> #VALUE!
A175: =IF(E175="","",MATCH(E175,'Daily Sales'!B$4:B$51,0)+3) -> 17 | B175: 46179 | C175: DS26-0606 | D175: {=IF($A175="","",INDEX('Daily Sales'!A:A,$A175))} -> 4-2601 | E175: Misc | F175: =E175 -> Misc | H175: {=IF($A175="","", IF( OR( $A175=23, AND($A175>=32,$A175<=50) ), IFERROR( INDEX('Daily Sales'!$C:$AG, $A175, MATCH(TEXT($B175,"0"),TEXT('Daily Sales'!$C$2:$AG$2,"0"),0) ), ""), "") )} | I175: {=IF($A175="","", IF( OR( AND($A175>=4,$A175<=8), AND($A175>=12,$A175<=19), AND($A175>=28,$A175<=29) ), IFERROR( INDEX('Daily Sales'!$C:$AG, $A175, MATCH(TEXT($B175,"0"),TEXT('Daily Sales'!$C$2:$AG$2,"0"),0) ), ""), "") )} -> 0 | J175: =J174+H175-I175 -> #VALUE!
A176: =IF(E176="","",MATCH(E176,'Daily Sales'!B$4:B$51,0)+3) -> 19 | B176: 46179 | C176: DS26-0606 | D176: {=IF($A176="","",INDEX('Daily Sales'!A:A,$A176))} -> 4-2500 | E176: Sales Ticket | F176: =E176 -> Sales Ticket | H176: {=IF($A176="","", IF( OR( $A176=23, AND($A176>=32,$A176<=50) ), IFERROR( INDEX('Daily Sales'!$C:$AG, $A176, MATCH(TEXT($B176,"0"),TEXT('Daily Sales'!$C$2:$AG$2,"0"),0) ), ""), "") )} | I176: {=IF($A176="","", IF( OR( AND($A176>=4,$A176<=8), AND($A176>=12,$A176<=19), AND($A176>=28,$A176<=29) ), IFERROR( INDEX('Daily Sales'!$C:$AG, $A176, MATCH(TEXT($B176,"0"),TEXT('Daily Sales'!$C$2:$AG$2,"0"),0) ), ""), "") )} -> 36321255 | J176: =J175+H176-I176 -> #VALUE!
A177: =IF(E177="","",MATCH(E177,'Daily Sales'!B$4:B$51,0)+3) -> 28 | B177: 46179 | C177: DS26-0606 | D177: {=IF($A177="","",INDEX('Daily Sales'!A:A,$A177))} -> 2-2106 | E177: Service Charges 7% | F177: =E177 -> Service Charges 7% | H177: {=IF($A177="","", IF( OR( $A177=23, AND($A177>=32,$A177<=50) ), IFERROR( INDEX('Daily Sales'!$C:$AG, $A177, MATCH(TEXT($B177,"0"),TEXT('Daily Sales'!$C$2:$AG$2,"0"),0) ), ""), "") )} | I177: {=IF($A177="","", IF( OR( AND($A177>=4,$A177<=8), AND($A177>=12,$A177<=19), AND($A177>=28,$A177<=29) ), IFERROR( INDEX('Daily Sales'!$C:$AG, $A177, MATCH(TEXT($B177,"0"),TEXT('Daily Sales'!$C$2:$AG$2,"0"),0) ), ""), "") )} -> 10084568 | J177: =J176+H177-I177 -> #VALUE!
...

Sheet TB
B1: TRIAL BALANCE
B2: =GL!I1 -> PT TAMAN BINTANG BALI
B3: =GL!I3 -> MONTH OF June 2026
B4: DESCRIPTION | D4: QTY | E4: TRIAL BALANCF | I4: TRIAL BALANCE (MTD) | N4: TRIAL BALANCE (YTD) | P4: ADJUSMENT ENTRY | R4: ADJUSTED ENTRY | T4: PROFIT AND LOST | V4: EQUITY | X4: BALANCE
E5: DB | F5: CR | I5: DB | J5: CR | N5: DB | O5: CR | P5: DB | Q5: CR | R5: DB | S5: CR | T5: DB | U5: CR | V5: DB | W5: CR | X5: DB | Y5: CR
B7: 1-0000 | C7: Assets
B8: 1-1000 | C8: Current Assets
B9: 1-1100 | C9: Cash | E9: =SUM(E10:E11) -> 638838402 | F9: =SUM(F10:F11) -> 642880644 | I9: =SUM(I10:I11) -> 10730518 | J9: =SUM(J10:J11) -> 14772760 | K9: =SUM(K10:K11) -> 0 | L9: =SUM(L10:L11) -> 25194675 | M9: =SUM(M10:M11) -> 0 | N9: =SUM(N10:N11) -> 21152433 | O9: =SUM(O10:O11) -> 0 | P9: =SUM(P10:P11) -> 0 | ... Y9: =SUM(Y10:Y11) -> 0
B10: 1-1106 | C10: Petty Cash IDR - on General Cashier | E10: =SUMIF(GL!$D$6:$D$6487,B10,GL!$H$6:$H$6487) -> 326805581 | F10: =SUMIF(GL!$D$6:$D$6487,B10,GL!$I$6:$I$6487) -> 316075063 | I10: =IF(E10>F10,E10-F10,0) -> 10730518 | J10: =IF(F10>E10,F10-E10,0) -> 0 | L10: 5921915 | N10: =IF(I10+L10>J10+M10,(I10+L10)-(J10+M10),0) -> 16652433 | O10: =IF(J10+M10>I10+L10,(J10+M10)-(I10+L10),0) -> 0 | P10: =SUMIF(GL!$D$6488:$D$6532,B10,GL!$H$6488:$H$6532) -> 0 | Q10: =SUMIF(GL!$D$6408:$D$6452,B10,GL!$I$6408:$I$6452) -> 0 | R10: =P10+N10 -> 16652433 | S10: =Q10+O10 -> 0 | X10: =IF(R10>S10,R10-S10,0) -> 16652433 | Y10: =IF(S10>R10,S10-R10,0) -> 0 | Z10: V | AA10: 16652433 | AB10: =X10-AA10 -> 0
B11: 1-1119 | C11: Petty Cash IDR - on Bar Cashier | E11: =SUMIF(GL!$D$6:$D$6487,B11,GL!$H$6:$H$6487) -> 312032821 | F11: =SUMIF(GL!$D$6:$D$6487,B11,GL!$I$6:$I$6487) -> 326805581 | I11: =IF(E11>F11,E11-F11,0) -> 0 | J11: =IF(F11>E11,F11-E11,0) -> 14772760 | L11: 19272760 | N11: =IF(I11+L11>J11+M11,(I11+L11)-(J11+M11),0) -> 4500000 | O11: =IF(J11+M11>I11+L11,(J11+M11)-(I11+L11),0) -> 0 | P11: =SUMIF(GL!$D$6488:$D$6532,B11,GL!$H$6488:$H$6532) -> 0 | Q11: =SUMIF(GL!$D$6408:$D$6452,B11,GL!$I$6408:$I$6452) -> 0 | R11: =P11+N11 -> 4500000 | S11: =Q11+O11 -> 0 | X11: =IF(R11>S11,R11-S11,0) -> 4500000 | Y11: =IF(S11>R11,S11-R11,0) -> 0
B12: 1-1120 | C12: Cash in banks | E12: =SUM(E13:E22) -> 3.3949518e+09 | F12: =SUM(F13:F22) -> 3.5681557e+09 | G12: =SUM(G13:G22) -> 0 | H12: =SUM(H13:H22) -> 0 | I12: =SUM(I13:I22) -> 1400779 | J12: =SUM(J13:J22) -> 1.7460464e+08 | K12: =SUM(K13:K22) -> 0 | L12: =SUM(L13:L22) -> 496257319 | ... Y12: =SUM(Y13:Y22) -> 0
B13: 1-1121 | C13: Mandiri KBB 2 | E13: =SUMIF(GL!$D$6:$D$6487,B13,GL!$H$6:$H$6487) -> 0 | F13: =SUMIF(GL!$D$6:$D$6487,B13,GL!$I$6:$I$6487) -> 0 | I13: =IF(E13>F13,E13-F13,0) -> 0 | J13: =IF(F13>E13,F13-E13,0) -> 0 | N13: =IF(I13+L13>J13+M13,(I13+L13)-(J13+M13),0) -> 0 | O13: =IF(J13+M13>I13+L13,(J13+M13)-(I13+L13),0) -> 0 | P13: =SUMIF(GL!$D$6488:$D$6532,B13,GL!$H$6488:$H$6532) -> 0 | Q13: =SUMIF(GL!$D$6408:$D$6452,B13,GL!$I$6408:$I$6452) -> 0 | R13: =P13+N13 -> 0 | S13: =Q13+O13 -> 0 | X13: =IF(R13>S13,R13-S13,0) -> 0 | Y13: =IF(S13>R13,S13-R13,0) -> 0
B14: 1-1122 | C14: Mandiri TBB USD | E14: =SUMIF(GL!$D$6:$D$6487,B14,GL!$H$6:$H$6487) -> 223920000 | F14: =SUMIF(GL!$D$6:$D$6487,B14,GL!$I$6:$I$6487) -> 223703177 | I14: =IF(E14>F14,E14-F14,0) -> 216823 | J14: =IF(F14>E14,F14-E14,0) -> 0 | L14: 9215363 | N14: =IF(I14+L14>J14+M14,(I14+L14)-(J14+M14),0) -> 9432186 | O14: =IF(J14+M14>I14+L14,(J14+M14)-(I14+L14),0) -> 0 | P14: =SUMIF(GL!$D$6488:$D$6532,B14,GL!$H$6488:$H$6532) -> 0 | Q14: =SUMIF(GL!$D$6408:$D$6452,B14,GL!$I$6408:$I$6452) -> 0 | R14: =P14+N14 -> 9432186 | S14: =Q14+O14 -> 0 | X14: =IF(R14>S14,R14-S14,0) -> 9432186 | Y14: =IF(S14>R14,S14-R14,0) -> 0 | Z14: V | AA14: =528.71*17840 -> 9432186.4 | AB14: =X14-AA14 -> -0.4
B15: 1-1123 | C15: Mandiri TBB IDR | E15: =SUMIF(GL!$D$6:$D$6487,B15,GL!$H$6:$H$6487) -> 1.8782882e+09 | F15: =SUMIF(GL!$D$6:$D$6487,B15,GL!$I$6:$I$6487) -> 1.9757022e+09 | I15: =IF(E15>F15,E15-F15,0) -> 0 | J15: =IF(F15>E15,F15-E15,0) -> 97413971 | L15: 98857588 | N15: =IF(I15+L15>J15+M15,(I15+L15)-(J15+M15),0) -> 1443616.9 | O15: =IF(J15+M15>I15+L15,(J15+M15)-(I15+L15),0) -> 0 | P15: =SUMIF(GL!$D$6488:$D$6532,B15,GL!$H$6488:$H$6532) -> 0 | Q15: =SUMIF(GL!$D$6408:$D$6452,B15,GL!$I$6408:$I$6452) -> 0 | R15: =P15+N15 -> 1443616.9 | S15: =Q15+O15 -> 0 | X15: =IF(R15>S15,R15-S15,0) -> 1443616.9 | Y15: =IF(S15>R15,S15-R15,0) -> 0 | Z15: V | AA15: 1443616.9 | AB15: =X15-Y15-AA15 -> -0.001999073
B16: 1-1124 | C16: BANK BRI | E16: =SUMIF(GL!$D$6:$D$6487,B16,GL!$H$6:$H$6487) -> 16898675 | F16: =SUMIF(GL!$D$6:$D$6487,B16,GL!$I$6:$I$6487) -> 18557500 | I16: =IF(E16>F16,E16-F16,0) -> 0 | J16: =IF(F16>E16,F16-E16,0) -> 1658825 | L16: 2008743 | N16: =IF(I16+L16>J16+M16,(I16+L16)-(J16+M16),0) -> 349918 | O16: =IF(J16+M16>I16+L16,(J16+M16)-(I16+L16),0) -> 0 | P16: =SUMIF(GL!$D$6488:$D$6532,B16,GL!$H$6488:$H$6532) -> 0 | Q16: =SUMIF(GL!$D$6408:$D$6452,B16,GL!$I$6408:$I$6452) -> 0 | R16: =P16+N16 -> 349918 | S16: =Q16+O16 -> 0 | X16: =IF(R16>S16,R16-S16,0) -> 349918 | Y16: =IF(S16>R16,S16-R16,0) -> 0 | Z16: V | AA16: 349918 | AB16: =X16-Y16-AA16 -> 0.0019999966
B17: 1-1125 | C17: Mandiri GRAB | E17: =SUMIF(GL!$D$6:$D$6487,B17,GL!$H$6:$H$6487) -> 8549673 | F17: =SUMIF(GL!$D$6:$D$6487,B17,GL!$I$6:$I$6487) -> 8977500 | I17: =IF(E17>F17,E17-F17,0) -> 0 | J17: =IF(F17>E17,F17-E17,0) -> 427827 | L17: 1452954 | N17: =IF(I17+L17>J17+M17,(I17+L17)-(J17+M17),0) -> 1025127 | O17: =IF(J17+M17>I17+L17,(J17+M17)-(I17+L17),0) -> 0 | P17: =SUMIF(GL!$D$6488:$D$6532,B17,GL!$H$6488:$H$6532) -> 0 | Q17: =SUMIF(GL!$D$6408:$D$6452,B17,GL!$I$6408:$I$6452) -> 0 | R17: =P17+N17 -> 1025127 | S17: =Q17+O17 -> 0 | X17: =IF(R17>S17,R17-S17,0) -> 1025127 | Y17: =IF(S17>R17,S17-R17,0) -> 0 | Z17: V | AA17: 1025127 | AB17: =X17-Y17-AA17 -> 0
B18: 1-1126 | C18: Cimb Niaga TBB | E18: =SUMIF(GL!$D$6:$D$6487,B18,GL!$H$6:$H$6487) -> 102154080 | F18: =SUMIF(GL!$D$6:$D$6487,B18,GL!$I$6:$I$6487) -> 102157500 | I18: =IF(E18>F18,E18-F18,0) -> 0 | J18: =IF(F18>E18,F18-E18,0) -> 3420 | L18: 1058653 | N18: =IF(I18+L18>J18+M18,(I18+L18)-(J18+M18),0) -> 1055233 | O18: =IF(J18+M18>I18+L18,(J18+M18)-(I18+L18),0) -> 0 | P18: =SUMIF(GL!$D$6488:$D$6532,B18,GL!$H$6488:$H$6532) -> 0 | Q18: =SUMIF(GL!$D$6408:$D$6452,B18,GL!$I$6408:$I$6452) -> 0 | R18: =P18+N18 -> 1055233 | S18: =Q18+O18 -> 0 | X18: =IF(R18>S18,R18-S18,0) -> 1055233 | Y18: =IF(S18>R18,S18-R18,0) -> 0 | Z18: V | AA18: 1055233.4 | AB18: =X18-AA18 -> -0.43
B19: 1-1127 | C19: BCA TBB | E19: =SUMIF(GL!$D$6:$D$6487,B19,GL!$H$6:$H$6487) -> 1.1633698e+09 | F19: =SUMIF(GL!$D$6:$D$6487,B19,GL!$I$6:$I$6487) -> 1238470370 | I19: =IF(E19>F19,E19-F19,0) -> 0 | J19: =IF(F19>E19,F19-E19,0) -> 75100595 | L19: 75507728 | N19: =IF(I19+L19>J19+M19,(I19+L19)-(J19+M19),0) -> 407132.89 | O19: =IF(J19+M19>I19+L19,(J19+M19)-(I19+L19),0) -> 0 | P19: =SUMIF(GL!$D$6488:$D$6532,B19,GL!$H$6488:$H$6532) -> 0 | Q19: =SUMIF(GL!$D$6408:$D$6452,B19,GL!$I$6408:$I$6452) -> 0 | R19: =P19+N19 -> 407132.89 | S19: =Q19+O19 -> 0 | X19: =IF(R19>S19,R19-S19,0) -> 407132.89 | Y19: =IF(S19>R19,S19-R19,0) -> 0 | Z19: V | AA19: 407132.89 | AB19: =X19-Y19-AA19 -> 0.0019999599
B20: 1-1128 | C20: MEGA BANK | E20: =SUMIF(GL!$D$6:$D$6487,B20,GL!$H$6:$H$6487) -> 0 | F20: =SUMIF(GL!$D$6:$D$6487,B20,GL!$I$6:$I$6487) -> 0 | I20: =IF(E20>F20,E20-F20,0) -> 0 | J20: =IF(F20>E20,F20-E20,0) -> 0 | N20: =IF(I20+L20>J20+M20,(I20+L20)-(J20+M20),0) -> 0 | O20: =IF(J20+M20>I20+L20,(J20+M20)-(I20+L20),0) -> 0 | P20: =SUMIF(GL!$D$6488:$D$6532,B20,GL!$H$6488:$H$6532) -> 0 | Q20: =SUMIF(GL!$D$6408:$D$6452,B20,GL!$I$6408:$I$6452) -> 0 | R20: =P20+N20 -> 0 | S20: =Q20+O20 -> 0 | X20: =IF(R20>S20,R20-S20,0) -> 0 | Y20: =IF(S20>R20,S20-R20,0) -> 0
B21: 1-1129 | C21: STARXP | E21: =SUMIF(GL!$D$6:$D$6487,B21,GL!$H$6:$H$6487) -> 1771385 | F21: =SUMIF(GL!$D$6:$D$6487,B21,GL!$I$6:$I$6487) -> 587429 | I21: =IF(E21>F21,E21-F21,0) -> 1183956 | J21: =IF(F21>E21,F21-E21,0) -> 0 | L21: 308156290 | N21: =IF(I21+L21>J21+M21,(I21+L21)-(J21+M21),0) -> 309340246 | O21: =IF(J21+M21>I21+L21,(J21+M21)-(I21+L21),0) -> 0 | P21: =SUMIF(GL!$D$6488:$D$6532,B21,GL!$H$6488:$H$6532) -> 0 | Q21: =SUMIF(GL!$D$6408:$D$6452,B21,GL!$I$6408:$I$6452) -> 0 | R21: =P21+N21 -> 309340246 | S21: =Q21+O21 -> 0 | X21: =IF(R21>S21,R21-S21,0) -> 309340246 | Y21: =IF(S21>R21,S21-R21,0) -> 0
B22: 1-1130 | C22: BPR DEWATA CHANDRADANA | E22: =SUMIF(GL!$D$6:$D$6487,B22,GL!$H$6:$H$6487) -> 0 | F22: =SUMIF(GL!$D$6:$D$6487,B22,GL!$I$6:$I$6487) -> 0 | I22: =IF(E22>F22,E22-F22,0) -> 0 | J22: =IF(F22>E22,F22-E22,0) -> 0 | N22: =IF(I22+L22>J22+M22,(I22+L22)-(J22+M22),0) -> 0 | O22: =IF(J22+M22>I22+L22,(J22+M22)-(I22+L22),0) -> 0 | P22: =SUMIF(GL!$D$6488:$D$6532,B22,GL!$H$6488:$H$6532) -> 0 | Q22: =SUMIF(GL!$D$6408:$D$6452,B22,GL!$I$6408:$I$6452) -> 0 | R22: =P22+N22 -> 0 | S22: =Q22+O22 -> 0 | X22: =IF(R22>S22,R22-S22,0) -> 0 | Y22: =IF(S22>R22,S22-R22,0) -> 0
B23: 1-1199 | C23: Total Cash and Cash At Bank | E23: =E12+E9 -> 4.0337902e+09 | F23: =F12+F9 -> 4.2110363e+09 | I23: =I12+I9 -> 12131297 | J23: =J12+J9 -> 1.893774e+08 | L23: =L9+L12 -> 521451994 | M23: =M9+M12 -> 0 | N23: =N12+N9 -> 3.4420589e+08 | O23: =O12+O9 -> 0 | P23: =P12+P9 -> 0 | Q23: =Q12+Q9 -> 0 | R23: =R12+R9 -> 3.4420589e+08 | S23: =S12+S9 -> 0 | T23: =T12+T9 -> 0 | U23: =U12+U9 -> 0 | ... Y23: =Y12+Y9 -> 0
B25: 1-1200 | C25: Account Receivables | E25: =SUM(E26:E28) -> 52938163 | F25: =SUM(F26:F28) -> 65886554 | G25: =SUM(G26:G28) -> 0 | H25: =SUM(H26:H28) -> 0 | I25: =SUM(I26:I28) -> 0 | J25: =SUM(J26:J28) -> 12948391 | K25: =SUM(K26:K28) -> 0 | L25: =SUM(L26:L28) -> 120303822 | ... Y25: =SUM(Y26:Y28) -> 0
B26: 1-1201 | C26: Accounts receivable Trade | E26: =SUMIF(GL!$D$6:$D$6487,B26,GL!$H$6:$H$6487) -> 0 | F26: =SUMIF(GL!$D$6:$D$6487,B26,GL!$I$6:$I$6487) -> 0 | I26: =IF(E26>F26,E26-F26,0) -> 0 | J26: =IF(F26>E26,F26-E26,0) -> 0 | N26: =IF(I26+L26>J26+M26,(I26+L26)-(J26+M26),0) -> 0 | O26: =IF(J26+M26>I26+L26,(J26+M26)-(I26+L26),0) -> 0 | P26: =SUMIF(GL!$D$6488:$D$6532,B26,GL!$H$6488:$H$6532) -> 0 | Q26: =SUMIF(GL!$D$6408:$D$6452,B26,GL!$I$6408:$I$6452) -> 0 | R26: =P26+N26 -> 0 | S26: =Q26+O26 -> 0 | X26: =IF(R26>S26,R26-S26,0) -> 0 | Y26: =IF(S26>R26,S26-R26,0) -> 0
B27: 1-1202 | C27: City Ledger | E27: =SUMIF(GL!$D$6:$D$6487,B27,GL!$H$6:$H$6487) -> 23626023 | F27: =SUMIF(GL!$D$6:$D$6487,B27,GL!$I$6:$I$6487) -> 23957403 | I27: =IF(E27>F27,E27-F27,0) -> 0 | J27: =IF(F27>E27,F27-E27,0) -> 331380 | L27: 81266358 | N27: =IF(I27+L27>J27+M27,(I27+L27)-(J27+M27),0) -> 80934978 | O27: =IF(J27+M27>I27+L27,(J27+M27)-(I27+L27),0) -> 0 | P27: =SUMIF(GL!$D$6488:$D$6532,B27,GL!$H$6488:$H$6532) -> 0 | Q27: =SUMIF(GL!$D$6408:$D$6452,B27,GL!$I$6408:$I$6452) -> 0 | R27: =P27+N27 -> 80934978 | S27: =Q27+O27 -> 0 | X27: =IF(R27>S27,R27-S27,0) -> 80934978 | Y27: =IF(S27>R27,S27-R27,0) -> 0
B28: 1-1203 | C28: Cash Advance | E28: =SUMIF(GL!$D$6:$D$6487,B28,GL!$H$6:$H$6487) -> 29312140 | F28: =SUMIF(GL!$D$6:$D$6487,B28,GL!$I$6:$I$6487) -> 41929151 | I28: =IF(E28>F28,E28-F28,0) -> 0 | J28: =IF(F28>E28,F28-E28,0) -> 12617011 | L28: 39037464 | N28: =IF(I28+L28>J28+M28,(I28+L28)-(J28+M28),0) -> 26420453 | O28: =IF(J28+M28>I28+L28,(J28+M28)-(I28+L28),0) -> 0 | P28: =SUMIF(GL!$D$6488:$D$6532,B28,GL!$H$6488:$H$6532) -> 0 | Q28: =SUMIF(GL!$D$6408:$D$6452,B28,GL!$I$6408:$I$6452) -> 0 | R28: =P28+N28 -> 26420453 | S28: =Q28+O28 -> 0 | X28: =IF(R28>S28,R28-S28,0) -> 26420453 | Y28: =IF(S28>R28,S28-R28,0) -> 0
B29: 1-1210 | C29: AR Credit Card | E29: =SUM(E30:E37) -> 1988881010 | F29: =SUM(F30:F37) -> 2116535501 | G29: =SUM(G30:G37) -> 0 | H29: =SUM(H30:H37) -> 0 | I29: =SUM(I30:I37) -> 143750 | J29: =SUM(J30:J37) -> 127798241 | K29: =SUM(K30:K37) -> 0 | L29: =SUM(L30:L37) -> 192358312 | ... Y29: =SUM(Y30:Y37) -> 0
B30: 1-1211 | C30: GOPAY | E30: =SUMIF(GL!$D$6:$D$6487,B30,GL!$H$6:$H$6487) -> 222000 | F30: =SUMIF(GL!$D$6:$D$6487,B30,GL!$I$6:$I$6487) -> 222000 | I30: =IF(E30>F30,E30-F30,0) -> 0 | J30: =IF(F30>E30,F30-E30,0) -> 0 | N30: =IF(I30+L30>J30+M30,(I30+L30)-(J30+M30),0) -> 0 | O30: =IF(J30+M30>I30+L30,(J30+M30)-(I30+L30),0) -> 0 | P30: =SUMIF(GL!$D$6488:$D$6532,B30,GL!$H$6488:$H$6532) -> 0 | Q30: =SUMIF(GL!$D$6408:$D$6452,B30,GL!$I$6408:$I$6452) -> 0 | R30: =P30+N30 -> 0 | S30: =Q30+O30 -> 0 | X30: =IF(R30>S30,R30-S30,0) -> 0 | Y30: =IF(S30>R30,S30-R30,0) -> 0
B31: 1-1212 | C31: Mega Card | E31: =SUMIF(GL!$D$6:$D$6487,B31,GL!$H$6:$H$6487) -> 0 | F31: =SUMIF(GL!$D$6:$D$6487,B31,GL!$I$6:$I$6487) -> 0 | I31: =IF(E31>F31,E31-F31,0) -> 0 | J31: =IF(F31>E31,F31-E31,0) -> 0 | N31: =IF(I31+L31>J31+M31,(I31+L31)-(J31+M31),0) -> 0 | O31: =IF(J31+M31>I31+L31,(J31+M31)-(I31+L31),0) -> 0 | P31: =SUMIF(GL!$D$6488:$D$6532,B31,GL!$H$6488:$H$6532) -> 0 | Q31: =SUMIF(GL!$D$6408:$D$6452,B31,GL!$I$6408:$I$6452) -> 0 | R31: =P31+N31 -> 0 | S31: =Q31+O31 -> 0 | X31: =IF(R31>S31,R31-S31,0) -> 0 | Y31: =IF(S31>R31,S31-R31,0) -> 0
B32: 1-1213 | C32: Mandiri Card TBB | E32: =SUMIF(GL!$D$6:$D$6487,B32,GL!$H$6:$H$6487) -> 1543583788 | F32: =SUMIF(GL!$D$6:$D$6487,B32,GL!$I$6:$I$6487) -> 1608132299 | I32: =IF(E32>F32,E32-F32,0) -> 0 | J32: =IF(F32>E32,F32-E32,0) -> 64548511 | L32: 122329062 | N32: =IF(I32+L32>J32+M32,(I32+L32)-(J32+M32),0) -> 57780551 | O32: =IF(J32+M32>I32+L32,(J32+M32)-(I32+L32),0) -> 0 | P32: =SUMIF(GL!$D$6488:$D$6532,B32,GL!$H$6488:$H$6532) -> 0 | Q32: =SUMIF(GL!$D$6408:$D$6452,B32,GL!$I$6408:$I$6452) -> 0 | R32: =P32+N32 -> 57780551 | S32: =Q32+O32 -> 0 | X32: =IF(R32>S32,R32-S32,0) -> 57780551 | Y32: =IF(S32>R32,S32-R32,0) -> 0 | Z32: V | AA32: 57780551 | AB32: =X32-AA32 -> 0
B33: 1-1214 | C33: BRI CARD CC | E33: =SUMIF(GL!$D$6:$D$6487,B33,GL!$H$6:$H$6487) -> 5877351 | F33: =SUMIF(GL!$D$6:$D$6487,B33,GL!$I$6:$I$6487) -> 5877351 | I33: =IF(E33>F33,E33-F33,0) -> 0 | J33: =IF(F33>E33,F33-E33,0) -> 0 | N33: =IF(I33+L33>J33+M33,(I33+L33)-(J33+M33),0) -> 0 | O33: =IF(J33+M33>I33+L33,(J33+M33)-(I33+L33),0) -> 0 | P33: =SUMIF(GL!$D$6488:$D$6532,B33,GL!$H$6488:$H$6532) -> 0 | Q33: =SUMIF(GL!$D$6408:$D$6452,B33,GL!$I$6408:$I$6452) -> 0 | R33: =P33+N33 -> 0 | S33: =Q33+O33 -> 0 | X33: =IF(R33>S33,R33-S33,0) -> 0 | Y33: =IF(S33>R33,S33-R33,0) -> 0
B34: 1-1215 | C34: GRAB / OVO | E34: =SUMIF(GL!$D$6:$D$6487,B34,GL!$H$6:$H$6487) -> 4617625 | F34: =SUMIF(GL!$D$6:$D$6487,B34,GL!$I$6:$I$6487) -> 4473875 | I34: =IF(E34>F34,E34-F34,0) -> 143750 | J34: =IF(F34>E34,F34-E34,0) -> 0 | N34: =IF(I34+L34>J34+M34,(I34+L34)-(J34+M34),0) -> 143750 | O34: =IF(J34+M34>I34+L34,(J34+M34)-(I34+L34),0) -> 0 | P34: =SUMIF(GL!$D$6488:$D$6532,B34,GL!$H$6488:$H$6532) -> 0 | Q34: =SUMIF(GL!$D$6408:$D$6452,B34,GL!$I$6408:$I$6452) -> 0 | R34: =P34+N34 -> 143750 | S34: =Q34+O34 -> 0 | X34: =IF(R34>S34,R34-S34,0) -> 143750 | Y34: =IF(S34>R34,S34-R34,0) -> 0 | Z34: V | AA34: 143750 | AB34: =X34-AA34 -> 0
B35: 1-1216 | C35: Credit Card Cimb Niaga TBB | E35: =SUMIF(GL!$D$6:$D$6487,B35,GL!$H$6:$H$6487) -> 80612915 | F35: =SUMIF(GL!$D$6:$D$6487,B35,GL!$I$6:$I$6487) -> 103334000 | I35: =IF(E35>F35,E35-F35,0) -> 0 | J35: =IF(F35>E35,F35-E35,0) -> 22721085 | L35: 22721085 | N35: =IF(I35+L35>J35+M35,(I35+L35)-(J35+M35),0) -> 0 | O35: =IF(J35+M35>I35+L35,(J35+M35)-(I35+L35),0) -> 0 | P35: =SUMIF(GL!$D$6488:$D$6532,B35,GL!$H$6488:$H$6532) -> 0 | Q35: =SUMIF(GL!$D$6408:$D$6452,B35,GL!$I$6408:$I$6452) -> 0 | R35: =P35+N35 -> 0 | S35: =Q35+O35 -> 0 | X35: =IF(R35>S35,R35-S35,0) -> 0 | Y35: =IF(S35>R35,S35-R35,0) -> 0
B36: 1-1217 | C36: BCA Card TBB | E36: =SUMIF(GL!$D$6:$D$6487,B36,GL!$H$6:$H$6487) -> 353967331 | F36: =SUMIF(GL!$D$6:$D$6487,B36,GL!$I$6:$I$6487) -> 394495976 | I36: =IF(E36>F36,E36-F36,0) -> 0 | J36: =IF(F36>E36,F36-E36,0) -> 40528645 | L36: 47308165 | N36: =IF(I36+L36>J36+M36,(I36+L36)-(J36+M36),0) -> 6779520 | O36: =IF(J36+M36>I36+L36,(J36+M36)-(I36+L36),0) -> 0 | P36: =SUMIF(GL!$D$6488:$D$6532,B36,GL!$H$6488:$H$6532) -> 0 | Q36: =SUMIF(GL!$D$6408:$D$6452,B36,GL!$I$6408:$I$6452) -> 0 | R36: =P36+N36 -> 6779520 | S36: =Q36+O36 -> 0 | X36: =IF(R36>S36,R36-S36,0) -> 6779520 | Y36: =IF(S36>R36,S36-R36,0) -> 0 | Z36: V | AA36: 6779520 | AB36: =X36-AA36 -> 0
B37: 1-1218 | C37: STARXP | E37: =SUMIF(GL!$D$6:$D$6487,B37,GL!$H$6:$H$6487) -> 0 | F37: =SUMIF(GL!$D$6:$D$6487,B37,GL!$I$6:$I$6487) -> 0 | I37: =IF(E37>F37,E37-F37,0) -> 0 | J37: =IF(F37>E37,F37-E37,0) -> 0 | N37: =IF(I37+L37>J37+M37,(I37+L37)-(J37+M37),0) -> 0 | O37: =IF(J37+M37>I37+L37,(J37+M37)-(I37+L37),0) -> 0 | P37: =SUMIF(GL!$D$6488:$D$6532,B37,GL!$H$6488:$H$6532) -> 0 | Q37: =SUMIF(GL!$D$6408:$D$6452,B37,GL!$I$6408:$I$6452) -> 0 | R37: =P37+N37 -> 0 | S37: =Q37+O37 -> 0 | X37: =IF(R37>S37,R37-S37,0) -> 0 | Y37: =IF(S37>R37,S37-R37,0) -> 0
B39: 1-1220 | C39: Related Party | E39: =SUM(E40) -> 39325785 | F39: =SUM(F40) -> 25770573 | G39: =SUM(G40) -> 0 | H39: =SUM(H40) -> 0 | I39: =SUM(I40) -> 13555212 | J39: =SUM(J40) -> 0 | K39: =SUM(K40) -> 0 | L39: =SUM(L40) -> 18738149444 | ... Y39: =SUM(Y40) -> 0
B40: 1-1221 | C40: Intercompany Receivable – Treasury StarPOINTS | E40: =SUMIF(GL!$D$6:$D$6487,B40,GL!$H$6:$H$6487) -> 39325785 | F40: =SUMIF(GL!$D$6:$D$6487,B40,GL!$I$6:$I$6487) -> 25770573 | I40: =IF(E40>F40,E40-F40,0) -> 13555212 | J40: =IF(F40>E40,F40-E40,0) -> 0 | L40: 18738149444 | N40: =IF(I40+L40>J40+M40,(I40+L40)-(J40+M40),0) -> 18751704656 | O40: =IF(J40+M40>I40+L40,(J40+M40)-(I40+L40),0) -> 0 | P40: =SUMIF(GL!$D$6488:$D$6532,B40,GL!$H$6488:$H$6532) -> 0 | Q40: =SUMIF(GL!$D$6408:$D$6452,B40,GL!$I$6408:$I$6452) -> 0 | R40: =P40+N40 -> 18751704656 | S40: =Q40+O40 -> 0 | X40: =IF(R40>S40,R40-S40,0) -> 18751704656 | Y40: =IF(S40>R40,S40-R40,0) -> 0
B41: 1-1299 | C41: Total Account Receivables | E41: =E39+E29+E25 -> 2081144958 | F41: =F39+F29+F25 -> 2208192628 | G41: =G39+G29+G25 -> 0 | H41: =H39+H29+H25 -> 0 | I41: =I39+I29+I25 -> 13698962 | J41: =J39+J29+J25 -> 140746632 | K41: =K39+K29+K25 -> 0 | L41: =L39+L29+L25 -> 19050811578 | ... Y41: =Y39+Y29+Y25 -> 0
B43: 1-1300 | C43: INVENTORY
B44: 1-1301 | C44: INVENTORY FOOD | D44: =SUM(D45:D333) -> 2458.0855 | E44: =SUM(E45:E333) -> 82057462 | F44: =SUM(F45:F333) -> 0 | G44: =SUM(G45:G333) -> 0 | H44: =SUM(H45:H333) -> 0 | I44: =SUM(I45:I333) -> 82057462 | J44: =SUM(J45:J333) -> 0 | K44: =SUM(K45:K333) -> 0 | L44: 34932752 | N44: =IF(I44+L44>J44+M44,(I44+L44)-(J44+M44),0) -> 1.1699021e+08 | O44: =IF(J44+M44>I44+L44,(J44+M44)-(I44+L44),0) -> 0 | P44: =SUMIF(GL!$D$6488:$D$6532,B44,GL!$H$6488:$H$6532) -> 0 | Q44: =GL!H5870 -> 71182006 | R44: =P44+N44 -> 1.1699021e+08 | S44: =Q44+O44 -> 71182006 | X44: =IF(R44>S44,R44-S44,0) -> 45808208 | Y44: =IF(S44>R44,S44-R44,0) -> 0
C45: MEAT & FISH | D45: =SUMIF(GL!$D$5:$D$6505,B45,GL!$G$5:$G$6505) -> 0 | E45: =SUMIF(GL!$D$6:$D$6487,B45,GL!$H$6:$H$6487) -> 0 | F45: =SUMIF(GL!$D$6:$D$6487,B45,GL!$I$6:$I$6487) -> 0 | I45: =IF(E45>F45,E45-F45,0) -> 0 | J45: =IF(F45>E45,F45-E45,0) -> 0 | N45: =IF(I45+L45>J45+M45,(I45+L45)-(J45+M45),0) -> 0 | O45: =IF(J45+M45>I45+L45,(J45+M45)-(I45+L45),0) -> 0 | P45: =SUMIF(GL!$D$6488:$D$6532,B45,GL!$H$6488:$H$6532) -> 0 | Q45: =SUMIF(GL!$D$6408:$D$6452,B45,GL!$I$6408:$I$6452) -> 0 | R45: =P45+N45 -> 0 | S45: =Q45+O45 -> 0 | X45: =IF(R45>S45,R45-S45,0) -> 0 | Y45: =IF(S45>R45,S45-R45,0) -> 0
B46: M001 | C46: Minced Beef | D46: =SUMIF(GL!$D$5:$D$6505,B46,GL!$G$5:$G$6505) -> 20.14 | E46: =SUMIF(GL!$D$6:$D$6487,B46,GL!$H$6:$H$6487) -> 2548780 | F46: =SUMIF(GL!$D$6:$D$6487,B46,GL!$I$6:$I$6487) -> 0 | I46: =IF(E46>F46,E46-F46,0) -> 2548780 | J46: =IF(F46>E46,F46-E46,0) -> 0 | N46: =IF(I46+L46>J46+M46,(I46+L46)-(J46+M46),0) -> 2548780 | O46: =IF(J46+M46>I46+L46,(J46+M46)-(I46+L46),0) -> 0 | P46: =SUMIF(GL!$D$6488:$D$6532,B46,GL!$H$6488:$H$6532) -> 0 | Q46: =SUMIF(GL!$D$6408:$D$6452,B46,GL!$I$6408:$I$6452) -> 0 | R46: =P46+N46 -> 2548780 | S46: =Q46+O46 -> 0 | X46: =IF(R46>S46,R46-S46,0) -> 2548780 | Y46: =IF(S46>R46,S46-R46,0) -> 0
B47: M002 | C47: Sausage/Sosis / Beef | D47: =SUMIF(GL!$D$5:$D$6505,B47,GL!$G$5:$G$6505) -> 0 | E47: =SUMIF(GL!$D$6:$D$6487,B47,GL!$H$6:$H$6487) -> 0 | F47: =SUMIF(GL!$D$6:$D$6487,B47,GL!$I$6:$I$6487) -> 0 | I47: =IF(E47>F47,E47-F47,0) -> 0 | J47: =IF(F47>E47,F47-E47,0) -> 0 | N47: =IF(I47+L47>J47+M47,(I47+L47)-(J47+M47),0) -> 0 | O47: =IF(J47+M47>I47+L47,(J47+M47)-(I47+L47),0) -> 0 | P47: =SUMIF(GL!$D$6488:$D$6532,B47,GL!$H$6488:$H$6532) -> 0 | Q47: =SUMIF(GL!$D$6408:$D$6452,B47,GL!$I$6408:$I$6452) -> 0 | R47: =P47+N47 -> 0 | S47: =Q47+O47 -> 0 | X47: =IF(R47>S47,R47-S47,0) -> 0 | Y47: =IF(S47>R47,S47-R47,0) -> 0
B48: M003 | C48: Beef Scalopine | D48: =SUMIF(GL!$D$5:$D$6505,B48,GL!$G$5:$G$6505) -> 0 | E48: =SUMIF(GL!$D$6:$D$6487,B48,GL!$H$6:$H$6487) -> 0 | F48: =SUMIF(GL!$D$6:$D$6487,B48,GL!$I$6:$I$6487) -> 0 | I48: =IF(E48>F48,E48-F48,0) -> 0 | J48: =IF(F48>E48,F48-E48,0) -> 0 | N48: =IF(I48+L48>J48+M48,(I48+L48)-(J48+M48),0) -> 0 | O48: =IF(J48+M48>I48+L48,(J48+M48)-(I48+L48),0) -> 0 | P48: =SUMIF(GL!$D$6488:$D$6532,B48,GL!$H$6488:$H$6532) -> 0 | Q48: =SUMIF(GL!$D$6408:$D$6452,B48,GL!$I$6408:$I$6452) -> 0 | R48: =P48+N48 -> 0 | S48: =Q48+O48 -> 0 | X48: =IF(R48>S48,R48-S48,0) -> 0 | Y48: =IF(S48>R48,S48-R48,0) -> 0
B49: M004 | C49: Beef Pepperoni | D49: =SUMIF(GL!$D$5:$D$6505,B49,GL!$G$5:$G$6505) -> 0 | E49: =SUMIF(GL!$D$6:$D$6487,B49,GL!$H$6:$H$6487) -> 0 | F49: =SUMIF(GL!$D$6:$D$6487,B49,GL!$I$6:$I$6487) -> 0 | I49: =IF(E49>F49,E49-F49,0) -> 0 | J49: =IF(F49>E49,F49-E49,0) -> 0 | N49: =IF(I49+L49>J49+M49,(I49+L49)-(J49+M49),0) -> 0 | O49: =IF(J49+M49>I49+L49,(J49+M49)-(I49+L49),0) -> 0 | P49: =SUMIF(GL!$D$6488:$D$6532,B49,GL!$H$6488:$H$6532) -> 0 | Q49: =SUMIF(GL!$D$6408:$D$6452,B49,GL!$I$6408:$I$6452) -> 0 | R49: =P49+N49 -> 0 | S49: =Q49+O49 -> 0 | X49: =IF(R49>S49,R49-S49,0) -> 0 | Y49: =IF(S49>R49,S49-R49,0) -> 0
B50: M005 | C50: Chorizo Pork | D50: =SUMIF(GL!$D$5:$D$6505,B50,GL!$G$5:$G$6505) -> 4.3 | E50: =SUMIF(GL!$D$6:$D$6487,B50,GL!$H$6:$H$6487) -> 811410 | F50: =SUMIF(GL!$D$6:$D$6487,B50,GL!$I$6:$I$6487) -> 0 | I50: =IF(E50>F50,E50-F50,0) -> 811410 | J50: =IF(F50>E50,F50-E50,0) -> 0 | N50: =IF(I50+L50>J50+M50,(I50+L50)-(J50+M50),0) -> 811410 | O50: =IF(J50+M50>I50+L50,(J50+M50)-(I50+L50),0) -> 0 | P50: =SUMIF(GL!$D$6488:$D$6532,B50,GL!$H$6488:$H$6532) -> 0 | Q50: =SUMIF(GL!$D$6408:$D$6452,B50,GL!$I$6408:$I$6452) -> 0 | R50: =P50+N50 -> 811410 | S50: =Q50+O50 -> 0 | X50: =IF(R50>S50,R50-S50,0) -> 811410 | Y50: =IF(S50>R50,S50-R50,0) -> 0
B51: M006 | C51: Salami | D51: =SUMIF(GL!$D$5:$D$6505,B51,GL!$G$5:$G$6505) -> 0 | E51: =SUMIF(GL!$D$6:$D$6487,B51,GL!$H$6:$H$6487) -> 0 | F51: =SUMIF(GL!$D$6:$D$6487,B51,GL!$I$6:$I$6487) -> 0 | I51: =IF(E51>F51,E51-F51,0) -> 0 | J51: =IF(F51>E51,F51-E51,0) -> 0 | N51: =IF(I51+L51>J51+M51,(I51+L51)-(J51+M51),0) -> 0 | O51: =IF(J51+M51>I51+L51,(J51+M51)-(I51+L51),0) -> 0 | P51: =SUMIF(GL!$D$6488:$D$6532,B51,GL!$H$6488:$H$6532) -> 0 | Q51: =SUMIF(GL!$D$6408:$D$6452,B51,GL!$I$6408:$I$6452) -> 0 | R51: =P51+N51 -> 0 | S51: =Q51+O51 -> 0 | X51: =IF(R51>S51,R51-S51,0) -> 0 | Y51: =IF(S51>R51,S51-R51,0) -> 0
B52: M007 | C52: Italia Chick | D52: =SUMIF(GL!$D$5:$D$6505,B52,GL!$G$5:$G$6505) -> 0 | E52: =SUMIF(GL!$D$6:$D$6487,B52,GL!$H$6:$H$6487) -> 0 | F52: =SUMIF(GL!$D$6:$D$6487,B52,GL!$I$6:$I$6487) -> 0 | I52: =IF(E52>F52,E52-F52,0) -> 0 | J52: =IF(F52>E52,F52-E52,0) -> 0 | N52: =IF(I52+L52>J52+M52,(I52+L52)-(J52+M52),0) -> 0 | O52: =IF(J52+M52>I52+L52,(J52+M52)-(I52+L52),0) -> 0 | P52: =SUMIF(GL!$D$6488:$D$6532,B52,GL!$H$6488:$H$6532) -> 0 | Q52: =SUMIF(GL!$D$6408:$D$6452,B52,GL!$I$6408:$I$6452) -> 0 | R52: =P52+N52 -> 0 | S52: =Q52+O52 -> 0 | X52: =IF(R52>S52,R52-S52,0) -> 0 | Y52: =IF(S52>R52,S52-R52,0) -> 0
B53: M008 | C53: Chorizo Beef/Salami Chorizo | D53: =SUMIF(GL!$D$5:$D$6505,B53,GL!$G$5:$G$6505) -> 3.02 | E53: =SUMIF(GL!$D$6:$D$6487,B53,GL!$H$6:$H$6487) -> 838050 | F53: =SUMIF(GL!$D$6:$D$6487,B53,GL!$I$6:$I$6487) -> 0 | I53: =IF(E53>F53,E53-F53,0) -> 838050 | J53: =IF(F53>E53,F53-E53,0) -> 0 | N53: =IF(I53+L53>J53+M53,(I53+L53)-(J53+M53),0) -> 838050 | O53: =IF(J53+M53>I53+L53,(J53+M53)-(I53+L53),0) -> 0 | P53: =SUMIF(GL!$D$6488:$D$6532,B53,GL!$H$6488:$H$6532) -> 0 | Q53: =SUMIF(GL!$D$6408:$D$6452,B53,GL!$I$6408:$I$6452) -> 0 | R53: =P53+N53 -> 838050 | S53: =Q53+O53 -> 0 | X53: =IF(R53>S53,R53-S53,0) -> 838050 | Y53: =IF(S53>R53,S53-R53,0) -> 0
B54: M009 | C54: Pork Pepperoni | D54: =SUMIF(GL!$D$5:$D$6505,B54,GL!$G$5:$G$6505) -> 0 | E54: =SUMIF(GL!$D$6:$D$6487,B54,GL!$H$6:$H$6487) -> 0 | F54: =SUMIF(GL!$D$6:$D$6487,B54,GL!$I$6:$I$6487) -> 0 | I54: =IF(E54>F54,E54-F54,0) -> 0 | J54: =IF(F54>E54,F54-E54,0) -> 0 | N54: =IF(I54+L54>J54+M54,(I54+L54)-(J54+M54),0) -> 0 | O54: =IF(J54+M54>I54+L54,(J54+M54)-(I54+L54),0) -> 0 | P54: =SUMIF(GL!$D$6488:$D$6532,B54,GL!$H$6488:$H$6532) -> 0 | Q54: =SUMIF(GL!$D$6408:$D$6452,B54,GL!$I$6408:$I$6452) -> 0 | R54: =P54+N54 -> 0 | S54: =Q54+O54 -> 0 | X54: =IF(R54>S54,R54-S54,0) -> 0 | Y54: =IF(S54>R54,S54-R54,0) -> 0
B55: M010 | C55: Italian Sausage | D55: =SUMIF(GL!$D$5:$D$6505,B55,GL!$G$5:$G$6505) -> 0 | E55: =SUMIF(GL!$D$6:$D$6487,B55,GL!$H$6:$H$6487) -> 0 | F55: =SUMIF(GL!$D$6:$D$6487,B55,GL!$I$6:$I$6487) -> 0 | I55: =IF(E55>F55,E55-F55,0) -> 0 | J55: =IF(F55>E55,F55-E55,0) -> 0 | N55: =IF(I55+L55>J55+M55,(I55+L55)-(J55+M55),0) -> 0 | O55: =IF(J55+M55>I55+L55,(J55+M55)-(I55+L55),0) -> 0 | P55: =SUMIF(GL!$D$6488:$D$6532,B55,GL!$H$6488:$H$6532) -> 0 | Q55: =SUMIF(GL!$D$6408:$D$6452,B55,GL!$I$6408:$I$6452) -> 0 | R55: =P55+N55 -> 0 | S55: =Q55+O55 -> 0 | X55: =IF(R55>S55,R55-S55,0) -> 0 | Y55: =IF(S55>R55,S55-R55,0) -> 0
B56: M011 | C56: English Banger Sausage | D56: =SUMIF(GL!$D$5:$D$6505,B56,GL!$G$5:$G$6505) -> 0 | E56: =SUMIF(GL!$D$6:$D$6487,B56,GL!$H$6:$H$6487) -> 0 | F56: =SUMIF(GL!$D$6:$D$6487,B56,GL!$I$6:$I$6487) -> 0 | I56: =IF(E56>F56,E56-F56,0) -> 0 | J56: =IF(F56>E56,F56-E56,0) -> 0 | N56: =IF(I56+L56>J56+M56,(I56+L56)-(J56+M56),0) -> 0 | O56: =IF(J56+M56>I56+L56,(J56+M56)-(I56+L56),0) -> 0 | P56: =SUMIF(GL!$D$6488:$D$6532,B56,GL!$H$6488:$H$6532) -> 0 | Q56: =SUMIF(GL!$D$6408:$D$6452,B56,GL!$I$6408:$I$6452) -> 0 | R56: =P56+N56 -> 0 | S56: =Q56+O56 -> 0 | X56: =IF(R56>S56,R56-S56,0) -> 0 | Y56: =IF(S56>R56,S56-R56,0) -> 0
B57: M012 | C57: Minced Pork | D57: =SUMIF(GL!$D$5:$D$6505,B57,GL!$G$5:$G$6505) -> 0 | E57: =SUMIF(GL!$D$6:$D$6487,B57,GL!$H$6:$H$6487) -> 0 | F57: =SUMIF(GL!$D$6:$D$6487,B57,GL!$I$6:$I$6487) -> 0 | I57: =IF(E57>F57,E57-F57,0) -> 0 | J57: =IF(F57>E57,F57-E57,0) -> 0 | N57: =IF(I57+L57>J57+M57,(I57+L57)-(J57+M57),0) -> 0 | O57: =IF(J57+M57>I57+L57,(J57+M57)-(I57+L57),0) -> 0 | P57: =SUMIF(GL!$D$6488:$D$6532,B57,GL!$H$6488:$H$6532) -> 0 | Q57: =SUMIF(GL!$D$6408:$D$6452,B57,GL!$I$6408:$I$6452) -> 0 | R57: =P57+N57 -> 0 | S57: =Q57+O57 -> 0 | X57: =IF(R57>S57,R57-S57,0) -> 0 | Y57: =IF(S57>R57,S57-R57,0) -> 0
... B100: M053A | C100: Tulang Sapi | D100: =SUMIF(GL!$D$5:$D$6505,B100,GL!$G$5:$G$6505) -> 5 | E100: =SUMIF(GL!$D$6:$D$6487,B100,GL!$H$6:$H$6487) -> 125000 | F100: =SUMIF(GL!$D$6:$D$6487,B100,GL!$I$6:$I$6487) -> 0 | I100: =IF(E100>F100,E100-F100,0) -> 125000 | J100: =IF(F100>E100,F100-E100,0) -> 0 | N100: =IF(I100+L100>J100+M100,(I100+L100)-(J100+M100),0) -> 125000 | O100: =IF(J100+M100>I100+L100,(J100+M100)-(I100+L100),0) -> 0 | P100: =SUMIF(GL!$D$6488:$D$6532,B100,GL!$H$6488:$H$6532) -> 0 | Q100: =SUMIF(GL!$D$6408:$D$6452,B100,GL!$I$6408:$I$6452) -> 0 | R100: =P100+N100 -> 125000 | S100: =Q100+O100 -> 0 | X100: =IF(R100>S100,R100-S100,0) -> 125000 | Y100: =IF(S100>R100,S100-R100,0) -> 0
D101: =SUMIF(GL!$D$5:$D$6505,B101,GL!$G$5:$G$6505) -> 0 | E101: =SUMIF(GL!$D$6:$D$6487,B101,GL!$H$6:$H$6487) -> 0 | F101: =SUMIF(GL!$D$6:$D$6487,B101,GL!$I$6:$I$6487) -> 0 | I101: =IF(E101>F101,E101-F101,0) -> 0 | J101: =IF(F101>E101,F101-E101,0) -> 0 | N101: =IF(I101+L101>J101+M101,(I101+L101)-(J101+M101),0) -> 0 | O101: =IF(J101+M101>I101+L101,(J101+M101)-(I101+L101),0) -> 0 | P101: =SUMIF(GL!$D$6488:$D$6532,B101,GL!$H$6488:$H$6532) -> 0 | Q101: =SUMIF(GL!$D$6408:$D$6452,B101,GL!$I$6408:$I$6452) -> 0 | R101: =P101+N101 -> 0 | S101: =Q101+O101 -> 0 | X101: =IF(R101>S101,R101-S101,0) -> 0 | Y101: =IF(S101>R101,S101-R101,0) -> 0
D102: =SUMIF(GL!$D$5:$D$6505,B102,GL!$G$5:$G$6505) -> 0 | E102: =SUMIF(GL!$D$6:$D$6487,B102,GL!$H$6:$H$6487) -> 0 | F102: =SUMIF(GL!$D$6:$D$6487,B102,GL!$I$6:$I$6487) -> 0 | I102: =IF(E102>F102,E102-F102,0) -> 0 | J102: =IF(F102>E102,F102-E102,0) -> 0 | N102: =IF(I102+L102>J102+M102,(I102+L102)-(J102+M102),0) -> 0 | O102: =IF(J102+M102>I102+L102,(J102+M102)-(I102+L102),0) -> 0 | P102: =SUMIF(GL!$D$6488:$D$6532,B102,GL!$H$6488:$H$6532) -> 0 | Q102: =SUMIF(GL!$D$6408:$D$6452,B102,GL!$I$6408:$I$6452) -> 0 | R102: =P102+N102 -> 0 | S102: =Q102+O102 -> 0 | X102: =IF(R102>S102,R102-S102,0) -> 0 | Y102: =IF(S102>R102,S102-R102,0) -> 0
C103: VEGETABLE & FRUIT | D103: =SUMIF(GL!$D$5:$D$6505,B103,GL!$G$5:$G$6505) -> 0 | E103: =SUMIF(GL!$D$6:$D$6487,B103,GL!$H$6:$H$6487) -> 0 | F103: =SUMIF(GL!$D$6:$D$6487,B103,GL!$I$6:$I$6487) -> 0 | I103: =IF(E103>F103,E103-F103,0) -> 0 | J103: =IF(F103>E103,F103-E103,0) -> 0 | N103: =IF(I103+L103>J103+M103,(I103+L103)-(J103+M103),0) -> 0 | O103: =IF(J103+M103>I103+L103,(J103+M103)-(I103+L103),0) -> 0 | P103: =SUMIF(GL!$D$6488:$D$6532,B103,GL!$H$6488:$H$6532) -> 0 | Q103: =SUMIF(GL!$D$6408:$D$6452,B103,GL!$I$6408:$I$6452) -> 0 | R103: =P103+N103 -> 0 | S103: =Q103+O103 -> 0 | X103: =IF(R103>S103,R103-S103,0) -> 0 | Y103: =IF(S103>R103,S103-R103,0) -> 0
B104: V001 | C104: Great Chilli / Lombok Besar | D104: =SUMIF(GL!$D$5:$D$6505,B104,GL!$G$5:$G$6505) -> 4.37 | E104: =SUMIF(GL!$D$6:$D$6487,B104,GL!$H$6:$H$6487) -> 214000 | F104: =SUMIF(GL!$D$6:$D$6487,B104,GL!$I$6:$I$6487) -> 0 | I104: =IF(E104>F104,E104-F104,0) -> 214000 | J104: =IF(F104>E104,F104-E104,0) -> 0 | N104: =IF(I104+L104>J104+M104,(I104+L104)-(J104+M104),0) -> 214000 | O104: =IF(J104+M104>I104+L104,(J104+M104)-(I104+L104),0) -> 0 | P104: =SUMIF(GL!$D$6488:$D$6532,B104,GL!$H$6488:$H$6532) -> 0 | Q104: =SUMIF(GL!$D$6408:$D$6452,B104,GL!$I$6408:$I$6452) -> 0 | R104: =P104+N104 -> 214000 | S104: =Q104+O104 -> 0 | X104: =IF(R104>S104,R104-S104,0) -> 214000 | Y104: =IF(S104>R104,S104-R104,0) -> 0
B105: V002 | C105: Tomato 1 Kg | D105: =SUMIF(GL!$D$5:$D$6505,B105,GL!$G$5:$G$6505) -> 19.2 | E105: =SUMIF(GL!$D$6:$D$6487,B105,GL!$H$6:$H$6487) -> 381000 | F105: =SUMIF(GL!$D$6:$D$6487,B105,GL!$I$6:$I$6487) -> 0 | I105: =IF(E105>F105,E105-F105,0) -> 381000 | J105: =IF(F105>E105,F105-E105,0) -> 0 | N105: =IF(I105+L105>J105+M105,(I105+L105)-(J105+M105),0) -> 381000 | O105: =IF(J105+M105>I105+L105,(J105+M105)-(I105+L105),0) -> 0 | P105: =SUMIF(GL!$D$6488:$D$6532,B105,GL!$H$6488:$H$6532) -> 0 | Q105: =SUMIF(GL!$D$6408:$D$6452,B105,GL!$I$6408:$I$6452) -> 0 | R105: =P105+N105 -> 381000 | S105: =Q105+O105 -> 0 | X105: =IF(R105>S105,R105-S105,0) -> 381000 | Y105: =IF(S105>R105,S105-R105,0) -> 0
B106: V003 | C106: Japanese Cucumber/Timun | D106: =SUMIF(GL!$D$5:$D$6505,B106,GL!$G$5:$G$6505) -> 20 | E106: =SUMIF(GL!$D$6:$D$6487,B106,GL!$H$6:$H$6487) -> 260000 | F106: =SUMIF(GL!$D$6:$D$6487,B106,GL!$I$6:$I$6487) -> 0 | I106: =IF(E106>F106,E106-F106,0) -> 260000 | J106: =IF(F106>E106,F106-E106,0) -> 0 | N106: =IF(I106+L106>J106+M106,(I106+L106)-(J106+M106),0) -> 260000 | O106: =IF(J106+M106>I106+L106,(J106+M106)-(I106+L106),0) -> 0 | P106: =SUMIF(GL!$D$6488:$D$6532,B106,GL!$H$6488:$H$6532) -> 0 | Q106: =SUMIF(GL!$D$6408:$D$6452,B106,GL!$I$6408:$I$6452) -> 0 | R106: =P106+N106 -> 260000 | S106: =Q106+O106 -> 0 | X106: =IF(R106>S106,R106-S106,0) -> 260000 | Y106: =IF(S106>R106,S106-R106,0) -> 0
B107: V004 | C107: Garlic/Bawang Putih | D107: =SUMIF(GL!$D$5:$D$6505,B107,GL!$G$5:$G$6505) -> 3.933 | E107: =SUMIF(GL!$D$6:$D$6487,B107,GL!$H$6:$H$6487) -> 168000 | F107: =SUMIF(GL!$D$6:$D$6487,B107,GL!$I$6:$I$6487) -> 0 | I107: =IF(E107>F107,E107-F107,0) -> 168000 | J107: =IF(F107>E107,F107-E107,0) -> 0 | N107: =IF(I107+L107>J107+M107,(I107+L107)-(J107+M107),0) -> 168000 | O107: =IF(J107+M107>I107+L107,(J107+M107)-(I107+L107),0) -> 0 | P107: =SUMIF(GL!$D$6488:$D$6532,B107,GL!$H$6488:$H$6532) -> 0 | Q107: =SUMIF(GL!$D$6408:$D$6452,B107,GL!$I$6408:$I$6452) -> 0 | R107: =P107+N107 -> 168000 | S107: =Q107+O107 -> 0 | X107: =IF(R107>S107,R107-S107,0) -> 168000 | Y107: =IF(S107>R107,S107-R107,0) -> 0
B108: V005 | C108: Shallot/Bawang Merah | D108: =SUMIF(GL!$D$5:$D$6505,B108,GL!$G$5:$G$6505) -> 3.25 | E108: =SUMIF(GL!$D$6:$D$6487,B108,GL!$H$6:$H$6487) -> 170750 | F108: =SUMIF(GL!$D$6:$D$6487,B108,GL!$I$6:$I$6487) -> 0 | I108: =IF(E108>F108,E108-F108,0) -> 170750 | J108: =IF(F108>E108,F108-E108,0) -> 0 | N108: =IF(I108+L108>J108+M108,(I108+L108)-(J108+M108),0) -> 170750 | O108: =IF(J108+M108>I108+L108,(J108+M108)-(I108+L108),0) -> 0 | P108: =SUMIF(GL!$D$6488:$D$6532,B108,GL!$H$6488:$H$6532) -> 0 | Q108: =SUMIF(GL!$D$6408:$D$6452,B108,GL!$I$6408:$I$6452) -> 0 | R108: =P108+N108 -> 170750 | S108: =Q108+O108 -> 0 | X108: =IF(R108>S108,R108-S108,0) -> 170750 | Y108: =IF(S108>R108,S108-R108,0) -> 0
B109: V006 | C109: Onion/Bombay | D109: =SUMIF(GL!$D$5:$D$6505,B109,GL!$G$5:$G$6505) -> 13.85 | E109: =SUMIF(GL!$D$6:$D$6487,B109,GL!$H$6:$H$6487) -> 332600 | F109: =SUMIF(GL!$D$6:$D$6487,B109,GL!$I$6:$I$6487) -> 0 | I109: =IF(E109>F109,E109-F109,0) -> 332600 | J109: =IF(F109>E109,F109-E109,0) -> 0 | N109: =IF(I109+L109>J109+M109,(I109+L109)-(J109+M109),0) -> 332600 | O109: =IF(J109+M109>I109+L109,(J109+M109)-(I109+L109),0) -> 0 | P109: =SUMIF(GL!$D$6488:$D$6532,B109,GL!$H$6488:$H$6532) -> 0 | Q109: =SUMIF(GL!$D$6408:$D$6452,B109,GL!$I$6408:$I$6452) -> 0 | R109: =P109+N109 -> 332600 | S109: =Q109+O109 -> 0 | X109: =IF(R109>S109,R109-S109,0) -> 332600 | Y109: =IF(S109>R109,S109-R109,0) -> 0
B110: V007 | C110: Capsicum/Paprika | D110: =SUMIF(GL!$D$5:$D$6505,B110,GL!$G$5:$G$6505) -> 25.93 | E110: =SUMIF(GL!$D$6:$D$6487,B110,GL!$H$6:$H$6487) -> 2688500 | F110: =SUMIF(GL!$D$6:$D$6487,B110,GL!$I$6:$I$6487) -> 0 | I110: =IF(E110>F110,E110-F110,0) -> 2688500 | J110: =IF(F110>E110,F110-E110,0) -> 0 | N110: =IF(I110+L110>J110+M110,(I110+L110)-(J110+M110),0) -> 2688500 | O110: =IF(J110+M110>I110+L110,(J110+M110)-(I110+L110),0) -> 0 | P110: =SUMIF(GL!$D$6488:$D$6532,B110,GL!$H$6488:$H$6532) -> 0 | Q110: =SUMIF(GL!$D$6408:$D$6452,B110,GL!$I$6408:$I$6452) -> 0 | R110: =P110+N110 -> 2688500 | S110: =Q110+O110 -> 0 | X110: =IF(R110>S110,R110-S110,0) -> 2688500 | Y110: =IF(S110>R110,S110-R110,0) -> 0
B111: V008 | C111: Basil | D111: =SUMIF(GL!$D$5:$D$6505,B111,GL!$G$5:$G$6505) -> 3.7 | E111: =SUMIF(GL!$D$6:$D$6487,B111,GL!$H$6:$H$6487) -> 277500 | F111: =SUMIF(GL!$D$6:$D$6487,B111,GL!$I$6:$I$6487) -> 0 | I111: =IF(E111>F111,E111-F111,0) -> 277500 | J111: =IF(F111>E111,F111-E111,0) -> 0 | N111: =IF(I111+L111>J111+M111,(I111+L111)-(J111+M111),0) -> 277500 | O111: =IF(J111+M111>I111+L111,(J111+M111)-(I111+L111),0) -> 0 | P111: =SUMIF(GL!$D$6488:$D$6532,B111,GL!$H$6488:$H$6532) -> 0 | Q111: =SUMIF(GL!$D$6408:$D$6452,B111,GL!$I$6408:$I$6452) -> 0 | R111: =P111+N111 -> 277500 | S111: =Q111+O111 -> 0 | X111: =IF(R111>S111,R111-S111,0) -> 277500 | Y111: =IF(S111>R111,S111-R111,0) -> 0
B112: V009 | C112: Parsley | D112: =SUMIF(GL!$D$5:$D$6505,B112,GL!$G$5:$G$6505) -> 0.49 | E112: =SUMIF(GL!$D$6:$D$6487,B112,GL!$H$6:$H$6487) -> 43500 | F112: =SUMIF(GL!$D$6:$D$6487,B112,GL!$I$6:$I$6487) -> 0 | I112: =IF(E112>F112,E112-F112,0) -> 43500 | J112: =IF(F112>E112,F112-E112,0) -> 0 | N112: =IF(I112+L112>J112+M112,(I112+L112)-(J112+M112),0) -> 43500 | O112: =IF(J112+M112>I112+L112,(J112+M112)-(I112+L112),0) -> 0 | P112: =SUMIF(GL!$D$6488:$D$6532,B112,GL!$H$6488:$H$6532) -> 0 | Q112: =SUMIF(GL!$D$6408:$D$6452,B112,GL!$I$6408:$I$6452) -> 0 | R112: =P112+N112 -> 43500 | S112: =Q112+O112 -> 0 | X112: =IF(R112>S112,R112-S112,0) -> 43500 | Y112: =IF(S112>R112,S112-R112,0) -> 0
B113: V010 | C113: Ruccola | D113: =SUMIF(GL!$D$5:$D$6505,B113,GL!$G$5:$G$6505) -> 5.21 | E113: =SUMIF(GL!$D$6:$D$6487,B113,GL!$H$6:$H$6487) -> 373500 | F113: =SUMIF(GL!$D$6:$D$6487,B113,GL!$I$6:$I$6487) -> 0 | I113: =IF(E113>F113,E113-F113,0) -> 373500 | J113: =IF(F113>E113,F113-E113,0) -> 0 | N113: =IF(I113+L113>J113+M113,(I113+L113)-(J113+M113),0) -> 373500 | O113: =IF(J113+M113>I113+L113,(J113+M113)-(I113+L113),0) -> 0 | P113: =SUMIF(GL!$D$6488:$D$6532,B113,GL!$H$6488:$H$6532) -> 0 | Q113: =SUMIF(GL!$D$6408:$D$6452,B113,GL!$I$6408:$I$6452) -> 0 | R113: =P113+N113 -> 373500 | S113: =Q113+O113 -> 0 | X113: =IF(R113>S113,R113-S113,0) -> 373500 | Y113: =IF(S113>R113,S113-R113,0) -> 0
B114: V011 | C114: Carrot/Wortel | D114: =SUMIF(GL!$D$5:$D$6505,B114,GL!$G$5:$G$6505) -> 10.6 | E114: =SUMIF(GL!$D$6:$D$6487,B114,GL!$H$6:$H$6487) -> 244000 | F114: =SUMIF(GL!$D$6:$D$6487,B114,GL!$I$6:$I$6487) -> 0 | I114: =IF(E114>F114,E114-F114,0) -> 244000 | J114: =IF(F114>E114,F114-E114,0) -> 0 | N114: =IF(I114+L114>J114+M114,(I114+L114)-(J114+M114),0) -> 244000 | O114: =IF(J114+M114>I114+L114,(J114+M114)-(I114+L114),0) -> 0 | P114: =SUMIF(GL!$D$6488:$D$6532,B114,GL!$H$6488:$H$6532) -> 0 | Q114: =SUMIF(GL!$D$6408:$D$6452,B114,GL!$I$6408:$I$6452) -> 0 | R114: =P114+N114 -> 244000 | S114: =Q114+O114 -> 0 | X114: =IF(R114>S114,R114-S114,0) -> 244000 | Y114: =IF(S114>R114,S114-R114,0) -> 0
B115: V011A | C115: Baby Carrot/Wortel | D115: =SUMIF(GL!$D$5:$D$6505,B115,GL!$G$5:$G$6505) -> 4.5 | E115: =SUMIF(GL!$D$6:$D$6487,B115,GL!$H$6:$H$6487) -> 157500 | F115: =SUMIF(GL!$D$6:$D$6487,B115,GL!$I$6:$I$6487) -> 0 | I115: =IF(E115>F115,E115-F115,0) -> 157500 | J115: =IF(F115>E115,F115-E115,0) -> 0 | N115: =IF(I115+L115>J115+M115,(I115+L115)-(J115+M115),0) -> 157500 | O115: =IF(J115+M115>I115+L115,(J115+M115)-(I115+L115),0) -> 0 | P115: =SUMIF(GL!$D$6488:$D$6532,B115,GL!$H$6488:$H$6532) -> 0 | Q115: =SUMIF(GL!$D$6408:$D$6452,B115,GL!$I$6408:$I$6452) -> 0 | R115: =P115+N115 -> 157500 | S115: =Q115+O115 -> 0 | X115: =IF(R115>S115,R115-S115,0) -> 157500 | Y115: =IF(S115>R115,S115-R115,0) -> 0
... B186: V054A | C186: Jagung / Corn | D186: =SUMIF(GL!$D$5:$D$6505,B186,GL!$G$5:$G$6505) -> 1.2 | E186: =SUMIF(GL!$D$6:$D$6487,B186,GL!$H$6:$H$6487) -> 16800 | F186: =SUMIF(GL!$D$6:$D$6487,B186,GL!$I$6:$I$6487) -> 0 | I186: =IF(E186>F186,E186-F186,0) -> 16800 | J186: =IF(F186>E186,F186-E186,0) -> 0 | N186: =IF(I186+L186>J186+M186,(I186+L186)-(J186+M186),0) -> 16800 | O186: =IF(J186+M186>I186+L186,(J186+M186)-(I186+L186),0) -> 0 | P186: =SUMIF(GL!$D$6488:$D$6532,B186,GL!$H$6488:$H$6532) -> 0 | Q186: =SUMIF(GL!$D$6408:$D$6452,B186,GL!$I$6408:$I$6452) -> 0 | R186: =P186+N186 -> 16800 | S186: =Q186+O186 -> 0 | X186: =IF(R186>S186,R186-S186,0) -> 16800 | Y186: =IF(S186>R186,S186-R186,0) -> 0
D187: =SUMIF(GL!$D$5:$D$6505,B187,GL!$G$5:$G$6505) -> 0 | E187: =SUMIF(GL!$D$6:$D$6487,B187,GL!$H$6:$H$6487) -> 0 | F187: =SUMIF(GL!$D$6:$D$6487,B187,GL!$I$6:$I$6487) -> 0 | I187: =IF(E187>F187,E187-F187,0) -> 0 | J187: =IF(F187>E187,F187-E187,0) -> 0 | N187: =IF(I187+L187>J187+M187,(I187+L187)-(J187+M187),0) -> 0 | O187: =IF(J187+M187>I187+L187,(J187+M187)-(I187+L187),0) -> 0 | P187: =SUMIF(GL!$D$6488:$D$6532,B187,GL!$H$6488:$H$6532) -> 0 | Q187: =SUMIF(GL!$D$6408:$D$6452,B187,GL!$I$6408:$I$6452) -> 0 | R187: =P187+N187 -> 0 | S187: =Q187+O187 -> 0 | X187: =IF(R187>S187,R187-S187,0) -> 0 | Y187: =IF(S187>R187,S187-R187,0) -> 0
D188: =SUMIF(GL!$D$5:$D$6505,B188,GL!$G$5:$G$6505) -> 0 | E188: =SUMIF(GL!$D$6:$D$6487,B188,GL!$H$6:$H$6487) -> 0 | F188: =SUMIF(GL!$D$6:$D$6487,B188,GL!$I$6:$I$6487) -> 0 | I188: =IF(E188>F188,E188-F188,0) -> 0 | J188: =IF(F188>E188,F188-E188,0) -> 0 | N188: =IF(I188+L188>J188+M188,(I188+L188)-(J188+M188),0) -> 0 | O188: =IF(J188+M188>I188+L188,(J188+M188)-(I188+L188),0) -> 0 | P188: =SUMIF(GL!$D$6488:$D$6532,B188,GL!$H$6488:$H$6532) -> 0 | Q188: =SUMIF(GL!$D$6408:$D$6452,B188,GL!$I$6408:$I$6452) -> 0 | R188: =P188+N188 -> 0 | S188: =Q188+O188 -> 0 | X188: =IF(R188>S188,R188-S188,0) -> 0 | Y188: =IF(S188>R188,S188-R188,0) -> 0
D189: =SUMIF(GL!$D$5:$D$6505,B189,GL!$G$5:$G$6505) -> 0 | E189: =SUMIF(GL!$D$6:$D$6487,B189,GL!$H$6:$H$6487) -> 0 | F189: =SUMIF(GL!$D$6:$D$6487,B189,GL!$I$6:$I$6487) -> 0 | I189: =IF(E189>F189,E189-F189,0) -> 0 | J189: =IF(F189>E189,F189-E189,0) -> 0 | N189: =IF(I189+L189>J189+M189,(I189+L189)-(J189+M189),0) -> 0 | O189: =IF(J189+M189>I189+L189,(J189+M189)-(I189+L189),0) -> 0 | P189: =SUMIF(GL!$D$6488:$D$6532,B189,GL!$H$6488:$H$6532) -> 0 | Q189: =SUMIF(GL!$D$6408:$D$6452,B189,GL!$I$6408:$I$6452) -> 0 | R189: =P189+N189 -> 0 | S189: =Q189+O189 -> 0 | X189: =IF(R189>S189,R189-S189,0) -> 0 | Y189: =IF(S189>R189,S189-R189,0) -> 0
D190: =SUMIF(GL!$D$5:$D$6505,B190,GL!$G$5:$G$6505) -> 0 | E190: =SUMIF(GL!$D$6:$D$6487,B190,GL!$H$6:$H$6487) -> 0 | F190: =SUMIF(GL!$D$6:$D$6487,B190,GL!$I$6:$I$6487) -> 0 | I190: =IF(E190>F190,E190-F190,0) -> 0 | J190: =IF(F190>E190,F190-E190,0) -> 0 | N190: =IF(I190+L190>J190+M190,(I190+L190)-(J190+M190),0) -> 0 | O190: =IF(J190+M190>I190+L190,(J190+M190)-(I190+L190),0) -> 0 | P190: =SUMIF(GL!$D$6488:$D$6532,B190,GL!$H$6488:$H$6532) -> 0 | Q190: =SUMIF(GL!$D$6408:$D$6452,B190,GL!$I$6408:$I$6452) -> 0 | R190: =P190+N190 -> 0 | S190: =Q190+O190 -> 0 | X190: =IF(R190>S190,R190-S190,0) -> 0 | Y190: =IF(S190>R190,S190-R190,0) -> 0
D191: =SUMIF(GL!$D$5:$D$6505,B191,GL!$G$5:$G$6505) -> 0 | E191: =SUMIF(GL!$D$6:$D$6487,B191,GL!$H$6:$H$6487) -> 0 | F191: =SUMIF(GL!$D$6:$D$6487,B191,GL!$I$6:$I$6487) -> 0 | I191: =IF(E191>F191,E191-F191,0) -> 0 | J191: =IF(F191>E191,F191-E191,0) -> 0 | N191: =IF(I191+L191>J191+M191,(I191+L191)-(J191+M191),0) -> 0 | O191: =IF(J191+M191>I191+L191,(J191+M191)-(I191+L191),0) -> 0 | P191: =SUMIF(GL!$D$6488:$D$6532,B191,GL!$H$6488:$H$6532) -> 0 | Q191: =SUMIF(GL!$D$6408:$D$6452,B191,GL!$I$6408:$I$6452) -> 0 | R191: =P191+N191 -> 0 | S191: =Q191+O191 -> 0 | X191: =IF(R191>S191,R191-S191,0) -> 0 | Y191: =IF(S191>R191,S191-R191,0) -> 0
D192: =SUMIF(GL!$D$5:$D$6505,B192,GL!$G$5:$G$6505) -> 0 | E192: =SUMIF(GL!$D$6:$D$6487,B192,GL!$H$6:$H$6487) -> 0 | F192: =SUMIF(GL!$D$6:$D$6487,B192,GL!$I$6:$I$6487) -> 0 | I192: =IF(E192>F192,E192-F192,0) -> 0 | J192: =IF(F192>E192,F192-E192,0) -> 0 | N192: =IF(I192+L192>J192+M192,(I192+L192)-(J192+M192),0) -> 0 | O192: =IF(J192+M192>I192+L192,(J192+M192)-(I192+L192),0) -> 0 | P192: =SUMIF(GL!$D$6488:$D$6532,B192,GL!$H$6488:$H$6532) -> 0 | Q192: =SUMIF(GL!$D$6408:$D$6452,B192,GL!$I$6408:$I$6452) -> 0 | R192: =P192+N192 -> 0 | S192: =Q192+O192 -> 0 | X192: =IF(R192>S192,R192-S192,0) -> 0 | Y192: =IF(S192>R192,S192-R192,0) -> 0
D193: =SUMIF(GL!$D$5:$D$6505,B193,GL!$G$5:$G$6505) -> 0 | E193: =SUMIF(GL!$D$6:$D$6487,B193,GL!$H$6:$H$6487) -> 0 | F193: =SUMIF(GL!$D$6:$D$6487,B193,GL!$I$6:$I$6487) -> 0 | I193: =IF(E193>F193,E193-F193,0) -> 0 | J193: =IF(F193>E193,F193-E193,0) -> 0 | N193: =IF(I193+L193>J193+M193,(I193+L193)-(J193+M193),0) -> 0 | O193: =IF(J193+M193>I193+L193,(J193+M193)-(I193+L193),0) -> 0 | P193: =SUMIF(GL!$D$6488:$D$6532,B193,GL!$H$6488:$H$6532) -> 0 | Q193: =SUMIF(GL!$D$6408:$D$6452,B193,GL!$I$6408:$I$6452) -> 0 | R193: =P193+N193 -> 0 | S193: =Q193+O193 -> 0 | X193: =IF(R193>S193,R193-S193,0) -> 0 | Y193: =IF(S193>R193,S193-R193,0) -> 0
D194: =SUMIF(GL!$D$5:$D$6505,B194,GL!$G$5:$G$6505) -> 0 | E194: =SUMIF(GL!$D$6:$D$6487,B194,GL!$H$6:$H$6487) -> 0 | F194: =SUMIF(GL!$D$6:$D$6487,B194,GL!$I$6:$I$6487) -> 0 | I194: =IF(E194>F194,E194-F194,0) -> 0 | J194: =IF(F194>E194,F194-E194,0) -> 0 | N194: =IF(I194+L194>J194+M194,(I194+L194)-(J194+M194),0) -> 0 | O194: =IF(J194+M194>I194+L194,(J194+M194)-(I194+L194),0) -> 0 | P194: =SUMIF(GL!$D$6488:$D$6532,B194,GL!$H$6488:$H$6532) -> 0 | Q194: =SUMIF(GL!$D$6408:$D$6452,B194,GL!$I$6408:$I$6452) -> 0 | R194: =P194+N194 -> 0 | S194: =Q194+O194 -> 0 | X194: =IF(R194>S194,R194-S194,0) -> 0 | Y194: =IF(S194>R194,S194-R194,0) -> 0
D195: =SUMIF(GL!$D$5:$D$6505,B195,GL!$G$5:$G$6505) -> 0 | E195: =SUMIF(GL!$D$6:$D$6487,B195,GL!$H$6:$H$6487) -> 0 | F195: =SUMIF(GL!$D$6:$D$6487,B195,GL!$I$6:$I$6487) -> 0 | I195: =IF(E195>F195,E195-F195,0) -> 0 | J195: =IF(F195>E195,F195-E195,0) -> 0 | N195: =IF(I195+L195>J195+M195,(I195+L195)-(J195+M195),0) -> 0 | O195: =IF(J195+M195>I195+L195,(J195+M195)-(I195+L195),0) -> 0 | P195: =SUMIF(GL!$D$6488:$D$6532,B195,GL!$H$6488:$H$6532) -> 0 | Q195: =SUMIF(GL!$D$6408:$D$6452,B195,GL!$I$6408:$I$6452) -> 0 | R195: =P195+N195 -> 0 | S195: =Q195+O195 -> 0 | X195: =IF(R195>S195,R195-S195,0) -> 0 | Y195: =IF(S195>R195,S195-R195,0) -> 0
D196: =SUMIF(GL!$D$5:$D$6505,B196,GL!$G$5:$G$6505) -> 0 | E196: =SUMIF(GL!$D$6:$D$6487,B196,GL!$H$6:$H$6487) -> 0 | F196: =SUMIF(GL!$D$6:$D$6487,B196,GL!$I$6:$I$6487) -> 0 | I196: =IF(E196>F196,E196-F196,0) -> 0 | J196: =IF(F196>E196,F196-E196,0) -> 0 | N196: =IF(I196+L196>J196+M196,(I196+L196)-(J196+M196),0) -> 0 | O196: =IF(J196+M196>I196+L196,(J196+M196)-(I196+L196),0) -> 0 | P196: =SUMIF(GL!$D$6488:$D$6532,B196,GL!$H$6488:$H$6532) -> 0 | Q196: =SUMIF(GL!$D$6408:$D$6452,B196,GL!$I$6408:$I$6452) -> 0 | R196: =P196+N196 -> 0 | S196: =Q196+O196 -> 0 | X196: =IF(R196>S196,R196-S196,0) -> 0 | Y196: =IF(S196>R196,S196-R196,0) -> 0
C197: GROCERIES | D197: =SUMIF(GL!$D$5:$D$6505,B197,GL!$G$5:$G$6505) -> 0 | E197: =SUMIF(GL!$D$6:$D$6487,B197,GL!$H$6:$H$6487) -> 0 | F197: =SUMIF(GL!$D$6:$D$6487,B197,GL!$I$6:$I$6487) -> 0 | I197: =IF(E197>F197,E197-F197,0) -> 0 | J197: =IF(F197>E197,F197-E197,0) -> 0 | N197: =IF(I197+L197>J197+M197,(I197+L197)-(J197+M197),0) -> 0 | O197: =IF(J197+M197>I197+L197,(J197+M197)-(I197+L197),0) -> 0 | P197: =SUMIF(GL!$D$6488:$D$6532,B197,GL!$H$6488:$H$6532) -> 0 | Q197: =SUMIF(GL!$D$6408:$D$6452,B197,GL!$I$6408:$I$6452) -> 0 | R197: =P197+N197 -> 0 | S197: =Q197+O197 -> 0 | X197: =IF(R197>S197,R197-S197,0) -> 0 | Y197: =IF(S197>R197,S197-R197,0) -> 0
B198: G001 | C198: Oyster Sauce @ 510Ltr | D198: =SUMIF(GL!$D$5:$D$6505,B198,GL!$G$5:$G$6505) -> 8.627451 | E198: =SUMIF(GL!$D$6:$D$6487,B198,GL!$H$6:$H$6487) -> 218914 | F198: =SUMIF(GL!$D$6:$D$6487,B198,GL!$I$6:$I$6487) -> 0 | I198: =IF(E198>F198,E198-F198,0) -> 218914 | J198: =IF(F198>E198,F198-E198,0) -> 0 | N198: =IF(I198+L198>J198+M198,(I198+L198)-(J198+M198),0) -> 218914 | O198: =IF(J198+M198>I198+L198,(J198+M198)-(I198+L198),0) -> 0 | P198: =SUMIF(GL!$D$6488:$D$6532,B198,GL!$H$6488:$H$6532) -> 0 | Q198: =SUMIF(GL!$D$6408:$D$6452,B198,GL!$I$6408:$I$6452) -> 0 | R198: =P198+N198 -> 218914 | S198: =Q198+O198 -> 0 | X198: =IF(R198>S198,R198-S198,0) -> 218914 | Y198: =IF(S198>R198,S198-R198,0) -> 0
B199: G002 | C199: Pine Nuts | D199: =SUMIF(GL!$D$5:$D$6505,B199,GL!$G$5:$G$6505) -> 0 | E199: =SUMIF(GL!$D$6:$D$6487,B199,GL!$H$6:$H$6487) -> 0 | F199: =SUMIF(GL!$D$6:$D$6487,B199,GL!$I$6:$I$6487) -> 0 | I199: =IF(E199>F199,E199-F199,0) -> 0 | J199: =IF(F199>E199,F199-E199,0) -> 0 | N199: =IF(I199+L199>J199+M199,(I199+L199)-(J199+M199),0) -> 0 | O199: =IF(J199+M199>I199+L199,(J199+M199)-(I199+L199),0) -> 0 | P199: =SUMIF(GL!$D$6488:$D$6532,B199,GL!$H$6488:$H$6532) -> 0 | Q199: =SUMIF(GL!$D$6408:$D$6452,B199,GL!$I$6408:$I$6452) -> 0 | R199: =P199+N199 -> 0 | S199: =Q199+O199 -> 0 | X199: =IF(R199>S199,R199-S199,0) -> 0 | Y199: =IF(S199>R199,S199-R199,0) -> 0
B200: G003 | C200: Dill Daun | D200: =SUMIF(GL!$D$5:$D$6505,B200,GL!$G$5:$G$6505) -> 0.2 | E200: =SUMIF(GL!$D$6:$D$6487,B200,GL!$H$6:$H$6487) -> 29000 | F200: =SUMIF(GL!$D$6:$D$6487,B200,GL!$I$6:$I$6487) -> 0 | I200: =IF(E200>F200,E200-F200,0) -> 29000 | J200: =IF(F200>E200,F200-E200,0) -> 0 | N200: =IF(I200+L200>J200+M200,(I200+L200)-(J200+M200),0) -> 29000 | O200: =IF(J200+M200>I200+L200,(J200+M200)-(I200+L200),0) -> 0 | P200: =SUMIF(GL!$D$6488:$D$6532,B200,GL!$H$6488:$H$6532) -> 0 | Q200: =SUMIF(GL!$D$6408:$D$6452,B200,GL!$I$6408:$I$6452) -> 0 | R200: =P200+N200 -> 29000 | S200: =Q200+O200 -> 0 | X200: =IF(R200>S200,R200-S200,0) -> 29000 | Y200: =IF(S200>R200,S200-R200,0) -> 0
B201: G004 | C201: Whipping Cream | D201: =SUMIF(GL!$D$5:$D$6505,B201,GL!$G$5:$G$6505) -> 0 | E201: =SUMIF(GL!$D$6:$D$6487,B201,GL!$H$6:$H$6487) -> 0 | F201: =SUMIF(GL!$D$6:$D$6487,B201,GL!$I$6:$I$6487) -> 0 | I201: =IF(E201>F201,E201-F201,0) -> 0 | J201: =IF(F201>E201,F201-E201,0) -> 0 | N201: =IF(I201+L201>J201+M201,(I201+L201)-(J201+M201),0) -> 0 | O201: =IF(J201+M201>I201+L201,(J201+M201)-(I201+L201),0) -> 0 | P201: =SUMIF(GL!$D$6488:$D$6532,B201,GL!$H$6488:$H$6532) -> 0 | Q201: =SUMIF(GL!$D$6408:$D$6452,B201,GL!$I$6408:$I$6452) -> 0 | R201: =P201+N201 -> 0 | S201: =Q201+O201 -> 0 | X201: =IF(R201>S201,R201-S201,0) -> 0 | Y201: =IF(S201>R201,S201-R201,0) -> 0
B202: G005 | C202: Green Peas/Kacang Polong | D202: =SUMIF(GL!$D$5:$D$6505,B202,GL!$G$5:$G$6505) -> 2 | E202: =SUMIF(GL!$D$6:$D$6487,B202,GL!$H$6:$H$6487) -> 150000 | F202: =SUMIF(GL!$D$6:$D$6487,B202,GL!$I$6:$I$6487) -> 0 | I202: =IF(E202>F202,E202-F202,0) -> 150000 | J202: =IF(F202>E202,F202-E202,0) -> 0 | N202: =IF(I202+L202>J202+M202,(I202+L202)-(J202+M202),0) -> 150000 | O202: =IF(J202+M202>I202+L202,(J202+M202)-(I202+L202),0) -> 0 | P202: =SUMIF(GL!$D$6488:$D$6532,B202,GL!$H$6488:$H$6532) -> 0 | Q202: =SUMIF(GL!$D$6408:$D$6452,B202,GL!$I$6408:$I$6452) -> 0 | R202: =P202+N202 -> 150000 | S202: =Q202+O202 -> 0 | X202: =IF(R202>S202,R202-S202,0) -> 150000 | Y202: =IF(S202>R202,S202-R202,0) -> 0
B203: G006 | C203: Corn Flake | D203: =SUMIF(GL!$D$5:$D$6505,B203,GL!$G$5:$G$6505) -> 0 | E203: =SUMIF(GL!$D$6:$D$6487,B203,GL!$H$6:$H$6487) -> 0 | F203: =SUMIF(GL!$D$6:$D$6487,B203,GL!$I$6:$I$6487) -> 0 | I203: =IF(E203>F203,E203-F203,0) -> 0 | J203: =IF(F203>E203,F203-E203,0) -> 0 | N203: =IF(I203+L203>J203+M203,(I203+L203)-(J203+M203),0) -> 0 | O203: =IF(J203+M203>I203+L203,(J203+M203)-(I203+L203),0) -> 0 | P203: =SUMIF(GL!$D$6488:$D$6532,B203,GL!$H$6488:$H$6532) -> 0 | Q203: =SUMIF(GL!$D$6408:$D$6452,B203,GL!$I$6408:$I$6452) -> 0 | R203: =P203+N203 -> 0 | S203: =Q203+O203 -> 0 | X203: =IF(R203>S203,R203-S203,0) -> 0 | Y203: =IF(S203>R203,S203-R203,0) -> 0
B204: G007 | C204: Figaro Caper Vngr | D204: =SUMIF(GL!$D$5:$D$6505,B204,GL!$G$5:$G$6505) -> 0 | E204: =SUMIF(GL!$D$6:$D$6487,B204,GL!$H$6:$H$6487) -> 0 | F204: =SUMIF(GL!$D$6:$D$6487,B204,GL!$I$6:$I$6487) -> 0 | I204: =IF(E204>F204,E204-F204,0) -> 0 | J204: =IF(F204>E204,F204-E204,0) -> 0 | N204: =IF(I204+L204>J204+M204,(I204+L204)-(J204+M204),0) -> 0 | O204: =IF(J204+M204>I204+L204,(J204+M204)-(I204+L204),0) -> 0 | P204: =SUMIF(GL!$D$6488:$D$6532,B204,GL!$H$6488:$H$6532) -> 0 | Q204: =SUMIF(GL!$D$6408:$D$6452,B204,GL!$I$6408:$I$6452) -> 0 | R204: =P204+N204 -> 0 | S204: =Q204+O204 -> 0 | X204: =IF(R204>S204,R204-S204,0) -> 0 | Y204: =IF(S204>R204,S204-R204,0) -> 0
B205: G008 | C205: Cooking Oil 1 Ltr | D205: =SUMIF(GL!$D$5:$D$6505,B205,GL!$G$5:$G$6505) -> 144 | E205: =SUMIF(GL!$D$6:$D$6487,B205,GL!$H$6:$H$6487) -> 3148000 | F205: =SUMIF(GL!$D$6:$D$6487,B205,GL!$I$6:$I$6487) -> 0 | I205: =IF(E205>F205,E205-F205,0) -> 3148000 | J205: =IF(F205>E205,F205-E205,0) -> 0 | N205: =IF(I205+L205>J205+M205,(I205+L205)-(J205+M205),0) -> 3148000 | O205: =IF(J205+M205>I205+L205,(J205+M205)-(I205+L205),0) -> 0 | P205: =SUMIF(GL!$D$6488:$D$6532,B205,GL!$H$6488:$H$6532) -> 0 | Q205: =SUMIF(GL!$D$6408:$D$6452,B205,GL!$I$6408:$I$6452) -> 0 | R205: =P205+N205 -> 3148000 | S205: =Q205+O205 -> 0 | X205: =IF(R205>S205,R205-S205,0) -> 3148000 | Y205: =IF(S205>R205,S205-R205,0) -> 0
B206: G009 | C206: Kemiri | D206: =SUMIF(GL!$D$5:$D$6505,B206,GL!$G$5:$G$6505) -> 0.25 | E206: =SUMIF(GL!$D$6:$D$6487,B206,GL!$H$6:$H$6487) -> 13750 | F206: =SUMIF(GL!$D$6:$D$6487,B206,GL!$I$6:$I$6487) -> 0 | I206: =IF(E206>F206,E206-F206,0) -> 13750 | J206: =IF(F206>E206,F206-E206,0) -> 0 | N206: =IF(I206+L206>J206+M206,(I206+L206)-(J206+M206),0) -> 13750 | O206: =IF(J206+M206>I206+L206,(J206+M206)-(I206+L206),0) -> 0 | P206: =SUMIF(GL!$D$6488:$D$6532,B206,GL!$H$6488:$H$6532) -> 0 | Q206: =SUMIF(GL!$D$6408:$D$6452,B206,GL!$I$6408:$I$6452) -> 0 | R206: =P206+N206 -> 13750 | S206: =Q206+O206 -> 0 | X206: =IF(R206>S206,R206-S206,0) -> 13750 | Y206: =IF(S206>R206,S206-R206,0) -> 0
B207: G010 | C207: Tomato Ketchup | D207: =SUMIF(GL!$D$5:$D$6505,B207,GL!$G$5:$G$6505) -> 28.5 | E207: =SUMIF(GL!$D$6:$D$6487,B207,GL!$H$6:$H$6487) -> 463495 | F207: =SUMIF(GL!$D$6:$D$6487,B207,GL!$I$6:$I$6487) -> 0 | I207: =IF(E207>F207,E207-F207,0) -> 463495 | J207: =IF(F207>E207,F207-E207,0) -> 0 | N207: =IF(I207+L207>J207+M207,(I207+L207)-(J207+M207),0) -> 463495 | O207: =IF(J207+M207>I207+L207,(J207+M207)-(I207+L207),0) -> 0 | P207: =SUMIF(GL!$D$6488:$D$6532,B207,GL!$H$6488:$H$6532) -> 0 | Q207: =SUMIF(GL!$D$6408:$D$6452,B207,GL!$I$6408:$I$6452) -> 0 | R207: =P207+N207 -> 463495 | S207: =Q207+O207 -> 0 | X207: =IF(R207>S207,R207-S207,0) -> 463495 | Y207: =IF(S207>R207,S207-R207,0) -> 0
B208: G011 | C208: Honey/Madu | D208: =SUMIF(GL!$D$5:$D$6505,B208,GL!$G$5:$G$6505) -> 1.25 | E208: =SUMIF(GL!$D$6:$D$6487,B208,GL!$H$6:$H$6487) -> 71000 | F208: =SUMIF(GL!$D$6:$D$6487,B208,GL!$I$6:$I$6487) -> 0 | I208: =IF(E208>F208,E208-F208,0) -> 71000 | J208: =IF(F208>E208,F208-E208,0) -> 0 | N208: =IF(I208+L208>J208+M208,(I208+L208)-(J208+M208),0) -> 71000 | O208: =IF(J208+M208>I208+L208,(J208+M208)-(I208+L208),0) -> 0 | P208: =SUMIF(GL!$D$6488:$D$6532,B208,GL!$H$6488:$H$6532) -> 0 | Q208: =SUMIF(GL!$D$6408:$D$6452,B208,GL!$I$6408:$I$6452) -> 0 | R208: =P208+N208 -> 71000 | S208: =Q208+O208 -> 0 | X208: =IF(R208>S208,R208-S208,0) -> 71000 | Y208: =IF(S208>R208,S208-R208,0) -> 0
B209: G012 | C209: Red Wine Vinegar/CAPE DIS CAB MERLOT | D209: =SUMIF(GL!$D$5:$D$6505,B209,GL!$G$5:$G$6505) -> 0 | E209: =SUMIF(GL!$D$6:$D$6487,B209,GL!$H$6:$H$6487) -> 0 | F209: =SUMIF(GL!$D$6:$D$6487,B209,GL!$I$6:$I$6487) -> 0 | I209: =IF(E209>F209,E209-F209,0) -> 0 | J209: =IF(F209>E209,F209-E209,0) -> 0 | N209: =IF(I209+L209>J209+M209,(I209+L209)-(J209+M209),0) -> 0 | O209: =IF(J209+M209>I209+L209,(J209+M209)-(I209+L209),0) -> 0 | P209: =SUMIF(GL!$D$6488:$D$6532,B209,GL!$H$6488:$H$6532) -> 0 | Q209: =SUMIF(GL!$D$6408:$D$6452,B209,GL!$I$6408:$I$6452) -> 0 | R209: =P209+N209 -> 0 | S209: =Q209+O209 -> 0 | X209: =IF(R209>S209,R209-S209,0) -> 0 | Y209: =IF(S209>R209,S209-R209,0) -> 0
... B330: G131B | C330: Cheddar Cheese Burger Slice | D330: =SUMIF(GL!$D$5:$D$6505,B330,GL!$G$5:$G$6505) -> 0 | E330: =SUMIF(GL!$D$6:$D$6487,B330,GL!$H$6:$H$6487) -> 0 | F330: =SUMIF(GL!$D$6:$D$6487,B330,GL!$I$6:$I$6487) -> 0 | I330: =IF(E330>F330,E330-F330,0) -> 0 | J330: =IF(F330>E330,F330-E330,0) -> 0 | N330: =IF(I330+L330>J330+M330,(I330+L330)-(J330+M330),0) -> 0 | O330: =IF(J330+M330>I330+L330,(J330+M330)-(I330+L330),0) -> 0 | P330: =SUMIF(GL!$D$6488:$D$6532,B330,GL!$H$6488:$H$6532) -> 0 | Q330: =SUMIF(GL!$D$6408:$D$6452,B330,GL!$I$6408:$I$6452) -> 0 | R330: =P330+N330 -> 0 | S330: =Q330+O330 -> 0 | X330: =IF(R330>S330,R330-S330,0) -> 0 | Y330: =IF(S330>R330,S330-R330,0) -> 0
D331: =SUMIF(GL!$D$5:$D$6505,B331,GL!$G$5:$G$6505) -> 0 | E331: =SUMIF(GL!$D$6:$D$6487,B331,GL!$H$6:$H$6487) -> 0 | F331: =SUMIF(GL!$D$6:$D$6487,B331,GL!$I$6:$I$6487) -> 0 | I331: =IF(E331>F331,E331-F331,0) -> 0 | J331: =IF(F331>E331,F331-E331,0) -> 0 | N331: =IF(I331+L331>J331+M331,(I331+L331)-(J331+M331),0) -> 0 | O331: =IF(J331+M331>I331+L331,(J331+M331)-(I331+L331),0) -> 0 | P331: =SUMIF(GL!$D$6488:$D$6532,B331,GL!$H$6488:$H$6532) -> 0 | Q331: =SUMIF(GL!$D$6408:$D$6452,B331,GL!$I$6408:$I$6452) -> 0 | R331: =P331+N331 -> 0 | S331: =Q331+O331 -> 0 | X331: =IF(R331>S331,R331-S331,0) -> 0 | Y331: =IF(S331>R331,S331-R331,0) -> 0
D332: =SUMIF(GL!$D$5:$D$6505,B332,GL!$G$5:$G$6505) -> 0 | E332: =SUMIF(GL!$D$6:$D$6487,B332,GL!$H$6:$H$6487) -> 0 | F332: =SUMIF(GL!$D$6:$D$6487,B332,GL!$I$6:$I$6487) -> 0 | I332: =IF(E332>F332,E332-F332,0) -> 0 | J332: =IF(F332>E332,F332-E332,0) -> 0 | N332: =IF(I332+L332>J332+M332,(I332+L332)-(J332+M332),0) -> 0 | O332: =IF(J332+M332>I332+L332,(J332+M332)-(I332+L332),0) -> 0 | P332: =SUMIF(GL!$D$6488:$D$6532,B332,GL!$H$6488:$H$6532) -> 0 | Q332: =SUMIF(GL!$D$6408:$D$6452,B332,GL!$I$6408:$I$6452) -> 0 | R332: =P332+N332 -> 0 | S332: =Q332+O332 -> 0 | X332: =IF(R332>S332,R332-S332,0) -> 0 | Y332: =IF(S332>R332,S332-R332,0) -> 0
D333: =SUMIF(GL!$D$5:$D$6505,B333,GL!$G$5:$G$6505) -> 0 | E333: =SUMIF(GL!$D$6:$D$6487,B333,GL!$H$6:$H$6487) -> 0 | F333: =SUMIF(GL!$D$6:$D$6487,B333,GL!$I$6:$I$6487) -> 0 | I333: =IF(E333>F333,E333-F333,0) -> 0 | J333: =IF(F333>E333,F333-E333,0) -> 0 | N333: =IF(I333+L333>J333+M333,(I333+L333)-(J333+M333),0) -> 0 | O333: =IF(J333+M333>I333+L333,(J333+M333)-(I333+L333),0) -> 0 | P333: =SUMIF(GL!$D$6488:$D$6532,B333,GL!$H$6488:$H$6532) -> 0 | Q333: =SUMIF(GL!$D$6408:$D$6452,B333,GL!$I$6408:$I$6452) -> 0 | R333: =P333+N333 -> 0 | S333: =Q333+O333 -> 0 | X333: =IF(R333>S333,R333-S333,0) -> 0 | Y333: =IF(S333>R333,S333-R333,0) -> 0
B334: 1-1302 | C334: INVENTORY BEVERAGE | D334: =SUM(D335:D672) -> 12830.794 | E334: =SUM(E335:E672) -> 507366303 | F334: =SUM(F335:F672) -> 0 | G334: =SUM(G335:G672) -> 0 | H334: =SUM(H335:H672) -> 0 | I334: =SUM(I335:I672) -> 507366303 | J334: =SUM(J335:J672) -> 0 | K334: =SUM(K335:K672) -> 0 | L334: 537419763 | M334: =SUM(M335:M672) -> 0 | N334: =IF(I334+L334>J334+M334,(I334+L334)-(J334+M334),0) -> 1044786066 | O334: =IF(J334+M334>I334+L334,(J334+M334)-(I334+L334),0) -> 0 | P334: =SUMIF(GL!$D$6488:$D$6532,B334,GL!$H$6488:$H$6532) -> 0 | Q334: =GL!H5871 -> 3.8522666e+08 | R334: =P334+N334 -> 1044786066 | S334: =Q334+O334 -> 3.8522666e+08 | X334: =IF(R334>S334,R334-S334,0) -> 6.595594e+08 | Y334: =IF(S334>R334,S334-R334,0) -> 0
C335: BEER & BAVERAGE | D335: =SUMIF(GL!$D$5:$D$6505,B335,GL!$G$5:$G$6505) -> 0 | E335: =SUMIF(GL!$D$6:$D$6487,B335,GL!$H$6:$H$6487) -> 0 | F335: =SUMIF(GL!$D$6:$D$6487,B335,GL!$I$6:$I$6487) -> 0 | I335: =IF(E335>F335,E335-F335,0) -> 0 | J335: =IF(F335>E335,F335-E335,0) -> 0 | N335: =IF(I335+L335>J335+M335,(I335+L335)-(J335+M335),0) -> 0 | O335: =IF(J335+M335>I335+L335,(J335+M335)-(I335+L335),0) -> 0 | P335: =SUMIF(GL!$D$6488:$D$6532,B335,GL!$H$6488:$H$6532) -> 0 | Q335: =SUMIF(GL!$D$6408:$D$6452,B335,GL!$I$6408:$I$6452) -> 0 | R335: =P335+N335 -> 0 | S335: =Q335+O335 -> 0 | X335: =IF(R335>S335,R335-S335,0) -> 0 | Y335: =IF(S335>R335,S335-R335,0) -> 0
B336: BV001 | C336: Guineess Beer | D336: =SUMIF(GL!$D$5:$D$6505,B336,GL!$G$5:$G$6505) -> 0 | E336: =SUMIF(GL!$D$6:$D$6487,B336,GL!$H$6:$H$6487) -> 0 | F336: =SUMIF(GL!$D$6:$D$6487,B336,GL!$I$6:$I$6487) -> 0 | I336: =IF(E336>F336,E336-F336,0) -> 0 | J336: =IF(F336>E336,F336-E336,0) -> 0 | N336: =IF(I336+L336>J336+M336,(I336+L336)-(J336+M336),0) -> 0 | O336: =IF(J336+M336>I336+L336,(J336+M336)-(I336+L336),0) -> 0 | P336: =SUMIF(GL!$D$6488:$D$6532,B336,GL!$H$6488:$H$6532) -> 0 | Q336: =SUMIF(GL!$D$6408:$D$6452,B336,GL!$I$6408:$I$6452) -> 0 | R336: =P336+N336 -> 0 | S336: =Q336+O336 -> 0 | X336: =IF(R336>S336,R336-S336,0) -> 0 | Y336: =IF(S336>R336,S336-R336,0) -> 0
...

Sheet PL
C1: PROFIT & LOSS
C2: Periode: June 2026
C3: PT Taman Bintang Bali
B4: DESCRIPTION | D4: Amount
D5: IDR
B6: 4-0000 | C6: INCOME
B7: 4-2100 | C7: Sales Food | D7: =TB!Y921-TB!X921 -> 177970625
B8: 4-2200 | C8: Sales Beverages | D8: =TB!Y922-TB!X922 -> 1273200752
B9: 4-2300 | C9: Sales Shisa | D9: =TB!Y923-TB!X923 -> 15070000
B10: 4-2400 | C10: Sales Cigarette | D10: =TB!Y924-TB!X924 -> 25295000
B11: 4-2500 | C11: Sales Ticket | D11: =TB!Y925-TB!X925 -> 466710191
B12: 4-2600 | C12: Sales Gofood | D12: =TB!Y926-TB!X926 -> 0
B13: 4-2601 | C13: Sales Misc | D13: =TB!Y927-TB!X927 -> 47820000
B14: 4-2602 | C14: Sales Merchandise | D14: =TB!Y928-TB!X928 -> 0
B15: 4-5100 | C15: Complement/FOC | D15: =TB!Y929-TB!X929 -> 0
B16: 4-5110 | C16: Sales Discounts | D16: =TB!Y930-TB!X930 -> -30762000
B17: 4-9999 | C17: Total Income | D17: =SUM(D7:D16) -> 1975304568
B19: 5-0000 | C19: Cost Of Sales
B20: 5-1000 | C20: COS - Food | D20: =TB!X934-TB!Y934 -> 65753306 | E20: =D20/(D7+D12) -> 0.36946157
B21: 5-2000 | C21: COS - Beverage | D21: =TB!X935-TB!Y935 -> 3.4906899e+08 | E21: =D21/D8 -> 0.2741665
B22: 5-3000 | C22: COS - Shisa | D22: =TB!X936-TB!Y936 -> 735701.88 | E22: =D22/D9 -> 0.04881897
B23: 5-4000 | C23: COS - Cigarettes | D23: =TB!X937-TB!Y937 -> 17082367 | E23: =D23/D10 -> 0.67532582
B24: 5-5000 | C24: COS - Entertainment | D24: =TB!X938-TB!Y938 -> 293036607 | E24: =D24/D17 -> 0.14835009
B25: 5-6000 | C25: COS - Merchandise | D25: =TB!X939-TB!Y939 -> 0
B26: 5-7000 | C26: COS - Promotor Fees Internal | D26: =TB!X940-TB!Y940 -> 20356317 | E26: =D26/D17 -> 0.010305407
B27: 5-8000 | C27: COS - Promotor Fees Other | D27: =TB!X941-TB!Y941 -> 11354386 | E27: =D27/D17 -> 0.0057481695
B28: 5-9000 | C28: COS - reward starxp | D28: =TB!X942-TB!Y942 -> 105350
B29: 5-9999 | C29: Total Cost Of Sales | D29: =SUM(D20:D28) -> 7.5749303e+08
B31: 6-0000 | C31: EXPENSES
B33: 6-1000 | C33: Salary And Wages
B34: 6-1101 | C34: Salaries | D34: =TB!X948-TB!Y948 -> 506375748
B35: 6-1102 | C35: Meals & Transport allowance | D35: =TB!X949-TB!Y949 -> 36045000
B36: 6-1103 | C36: Staff Medical expenses | D36: =TB!X950-TB!Y950 -> 0
B37: 6-1104 | C37: Jamsostek | D37: =TB!X951-TB!Y951 -> 25670334
B38: 6-1105 | C38: Medical insurance | D38: =TB!X952-TB!Y952 -> 0
B39: 6-1106 | C39: Bonus | D39: =TB!X953-TB!Y953 -> 25503742
B40: 6-1107 | C40: Staff Uniforms | D40: =TB!X954-TB!Y954 -> 1860000
B41: 6-1108 | C41: Other staff expenses | D41: =TB!X955-TB!Y955 -> 9909379.4
B42: 6-1109 | C42: Salaries Daily Worker | D42: =TB!X956-TB!Y956 -> 0
B43: 6-1110 | C43: BPJS Kesehatan | D43: =TB!X957-TB!Y957 -> 14758065
B44: 6-1199 | C44: Total Salary And Wages | D44: =SUM(D34:D43) -> 6.2012227e+08 | E44: =D44/D17 -> 0.31393755
B46: 6-2000 | C46: Operating Expenses
B47: 6-2101 | C47: Cleaning Supplies & Expenses | D47: =TB!X961-TB!Y961 -> 24137819
B48: 6-2102 | C48: Shisa Supplies | D48: =TB!X962-TB!Y962 -> 0
B49: 6-2103 | C49: Bar Supplies & Laundry | D49: =TB!X963-TB!Y963 -> 2164600
B50: 6-2104 | C50: Kitchen Supplies | D50: =TB!X964-TB!Y964 -> 3451270
B51: 6-2105 | C51: Merchandise Supplies | D51: =TB!X965-TB!Y965 -> 0
B52: 6-2199 | C52: Total Operating Expenses | D52: =SUM(D47:D51) -> 29753689
B54: 6-3000 | C54: Overhead Departement Expenses
B56: 6-3100 | C56: Administration General Expenses
B57: 6-3101 | C57: License & Taxes - A&G | D57: =TB!X971-TB!Y971 -> 31185
B58: 6-3102 | C58: Accounting and Legal | D58: =TB!X972-TB!Y972 -> 0
B59: 6-3103 | C59: Telephone/Interne/Pulsa/Courier & Postage | D59: =TB!X973-TB!Y973 -> 5658516
B60: 6-3104 | C60: Immigration/Custom Costs | D60: =TB!X974-TB!Y974 -> 3500000
B61: 6-3105 | C61: Stationary & Office Supplies | D61: =TB!X975-TB!Y975 -> 4550070
B62: 6-3106 | C62: Management/Consultancy Fees | D62: =TB!X976-TB!Y976 -> 18000000
B63: 6-3107 | C63: Tax consultant | D63: =TB!X977-TB!Y977 -> 2250000
B64: 6-3108 | C64: Salary General Manager | D64: =TB!X978-TB!Y978 -> 0
B65: 6-3109 | C65: Security/Police/Banjar Costs | D65: =TB!X979-TB!Y979 -> 82000000
B66: 6-3110 | C66: Rental area | D66: =TB!X980-TB!Y980 -> 2000000
B67: 6-3111 | C67: Meeting Expenses | D67: =TB!X981-TB!Y981 -> 0
B68: 6-3112 | C68: Insurance Expenses | D68: =TB!X982-TB!Y982 -> 0
... B73: 6-3117 | C73: Sundry Overhead Costs | D73: =TB!X987-TB!Y987 -> 0
B74: 6-3199 | C74: Total Administration General Expenses | D74: =SUM(D57:D73) -> 218079587
B76: 6-3200 | C76: Sales and Marketing
B77: 6-3201 | C77: Advertising Costs | D77: =TB!X991-TB!Y991 -> 68640219
B78: 6-3202 | C78: Promotional Costs | D78: =TB!X992-TB!Y992 -> 113415165
B79: 6-3203 | C79: Brochure Flyer Printing | D79: =TB!X993-TB!Y993 -> 3629000
B80: 6-3204 | C80: Marketing Fees | D80: =TB!X994-TB!Y994 -> 0
B81: 6-3205 | C81: Print Media/Beat Magazine | D81: =TB!X995-TB!Y995 -> 2000000
B82: 6-3206 | C82: Merchandise Expense | D82: =TB!X996-TB!Y996 -> 0
B83: 6-3207 | C83: Photography/video | D83: =TB!X997-TB!Y997 -> 4100000
B84: 6-3208 | C84: Designer/Consultancy | D84: =TB!X998-TB!Y998 -> 0
B85: 6-3209 | C85: Rental supplies | D85: =TB!X999-TB!Y999 -> 0
B86: 6-3210 | C86: Billboard/Mobile Billboard | D86: =TB!X1000-TB!Y1000 -> 1000000
B87: 6-3211 | C87: Decorations & Florist | D87: =TB!X1001-TB!Y1001 -> 4958296
B88: 6-3212 | C88: Other | D88: =TB!X1002-TB!Y1002 -> 642320
B89: 6-3299 | C89: Total Sales and Marketing | D89: =SUM(D77:D88) -> 198385000
B91: 6-3300 | C91: Repairs & Maintenance
B92: 6-3301 | C92: Genset Maintenance & Solar | D92: =TB!X1006-TB!Y1006 -> 0
B93: 6-3302 | C93: Enggineering Electrical & plumbing Supplies | D93: =TB!X1007-TB!Y1007 -> 2210267
B94: 6-3303 | C94: Property Repair & Maintenance | D94: =TB!X1008-TB!Y1008 -> 18180000
B95: 6-3304 | C95: Water/Gas etc | D95: =TB!X1009-TB!Y1009 -> 7774010
B96: 6-3305 | C96: Pestcontrol | D96: =TB!X1010-TB!Y1010 -> 1200000
B97: 6-3399 | C97: Total Engineering | D97: =SUM(D92:D96) -> 29364277
B99: 6-3400 | C99: Sound & Lighting
B100: 6-3401 | C100: Consulting Sound/Lighting/Video | D100: =TB!X1014-TB!Y1014 -> 0
B101: 6-3402 | C101: Repairs Sound Systems | D101: =TB!X1015-TB!Y1015 -> 1998000
B102: 6-3403 | C102: Repairs Lighting Systems | D102: =TB!X1016-TB!Y1016 -> 0
B103: 6-3404 | C103: Repairs Video Systems | D103: =TB!X1017-TB!Y1017 -> 0
B104: 6-3405 | C104: Rental Sound Systems | D104: =TB!X1018-TB!Y1018 -> 2810000
B105: 6-3406 | C105: Rental Lighting Systems | D105: =TB!X1019-TB!Y1019 -> 0
B106: 6-3407 | C106: Rental Video Systmes | D106: =TB!X1020-TB!Y1020 -> 0
B107: 6-3499 | C107: Total Sound & Lighting | D107: =SUM(D100:D106) -> 4808000
C109: GROSS OPERATING PROFIT | D109: =D17-D29-D44-D52-D74-D89-D97-D107 -> 1.1729872e+08
B111: 6-4000 | C111: Depreciations & Amortisations
B112: 6-4101 | C112: Depr Building Lease | D112: =TB!X1026-TB!Y1026 -> 65000000
B113: 6-4102 | C113: Depr Building Improvement | D113: =TB!X1027-TB!Y1027 -> 12104623
B114: 804782 | C114: Depr Equiptment | D114: =TB!X1028-TB!Y1028 -> 31561415
B115: 6-4104 | C115: Depr Furniture & Fixture | D115: =TB!X1029-TB!Y1029 -> 7885536.7
...

Sheet BS
C1: BALANCE SHEET
C2: Per June 2026
C3: PT Taman Bintang Bali
B4: DESCRIPTION | D4: AMOUNT
D5: IDR
B6: 1-0000 | C6: Assets
B7: 1-1000 | C7: Current Assets
B8: 1-1100 | C8: Cash | D8: =SUM(D9:D10) -> 21152433
B9: 1-1106 | C9: Petty Cash IDR - on General Cashier | D9: =TB!X10-TB!Y10 -> 16652433
B10: 1-1119 | C10: Petty Cash IDR - on Bar Cashier | D10: =TB!X11-TB!Y11 -> 4500000
B12: 1-1120 | C12: Cash in banks | D12: =SUM(D13:D22) -> 3.2305346e+08
B13: 1-1121 | C13: Mandiri KBB 2 | D13: =TB!X13-TB!Y13 -> 0
B14: 1-1122 | C14: Mandiri TBB USD | D14: =TB!X14-TB!Y14 -> 9432186
B15: 1-1123 | C15: Mandiri TBB IDR | D15: =TB!X15-TB!Y15 -> 1443616.9
B16: 1-1124 | C16: BANK BRI | D16: =TB!X16-TB!Y16 -> 349918
B17: 1-1125 | C17: Mandiri GRAB | D17: =TB!X17-TB!Y17 -> 1025127
B18: 1-1126 | C18: =TB!C18 -> Cimb Niaga TBB | D18: =TB!X18-TB!Y18 -> 1055233
B19: 1-1127 | C19: BCA TBB | D19: =TB!X19-TB!Y19 -> 407132.89
B20: 1-1128 | C20: MEGA BANK | D20: =TB!X20-TB!Y20 -> 0
B21: =TB!B21 -> 1-1129 | C21: =TB!C21 -> STARXP | D21: =TB!X21-TB!Y21 -> 309340246
B22: 1-1130 | C22: BPR DEWATA CHANDRADANA | D22: =TB!X22-TB!Y22 -> 0
B23: 1-1199 | C23: Total Cash and Cash At Bank | D23: =D12+D8 -> 3.4420589e+08
B25: 1-1200 | C25: Account Receivables | D25: =SUM(D26:D28) -> 107355431
B26: 1-1201 | C26: Accounts receivable Trade | D26: =TB!X26-TB!Y26 -> 0
B27: 1-1202 | C27: City Ledger | D27: =TB!X27-TB!Y27 -> 80934978
B28: 1-1203 | C28: Cash Advance | D28: =TB!X28-TB!Y28 -> 26420453
B30: 1-1210 | C30: AR Credit Card | D30: =SUM(D31:D38) -> 64703821
B31: 1-1211 | C31: GOPAY | D31: =TB!X30-TB!Y30 -> 0
B32: 1-1212 | C32: Mega Card | D32: =TB!X31-TB!Y31 -> 0
B33: 1-1213 | C33: Mandiri Card TBB | D33: =TB!X32-TB!Y32 -> 57780551
B34: 1-1214 | C34: BRI CARD CC | D34: =TB!X33-TB!Y33 -> 0
B35: 1-1215 | C35: GRAB / OVO | D35: =TB!X34-TB!Y34 -> 143750
B36: 1-1216 | C36: Credit Card Cimb Niaga TBB | D36: =TB!X35-TB!Y35 -> 0
B37: 1-1217 | C37: BCA Card TBB | D37: =TB!X36-TB!Y36 -> 6779520
B38: 1-1218 | C38: =TB!C37 -> STARXP | D38: =TB!X37-TB!Y37 -> 0
B39: 1-1220 | C39: Related Party | D39: =SUM(D40) -> 18751704656
B40: 1-1221 | C40: =TB!C40 -> Intercompany Receivable – Treasury StarPOINTS | D40: =TB!X39-TB!Y39 -> 18751704656
B41: 1-1299 | C41: Total Account Receivables | D41: =D39+D30+D25 -> 18923763908
B43: 1-1300 | C43: Inventory
B44: 1-1301 | C44: Inventory food | D44: =TB!X44-TB!Y44 -> 45808208
B45: 1-1302 | C45: Inventory beverage | D45: =TB!X334-TB!Y334 -> 6.595594e+08
B46: 1-1303 | C46: Inventory shisa | D46: =TB!X673-TB!Y673 -> 3140526.1
B47: 1-1304 | C47: Inventory cigarette | D47: =TB!X714-TB!Y714 -> 1594328.4
B48: 1-1305 | C48: Inventory Kitchen & Bar Utensil | D48: =TB!X805-TB!Y805 -> 60000000
B49: 1-1306 | C49: Inventory Merchandise | D49: =TB!X757-TB!Y757 -> 0
B50: 1-1399 | C50: Total Inventory | D50: =SUM(D44:D49) -> 7.7010247e+08
B52: 1-1400 | C52: Prepaid Expenses
B53: 1-1401 | C53: Prepaid building insurance | D53: =TB!X810-TB!Y810 -> 0
B54: 1-1402 | C54: Prepaid Guest DJ | D54: =TB!X811-TB!Y811 -> 29082000
B55: 1-1403 | C55: Prepaid Building and Land rental | D55: =TB!X812-TB!Y812 -> 1500000000
B56: 1-1404 | C56: Prepaid Insurance staff | D56: =TB!X813-TB!Y813 -> 0
B57: 1-1405 | C57: Prepaid repairs & maintenance | D57: =TB!X814-TB!Y814 -> 0
B58: 1-1406 | C58: Prepaid Vehicle Insurance | D58: =TB!X815-TB!Y815 -> 0
B59: 1-1407 | C59: Prepaid Website/Internet | D59: =TB!X816-TB!Y816 -> 4440000
B60: 1-1408 | C60: Prepaid Licences & Permitt | D60: =TB!X817-TB!Y817 -> 0
B61: 1-1409 | C61: Advances staff | D61: =TB!X818-TB!Y818 -> 156129983
B62: 1-1410 | C62: Prepaid others | D62: =TB!X819-TB!Y819 -> 57568115
B63: 1-1499 | C63: Total Prepaid Expenses | D63: =SUM(D53:D62) -> 1747220098
B65: 1-1500 | C65: Prepaid Tax
B66: 1-1510 | C66: VAT | D66: =TB!X823-TB!Y823 -> 0
B67: 1-1520 | C67: Tax article 21 | D67: =TB!X824-TB!Y824 -> 0
B68: 1-1530 | C68: Tax article 25 | D68: =TB!X825-TB!Y825 -> 0
B69: 1-1540 | C69: Tax article 26 | D69: =TB!X826-TB!Y826 -> 0
B70: 1-1598 | C70: Total Prepaid Tax | D70: =SUM(D66:D69) -> 0
B72: 1-1599 | C72: TOTAL CURRENT ASETS | D72: =D70+D63+D50+D41+D23 -> 2.1785292e+10
B74: 1-2000 | C74: NON CURRENT ASSET
B75: 1-2100 | C75: Fixed Assets
B76: 1-2101 | C76: Acc Cost Fixed Asset
B77: 1-2102 | C77: Building lease right | D77: =TB!X834-TB!Y834 -> 10023791126
B78: 1-2103 | C78: Building Improvement | D78: =TB!X835-TB!Y835 -> 3498061818
B79: 1-2104 | C79: Equipment | D79: =TB!X836-TB!Y836 -> 6202169449
B80: 1-2105 | C80: Furniture & Fixture | D80: =TB!X837-TB!Y837 -> 1128029840
B81: 1-2106 | C81: Machinery | D81: =TB!X838-TB!Y838 -> 70000000
B82: 1-2107 | C82: Business license | D82: =TB!X839-TB!Y839 -> 228000000
B83: 1-2108 | C83: IT Support | D83: =TB!X840-TB!Y840 -> 287209750
B84: 1-2109 | C84: Vehicle assets | D84: =TB!X841-TB!Y841 -> 557145000
B85: 1-2199 | C85: Total Fixed Assets | D85: =SUM(D76:D84) -> 21994406983
B86: 1-2200 | C86: Acm Depreciation
B87: 1-2201 | C87: Acm Depreciation Building lease right | D87: =TB!X844-TB!Y844 -> -4998541126
B88: 1-2202 | C88: Acm Depreciation Building Improvement | D88: =TB!X845-TB!Y845 -> -3.321451e+09
B89: 1-2203 | C89: Acm Depreciation Equiptment | D89: =TB!X846-TB!Y846 -> -4.1942314e+09
B90: 1-2204 | C90: Acm Depreciation Furniture & Fixture | D90: =TB!X847-TB!Y847 -> -1.039971e+09
B91: 1-2205 | C91: Acm Depreciation Machinery | D91: =TB!X848-TB!Y848 -> -70000002
B92: 1-2206 | C92: Acm Depreciation Business license | D92: =TB!X849-TB!Y849 -> -153950000
B93: 1-2207 | C93: Acm Depreciation IT Support | D93: =TB!X850-TB!Y850 -> -2.7893851e+08
B94: 1-2208 | C94: Acm Depreciation Vehicle | D94: =TB!X851-TB!Y851 -> -259859333
B95: 1-2299 | C95: Total Accumulation Fixed Assets | D95: =SUM(D87:D94) -> -1.4316942e+10
B97: 1-2300 | C97: Pre-operating Expenses
B98: 1-2301 | C98: Pre-operating Expenses | D98: =TB!X855-TB!Y855 -> 275389400
B99: 1-2302 | C99: Acc amort of pre op expenses | D99: =TB!X856-TB!Y856 -> 0
B100: 1-2309 | C100: Total Pre-operating Expenses | D100: =SUM(D98:D99) -> 275389400
B102: 1-9998 | C102: TOTAL NON CURRENT ASETS | D102: =D100+D95+D85 -> 7.9528541e+09
B104: 1-9999 | C104: TOTAL ASSETS | D104: =D102+D72 -> 2.9738146e+10
B106: 2-0000 | C106: LIABILITIES
B107: 2-1000 | C107: Currenct Liabilities
B108: 2-1100 | C108: Accounts payable | D108: =TB!Y865 -> 107250000
B109: 2-1101 | C109: Misc Cash Purchase | D109: =TB!Y866 -> 1.769509e+09
B111: 2-1199 | C111: Total Accounts Payable | D111: =SUM(D108:D109) -> 1.876759e+09
B113: 2-2100 | C113: Accrued Payable
B114: =TB!B871 -> 2-2101 | C114: =TB!C871 -> Salaries payable | D114: =TB!Y871-TB!X871 -> 4
...

Sheet COS
B2: TRIAL BALANCE
B3: =GL!I3 -> MONTH OF June 2026
B4: DESCRIPTION | D4: QTY | E4: TB | G4: FB Purchase | I4: QTY | J4: LAST MONTH BALANCE | L4: QTY | M4: BALANCE STOCK | O4: QTY | P4: ENDING STOCK | R4: COS
E5: DB | F5: CR | G5: DB | H5: CR | J5: Unit Price | K5: Amount | M5: Unit Price | N5: Amount | P5: Unit Price | Q5: Amount
B6: 1-1300 | C6: Inventory
B7: 1-1301 | C7: Inventory food | D7: =SUM(D9:D296) -> 2458.0855 | E7: =SUM(E9:E296) -> 82057462 | F7: =SUM(F9:F296) -> 0 | G7: =SUM(G9:G296) -> 82057462 | H7: =SUM(H9:H296) -> 0 | I7: =SUM(I9:I296) -> 592.74 | J7: =SUM(J9:J296) -> 10704090 | K7: =SUM(K9:K296) -> 34932753 | ... R7: =SUM(R9:R296) -> 71182006 | S7: =TB!X44 -> 45808208 | T7: =Q7-S7 -> 1.0000001
C8: MEAT & FISH | N8: =G8+K8 -> 0 | P8: =M8 -> 0 | Q8: =O8*P8 -> 0 | R8: =N8-Q8 -> 0
B9: =TB!B46 -> M001 | C9: =TB!C46 -> Minced Beef | D9: =SUMIF(GL!$D$5:$D$6446,B9,GL!$G$5:$G$6446) -> 20.14 | E9: =SUMIF(GL!$D$6:$D$6484,B9,GL!$H$6:$H$6484) -> 2548780 | F9: =SUMIF(GL!$D$6:$D$6484,B9,GL!$I$6:$I$6484) -> 0 | G9: =IF(E9>F9,E9-F9,0) -> 2548780 | H9: =IF(F9>E9,F9-E9,0) -> 0 | I9: 8 | J9: 125039 | K9: 1000316 | L9: =D9+I9 -> 28.14 | M9: =(G9+K9)/L9 -> 126122.81 | N9: =G9+K9 -> 3549096 | O9: 13 | P9: =M9 -> 126122.81 | Q9: =O9*P9 -> 1639596.6 | R9: =N9-Q9 -> 1909499.4 | T9: =J9-M9 -> -1083.8145
B10: =TB!B47 -> M002 | C10: =TB!C47 -> Sausage/Sosis / Beef | D10: =SUMIF(GL!$D$5:$D$6446,B10,GL!$G$5:$G$6446) -> 0 | E10: =SUMIF(GL!$D$6:$D$6484,B10,GL!$H$6:$H$6484) -> 0 | F10: =SUMIF(GL!$D$6:$D$6484,B10,GL!$I$6:$I$6484) -> 0 | G10: =IF(E10>F10,E10-F10,0) -> 0 | H10: =IF(F10>E10,F10-E10,0) -> 0 | N10: =G10+K10 -> 0 | P10: =M10 -> 0 | Q10: =O10*P10 -> 0 | R10: =N10-Q10 -> 0 | T10: =J10-M10 -> 0
B11: =TB!B48 -> M003 | C11: =TB!C48 -> Beef Scalopine | D11: =SUMIF(GL!$D$5:$D$6446,B11,GL!$G$5:$G$6446) -> 0 | E11: =SUMIF(GL!$D$6:$D$6484,B11,GL!$H$6:$H$6484) -> 0 | F11: =SUMIF(GL!$D$6:$D$6484,B11,GL!$I$6:$I$6484) -> 0 | G11: =IF(E11>F11,E11-F11,0) -> 0 | H11: =IF(F11>E11,F11-E11,0) -> 0 | N11: =G11+K11 -> 0 | P11: =M11 -> 0 | Q11: =O11*P11 -> 0 | R11: =N11-Q11 -> 0 | T11: =J11-M11 -> 0
B12: =TB!B49 -> M004 | C12: =TB!C49 -> Beef Pepperoni | D12: =SUMIF(GL!$D$5:$D$6446,B12,GL!$G$5:$G$6446) -> 0 | E12: =SUMIF(GL!$D$6:$D$6484,B12,GL!$H$6:$H$6484) -> 0 | F12: =SUMIF(GL!$D$6:$D$6484,B12,GL!$I$6:$I$6484) -> 0 | G12: =IF(E12>F12,E12-F12,0) -> 0 | H12: =IF(F12>E12,F12-E12,0) -> 0 | N12: =G12+K12 -> 0 | P12: =M12 -> 0 | Q12: =O12*P12 -> 0 | R12: =N12-Q12 -> 0 | T12: =J12-M12 -> 0
B13: =TB!B50 -> M005 | C13: =TB!C50 -> Chorizo Pork | D13: =SUMIF(GL!$D$5:$D$6446,B13,GL!$G$5:$G$6446) -> 4.3 | E13: =SUMIF(GL!$D$6:$D$6484,B13,GL!$H$6:$H$6484) -> 811410 | F13: =SUMIF(GL!$D$6:$D$6484,B13,GL!$I$6:$I$6484) -> 0 | G13: =IF(E13>F13,E13-F13,0) -> 811410 | H13: =IF(F13>E13,F13-E13,0) -> 0 | I13: 3.35 | J13: 185370 | K13: 620989 | L13: =D13+I13 -> 7.65 | M13: =(G13+K13)/L13 -> 187241.7 | N13: =G13+K13 -> 1432399 | O13: 5.49 | P13: =M13 -> 187241.7 | Q13: =O13*P13 -> 1027956.9 | R13: =N13-Q13 -> 404442.07 | T13: =J13-M13 -> -1871.6993
B14: =TB!B51 -> M006 | C14: =TB!C51 -> Salami | D14: =SUMIF(GL!$D$5:$D$6446,B14,GL!$G$5:$G$6446) -> 0 | E14: =SUMIF(GL!$D$6:$D$6484,B14,GL!$H$6:$H$6484) -> 0 | F14: =SUMIF(GL!$D$6:$D$6484,B14,GL!$I$6:$I$6484) -> 0 | G14: =IF(E14>F14,E14-F14,0) -> 0 | H14: =IF(F14>E14,F14-E14,0) -> 0 | I14: 2.15 | J14: 148931 | K14: 320201 | L14: =D14+I14 -> 2.15 | M14: =(G14+K14)/L14 -> 148930.7 | N14: =G14+K14 -> 320201 | O14: 3.1 | P14: =M14 -> 148930.7 | Q14: =O14*P14 -> 461685.16 | R14: =N14-Q14 -> -141484.16 | T14: =J14-M14 -> 0.30232558
B15: =TB!B52 -> M007 | C15: =TB!C52 -> Italia Chick | D15: =SUMIF(GL!$D$5:$D$6446,B15,GL!$G$5:$G$6446) -> 0 | E15: =SUMIF(GL!$D$6:$D$6484,B15,GL!$H$6:$H$6484) -> 0 | F15: =SUMIF(GL!$D$6:$D$6484,B15,GL!$I$6:$I$6484) -> 0 | G15: =IF(E15>F15,E15-F15,0) -> 0 | H15: =IF(F15>E15,F15-E15,0) -> 0 | N15: =G15+K15 -> 0 | P15: =M15 -> 0 | Q15: =O15*P15 -> 0 | R15: =N15-Q15 -> 0 | T15: =J15-M15 -> 0
B16: =TB!B53 -> M008 | C16: =TB!C53 -> Chorizo Beef/Salami Chorizo | D16: =SUMIF(GL!$D$5:$D$6446,B16,GL!$G$5:$G$6446) -> 3.02 | E16: =SUMIF(GL!$D$6:$D$6484,B16,GL!$H$6:$H$6484) -> 838050 | F16: =SUMIF(GL!$D$6:$D$6484,B16,GL!$I$6:$I$6484) -> 0 | G16: =IF(E16>F16,E16-F16,0) -> 838050 | H16: =IF(F16>E16,F16-E16,0) -> 0 | J16: 277500 | L16: =D16+I16 -> 3.02 | M16: =(G16+K16)/L16 -> 277500 | N16: =G16+K16 -> 838050 | P16: =M16 -> 277500 | Q16: =O16*P16 -> 0 | R16: =N16-Q16 -> 838050 | T16: =J16-M16 -> 0
B17: =TB!B54 -> M009 | C17: =TB!C54 -> Pork Pepperoni | D17: =SUMIF(GL!$D$5:$D$6446,B17,GL!$G$5:$G$6446) -> 0 | E17: =SUMIF(GL!$D$6:$D$6484,B17,GL!$H$6:$H$6484) -> 0 | F17: =SUMIF(GL!$D$6:$D$6484,B17,GL!$I$6:$I$6484) -> 0 | G17: =IF(E17>F17,E17-F17,0) -> 0 | H17: =IF(F17>E17,F17-E17,0) -> 0 | N17: =G17+K17 -> 0 | P17: =M17 -> 0 | Q17: =O17*P17 -> 0 | R17: =N17-Q17 -> 0 | T17: =J17-M17 -> 0
B18: =TB!B55 -> M010 | C18: =TB!C55 -> Italian Sausage | D18: =SUMIF(GL!$D$5:$D$6446,B18,GL!$G$5:$G$6446) -> 0 | E18: =SUMIF(GL!$D$6:$D$6484,B18,GL!$H$6:$H$6484) -> 0 | F18: =SUMIF(GL!$D$6:$D$6484,B18,GL!$I$6:$I$6484) -> 0 | G18: =IF(E18>F18,E18-F18,0) -> 0 | H18: =IF(F18>E18,F18-E18,0) -> 0 | N18: =G18+K18 -> 0 | P18: =M18 -> 0 | Q18: =O18*P18 -> 0 | R18: =N18-Q18 -> 0 | T18: =J18-M18 -> 0
B19: =TB!B56 -> M011 | C19: =TB!C56 -> English Banger Sausage | D19: =SUMIF(GL!$D$5:$D$6446,B19,GL!$G$5:$G$6446) -> 0 | E19: =SUMIF(GL!$D$6:$D$6484,B19,GL!$H$6:$H$6484) -> 0 | F19: =SUMIF(GL!$D$6:$D$6484,B19,GL!$I$6:$I$6484) -> 0 | G19: =IF(E19>F19,E19-F19,0) -> 0 | H19: =IF(F19>E19,F19-E19,0) -> 0 | N19: =G19+K19 -> 0 | P19: =M19 -> 0 | Q19: =O19*P19 -> 0 | R19: =N19-Q19 -> 0 | T19: =J19-M19 -> 0
B20: =TB!B57 -> M012 | C20: =TB!C57 -> Minced Pork | D20: =SUMIF(GL!$D$5:$D$6446,B20,GL!$G$5:$G$6446) -> 0 | E20: =SUMIF(GL!$D$6:$D$6484,B20,GL!$H$6:$H$6484) -> 0 | F20: =SUMIF(GL!$D$6:$D$6484,B20,GL!$I$6:$I$6484) -> 0 | G20: =IF(E20>F20,E20-F20,0) -> 0 | H20: =IF(F20>E20,F20-E20,0) -> 0 | N20: =G20+K20 -> 0 | P20: =M20 -> 0 | Q20: =O20*P20 -> 0 | R20: =N20-Q20 -> 0 | T20: =J20-M20 -> 0
B21: =TB!B58 -> M013 | C21: =TB!C58 -> Sausage Chicken | D21: =SUMIF(GL!$D$5:$D$6446,B21,GL!$G$5:$G$6446) -> 1.974 | E21: =SUMIF(GL!$D$6:$D$6484,B21,GL!$H$6:$H$6484) -> 246750 | F21: =SUMIF(GL!$D$6:$D$6484,B21,GL!$I$6:$I$6484) -> 0 | G21: =IF(E21>F21,E21-F21,0) -> 246750 | H21: =IF(F21>E21,F21-E21,0) -> 0 | J21: 125000 | L21: =D21+I21 -> 1.974 | M21: =(G21+K21)/L21 -> 125000 | N21: =G21+K21 -> 246750 | P21: =M21 -> 125000 | Q21: =O21*P21 -> 0 | R21: =N21-Q21 -> 246750 | T21: =J21-M21 -> 0
B22: =TB!B59 -> M014 | C22: =TB!C59 -> Pork Rib | D22: =SUMIF(GL!$D$5:$D$6446,B22,GL!$G$5:$G$6446) -> 0 | E22: =SUMIF(GL!$D$6:$D$6484,B22,GL!$H$6:$H$6484) -> 0 | F22: =SUMIF(GL!$D$6:$D$6484,B22,GL!$I$6:$I$6484) -> 0 | G22: =IF(E22>F22,E22-F22,0) -> 0 | H22: =IF(F22>E22,F22-E22,0) -> 0 | I22: 7.25 | J22: 122937 | K22: 891290 | L22: =D22+I22 -> 7.25 | M22: =(G22+K22)/L22 -> 122936.55 | N22: =G22+K22 -> 891290 | O22: 3.96 | P22: =M22 -> 122936.55 | Q22: =O22*P22 -> 486828.74 | R22: =N22-Q22 -> 404461.26 | T22: =J22-M22 -> 0.44827586
B23: =TB!B60 -> M015 | C23: =TB!C60 -> Beef Rib | D23: =SUMIF(GL!$D$5:$D$6446,B23,GL!$G$5:$G$6446) -> 10.4 | E23: =SUMIF(GL!$D$6:$D$6484,B23,GL!$H$6:$H$6484) -> 1768000 | F23: =SUMIF(GL!$D$6:$D$6484,B23,GL!$I$6:$I$6484) -> 0 | G23: =IF(E23>F23,E23-F23,0) -> 1768000 | H23: =IF(F23>E23,F23-E23,0) -> 0 | I23: 7.22 | J23: 164956 | K23: 1190979 | L23: =D23+I23 -> 17.62 | M23: =(G23+K23)/L23 -> 167932.97 | N23: =G23+K23 -> 2958979 | O23: 7.36 | P23: =M23 -> 167932.97 | Q23: =O23*P23 -> 1235986.7 | R23: =N23-Q23 -> 1722992.3 | T23: =J23-M23 -> -2976.9739
B24: =TB!B61 -> M016 | C24: =TB!C61 -> Beef Shank Cube | D24: =SUMIF(GL!$D$5:$D$6446,B24,GL!$G$5:$G$6446) -> 0 | E24: =SUMIF(GL!$D$6:$D$6484,B24,GL!$H$6:$H$6484) -> 0 | F24: =SUMIF(GL!$D$6:$D$6484,B24,GL!$I$6:$I$6484) -> 0 | G24: =IF(E24>F24,E24-F24,0) -> 0 | H24: =IF(F24>E24,F24-E24,0) -> 0 | N24: =G24+K24 -> 0 | P24: =M24 -> 0 | Q24: =O24*P24 -> 0 | R24: =N24-Q24 -> 0 | T24: =J24-M24 -> 0
B25: =TB!B62 -> M016A | C25: =TB!C62 -> Beef Cuberoll (Rib Eye) | D25: =SUMIF(GL!$D$5:$D$6446,B25,GL!$G$5:$G$6446) -> 9.14 | E25: =SUMIF(GL!$D$6:$D$6484,B25,GL!$H$6:$H$6484) -> 2544048 | F25: =SUMIF(GL!$D$6:$D$6484,B25,GL!$I$6:$I$6484) -> 0 | G25: =IF(E25>F25,E25-F25,0) -> 2544048 | H25: =IF(F25>E25,F25-E25,0) -> 0 | I25: 7.71 | J25: 266087 | K25: 2051531 | L25: =D25+I25 -> 16.85 | M25: =(G25+K25)/L25 -> 272734.66 | N25: =G25+K25 -> 4595579 | O25: 4.8 | P25: =M25 -> 272734.66 | Q25: =O25*P25 -> 1309126.4 | R25: =N25-Q25 -> 3286452.6 | T25: =J25-M25 -> -6647.6588
B26: =TB!B63 -> M017 | C26: =TB!C63 -> Bacon/Pork Bacon | D26: =SUMIF(GL!$D$5:$D$6446,B26,GL!$G$5:$G$6446) -> 4.06 | E26: =SUMIF(GL!$D$6:$D$6484,B26,GL!$H$6:$H$6484) -> 761615.4 | F26: =SUMIF(GL!$D$6:$D$6484,B26,GL!$I$6:$I$6484) -> 0 | G26: =IF(E26>F26,E26-F26,0) -> 761615.4 | H26: =IF(F26>E26,F26-E26,0) -> 0 | I26: 2.09 | J26: 185896 | K26: 388523 | L26: =D26+I26 -> 6.15 | M26: =(G26+K26)/L26 -> 187014.37 | N26: =G26+K26 -> 1150138.4 | O26: 4.67 | P26: =M26 -> 187014.37 | Q26: =O26*P26 -> 873357.13 | R26: =N26-Q26 -> 276781.27 | T26: =J26-M26 -> -1118.374
B27: =TB!B64 -> M018 | C27: =TB!C64 -> Ham | D27: =SUMIF(GL!$D$5:$D$6446,B27,GL!$G$5:$G$6446) -> 2.04 | E27: =SUMIF(GL!$D$6:$D$6484,B27,GL!$H$6:$H$6484) -> 418914 | F27: =SUMIF(GL!$D$6:$D$6484,B27,GL!$I$6:$I$6484) -> 0 | G27: =IF(E27>F27,E27-F27,0) -> 418914 | H27: =IF(F27>E27,F27-E27,0) -> 0 | I27: 2.72 | J27: 204058 | K27: 555038 | L27: =D27+I27 -> 4.76 | M27: =(G27+K27)/L27 -> 204611.76 | N27: =G27+K27 -> 973952 | O27: 3.06 | P27: =M27 -> 204611.76 | Q27: =O27*P27 -> 626112 | R27: =N27-Q27 -> 347840 | T27: =J27-M27 -> -553.76471
B28: =TB!B65 -> M019 | C28: =TB!C65 -> Beef Bacon | D28: =SUMIF(GL!$D$5:$D$6446,B28,GL!$G$5:$G$6446) -> 2 | E28: =SUMIF(GL!$D$6:$D$6484,B28,GL!$H$6:$H$6484) -> 366300 | F28: =SUMIF(GL!$D$6:$D$6484,B28,GL!$I$6:$I$6484) -> 0 | G28: =IF(E28>F28,E28-F28,0) -> 366300 | H28: =IF(F28>E28,F28-E28,0) -> 0 | I28: 1.86 | J28: 76632 | K28: 142535 | L28: =D28+I28 -> 3.86 | M28: =(G28+K28)/L28 -> 131822.54 | N28: =G28+K28 -> 508835 | O28: 2.87 | P28: =M28 -> 131822.54 | Q28: =O28*P28 -> 378330.69 | R28: =N28-Q28 -> 130504.31 | T28: =J28-M28 -> -55190.539
B29: =TB!B66 -> M020 | C29: =TB!C66 -> Pork Leg | D29: =SUMIF(GL!$D$5:$D$6446,B29,GL!$G$5:$G$6446) -> 0 | E29: =SUMIF(GL!$D$6:$D$6484,B29,GL!$H$6:$H$6484) -> 0 | F29: =SUMIF(GL!$D$6:$D$6484,B29,GL!$I$6:$I$6484) -> 0 | G29: =IF(E29>F29,E29-F29,0) -> 0 | H29: =IF(F29>E29,F29-E29,0) -> 0 | N29: =G29+K29 -> 0 | P29: =M29 -> 0 | Q29: =O29*P29 -> 0 | R29: =N29-Q29 -> 0 | T29: =J29-M29 -> 0
B30: =TB!B67 -> M021 | C30: =TB!C67 -> Ebi (Udang Kecil Kering) | D30: =SUMIF(GL!$D$5:$D$6446,B30,GL!$G$5:$G$6446) -> 0 | E30: =SUMIF(GL!$D$6:$D$6484,B30,GL!$H$6:$H$6484) -> 0 | F30: =SUMIF(GL!$D$6:$D$6484,B30,GL!$I$6:$I$6484) -> 0 | G30: =IF(E30>F30,E30-F30,0) -> 0 | H30: =IF(F30>E30,F30-E30,0) -> 0 | I30: 0.97 | J30: 103051 | K30: 99959 | L30: =D30+I30 -> 0.97 | M30: =(G30+K30)/L30 -> 103050.52 | N30: =G30+K30 -> 99959 | O30: 0.83 | P30: =M30 -> 103050.52 | Q30: =O30*P30 -> 85531.928 | R30: =N30-Q30 -> 14427.072 | T30: =J30-M30 -> 0.48453608
B31: =TB!B68 -> M022 | C31: =TB!C68 -> Burger Patties | D31: =SUMIF(GL!$D$5:$D$6446,B31,GL!$G$5:$G$6446) -> 0 | E31: =SUMIF(GL!$D$6:$D$6484,B31,GL!$H$6:$H$6484) -> 0 | F31: =SUMIF(GL!$D$6:$D$6484,B31,GL!$I$6:$I$6484) -> 0 | G31: =IF(E31>F31,E31-F31,0) -> 0 | H31: =IF(F31>E31,F31-E31,0) -> 0 | N31: =G31+K31 -> 0 | P31: =M31 -> 0 | Q31: =O31*P31 -> 0 | R31: =N31-Q31 -> 0 | T31: =J31-M31 -> 0
B32: =TB!B69 -> M023 | C32: =TB!C69 -> Striploin / Sirloin | D32: =SUMIF(GL!$D$5:$D$6446,B32,GL!$G$5:$G$6446) -> 23.2 | E32: =SUMIF(GL!$D$6:$D$6484,B32,GL!$H$6:$H$6484) -> 4524000 | F32: =SUMIF(GL!$D$6:$D$6484,B32,GL!$I$6:$I$6484) -> 0 | G32: =IF(E32>F32,E32-F32,0) -> 4524000 | H32: =IF(F32>E32,F32-E32,0) -> 0 | I32: 7.6 | J32: 195000 | K32: 1482000 | L32: =D32+I32 -> 30.8 | M32: =(G32+K32)/L32 -> 195000 | N32: =G32+K32 -> 6006000 | O32: 10.8 | P32: =M32 -> 195000 | Q32: =O32*P32 -> 2106000 | R32: =N32-Q32 -> 3900000 | T32: =J32-M32 -> 0
B33: =TB!B70 -> M024 | C33: =TB!C70 -> Chicken Wing / Sayap Ayam | D33: =SUMIF(GL!$D$5:$D$6446,B33,GL!$G$5:$G$6446) -> 37 | E33: =SUMIF(GL!$D$6:$D$6484,B33,GL!$H$6:$H$6484) -> 1416000 | F33: =SUMIF(GL!$D$6:$D$6484,B33,GL!$I$6:$I$6484) -> 0 | G33: =IF(E33>F33,E33-F33,0) -> 1416000 | H33: =IF(F33>E33,F33-E33,0) -> 0 | I33: 16.5 | J33: 40432 | K33: 667122 | L33: =D33+I33 -> 53.5 | M33: =(G33+K33)/L33 -> 38936.86 | N33: =G33+K33 -> 2083122 | O33: 21.5 | P33: =M33 -> 38936.86 | Q33: =O33*P33 -> 837142.49 | R33: =N33-Q33 -> 1245979.5 | T33: =J33-M33 -> 1495.1402
B34: =TB!B71 -> M025 | C34: =TB!C71 -> Chicken Breast | D34: =SUMIF(GL!$D$5:$D$6446,B34,GL!$G$5:$G$6446) -> 79.61 | E34: =SUMIF(GL!$D$6:$D$6484,B34,GL!$H$6:$H$6484) -> 4090110 | F34: =SUMIF(GL!$D$6:$D$6484,B34,GL!$I$6:$I$6484) -> 0 | G34: =IF(E34>F34,E34-F34,0) -> 4090110 | H34: =IF(F34>E34,F34-E34,0) -> 0 | I34: 18.3 | J34: 57788 | K34: 1057512 | L34: =D34+I34 -> 97.91 | M34: =(G34+K34)/L34 -> 52575.038 | N34: =G34+K34 -> 5147622 | O34: 21.3 | P34: =M34 -> 52575.038 | Q34: =O34*P34 -> 1119848.3 | R34: =N34-Q34 -> 4027773.7 | T34: =J34-M34 -> 5212.9617
B35: =TB!B72 -> M026 | C35: =TB!C72 -> Chicken Leg / Paha Ayam | D35: =SUMIF(GL!$D$5:$D$6446,B35,GL!$G$5:$G$6446) -> 0 | E35: =SUMIF(GL!$D$6:$D$6484,B35,GL!$H$6:$H$6484) -> 0 | F35: =SUMIF(GL!$D$6:$D$6484,B35,GL!$I$6:$I$6484) -> 0 | G35: =IF(E35>F35,E35-F35,0) -> 0 | H35: =IF(F35>E35,F35-E35,0) -> 0 | N35: =G35+K35 -> 0 | P35: =M35 -> 0 | Q35: =O35*P35 -> 0 | R35: =N35-Q35 -> 0 | T35: =J35-M35 -> 0
B36: =TB!B73 -> M027 | C36: =TB!C73 -> Chicken Leg Bone Less | D36: =SUMIF(GL!$D$5:$D$6446,B36,GL!$G$5:$G$6446) -> 0 | E36: =SUMIF(GL!$D$6:$D$6484,B36,GL!$H$6:$H$6484) -> 0 | F36: =SUMIF(GL!$D$6:$D$6484,B36,GL!$I$6:$I$6484) -> 0 | G36: =IF(E36>F36,E36-F36,0) -> 0 | H36: =IF(F36>E36,F36-E36,0) -> 0 | N36: =G36+K36 -> 0 | P36: =M36 -> 0 | Q36: =O36*P36 -> 0 | R36: =N36-Q36 -> 0 | T36: =J36-M36 -> 0
B37: =TB!B74 -> M028 | C37: =TB!C74 -> Chicken Leg Fillet/Ayam Penjantan | D37: =SUMIF(GL!$D$5:$D$6446,B37,GL!$G$5:$G$6446) -> 16 | E37: =SUMIF(GL!$D$6:$D$6484,B37,GL!$H$6:$H$6484) -> 1120000 | F37: =SUMIF(GL!$D$6:$D$6484,B37,GL!$I$6:$I$6484) -> 0 | G37: =IF(E37>F37,E37-F37,0) -> 1120000 | H37: =IF(F37>E37,F37-E37,0) -> 0 | I37: 3.84 | J37: 69649 | K37: 267452 | L37: =D37+I37 -> 19.84 | M37: =(G37+K37)/L37 -> 69932.056 | N37: =G37+K37 -> 1387452 | O37: 6.41 | P37: =M37 -> 69932.056 | Q37: =O37*P37 -> 448264.48 | R37: =N37-Q37 -> 939187.52 | T37: =J37-M37 -> -283.05645
B38: =TB!B75 -> M029 | C38: =TB!C75 -> Bakso Beef | D38: =SUMIF(GL!$D$5:$D$6446,B38,GL!$G$5:$G$6446) -> 0 | E38: =SUMIF(GL!$D$6:$D$6484,B38,GL!$H$6:$H$6484) -> 0 | F38: =SUMIF(GL!$D$6:$D$6484,B38,GL!$I$6:$I$6484) -> 0 | G38: =IF(E38>F38,E38-F38,0) -> 0 | H38: =IF(F38>E38,F38-E38,0) -> 0 | I38: 1 | J38: 118901 | K38: 118901 | L38: =D38+I38 -> 1 | M38: =(G38+K38)/L38 -> 118901 | N38: =G38+K38 -> 118901 | O38: 1 | P38: =M38 -> 118901 | Q38: =O38*P38 -> 118901 | R38: =N38-Q38 -> 0 | T38: =J38-M38 -> 0
B39: =TB!B76 -> M030 | C39: =TB!C76 -> Minced Chicken | D39: =SUMIF(GL!$D$5:$D$6446,B39,GL!$G$5:$G$6446) -> 0 | E39: =SUMIF(GL!$D$6:$D$6484,B39,GL!$H$6:$H$6484) -> 0 | F39: =SUMIF(GL!$D$6:$D$6484,B39,GL!$I$6:$I$6484) -> 0 | G39: =IF(E39>F39,E39-F39,0) -> 0 | H39: =IF(F39>E39,F39-E39,0) -> 0 | N39: =G39+K39 -> 0 | P39: =M39 -> 0 | Q39: =O39*P39 -> 0 | R39: =N39-Q39 -> 0 | T39: =J39-M39 -> 0
B40: =TB!B77 -> M031 | C40: =TB!C77 -> Beef Meltique Saikoro | D40: =SUMIF(GL!$D$5:$D$6446,B40,GL!$G$5:$G$6446) -> 4 | E40: =SUMIF(GL!$D$6:$D$6484,B40,GL!$H$6:$H$6484) -> 680000 | F40: =SUMIF(GL!$D$6:$D$6484,B40,GL!$I$6:$I$6484) -> 0 | G40: =IF(E40>F40,E40-F40,0) -> 680000 | H40: =IF(F40>E40,F40-E40,0) -> 0 | I40: 1.6 | J40: 170173 | K40: 272277 | L40: =D40+I40 -> 5.6 | M40: =(G40+K40)/L40 -> 170049.46 | N40: =G40+K40 -> 952277 | O40: 1.26 | P40: =M40 -> 170049.46 | Q40: =O40*P40 -> 214262.33 | R40: =N40-Q40 -> 738014.68 | T40: =J40-M40 -> 123.53571
B41: =TB!B78 -> M032 | C41: =TB!C78 -> Chiken Dramstick | D41: =SUMIF(GL!$D$5:$D$6446,B41,GL!$G$5:$G$6446) -> 0 | E41: =SUMIF(GL!$D$6:$D$6484,B41,GL!$H$6:$H$6484) -> 0 | F41: =SUMIF(GL!$D$6:$D$6484,B41,GL!$I$6:$I$6484) -> 0 | G41: =IF(E41>F41,E41-F41,0) -> 0 | H41: =IF(F41>E41,F41-E41,0) -> 0 | N41: =G41+K41 -> 0 | P41: =M41 -> 0 | Q41: =O41*P41 -> 0 | R41: =N41-Q41 -> 0 | T41: =J41-M41 -> 0
B42: =TB!B79 -> M033 | C42: =TB!C79 -> Tuna | D42: =SUMIF(GL!$D$5:$D$6446,B42,GL!$G$5:$G$6446) -> 0 | E42: =SUMIF(GL!$D$6:$D$6484,B42,GL!$H$6:$H$6484) -> 0 | F42: =SUMIF(GL!$D$6:$D$6484,B42,GL!$I$6:$I$6484) -> 0 | G42: =IF(E42>F42,E42-F42,0) -> 0 | H42: =IF(F42>E42,F42-E42,0) -> 0 | I42: 2.4 | J42: 122972 | K42: 295132 | L42: =D42+I42 -> 2.4 | M42: =(G42+K42)/L42 -> 122971.67 | N42: =G42+K42 -> 295132 | O42: 2.53 | P42: =M42 -> 122971.67 | Q42: =O42*P42 -> 311118.32 | R42: =N42-Q42 -> -15986.317 | T42: =J42-M42 -> 0.33333333
B43: =TB!B80 -> M034 | C43: =TB!C80 -> Cumi | D43: =SUMIF(GL!$D$5:$D$6446,B43,GL!$G$5:$G$6446) -> 9 | E43: =SUMIF(GL!$D$6:$D$6484,B43,GL!$H$6:$H$6484) -> 711000 | F43: =SUMIF(GL!$D$6:$D$6484,B43,GL!$I$6:$I$6484) -> 0 | G43: =IF(E43>F43,E43-F43,0) -> 711000 | H43: =IF(F43>E43,F43-E43,0) -> 0 | I43: 4.16 | J43: 89474 | K43: 372211 | L43: =D43+I43 -> 13.16 | M43: =(G43+K43)/L43 -> 82310.866 | N43: =G43+K43 -> 1083211 | O43: 6.98 | P43: =M43 -> 82310.866 | Q43: =O43*P43 -> 574529.85 | R43: =N43-Q43 -> 508681.15 | T43: =J43-M43 -> 7163.1337
B44: =TB!B81 -> M035 | C44: =TB!C81 -> Udang / Prawn 16" | D44: =SUMIF(GL!$D$5:$D$6446,B44,GL!$G$5:$G$6446) -> 0 | E44: =SUMIF(GL!$D$6:$D$6484,B44,GL!$H$6:$H$6484) -> 0 | F44: =SUMIF(GL!$D$6:$D$6484,B44,GL!$I$6:$I$6484) -> 0 | G44: =IF(E44>F44,E44-F44,0) -> 0 | H44: =IF(F44>E44,F44-E44,0) -> 0 | N44: =G44+K44 -> 0 | P44: =M44 -> 0 | Q44: =O44*P44 -> 0 | R44: =N44-Q44 -> 0 | T44: =J44-M44 -> 0
B45: =TB!B82 -> M036 | C45: =TB!C82 -> Kakap Fish | D45: =SUMIF(GL!$D$5:$D$6446,B45,GL!$G$5:$G$6446) -> 0 | E45: =SUMIF(GL!$D$6:$D$6484,B45,GL!$H$6:$H$6484) -> 0 | F45: =SUMIF(GL!$D$6:$D$6484,B45,GL!$I$6:$I$6484) -> 0 | G45: =IF(E45>F45,E45-F45,0) -> 0 | H45: =IF(F45>E45,F45-E45,0) -> 0 | N45: =G45+K45 -> 0 | P45: =M45 -> 0 | Q45: =O45*P45 -> 0 | R45: =N45-Q45 -> 0 | T45: =J45-M45 -> 0
B46: =TB!B83 -> M037 | C46: =TB!C83 -> Squid Baby | D46: =SUMIF(GL!$D$5:$D$6446,B46,GL!$G$5:$G$6446) -> 0 | E46: =SUMIF(GL!$D$6:$D$6484,B46,GL!$H$6:$H$6484) -> 0 | F46: =SUMIF(GL!$D$6:$D$6484,B46,GL!$I$6:$I$6484) -> 0 | G46: =IF(E46>F46,E46-F46,0) -> 0 | H46: =IF(F46>E46,F46-E46,0) -> 0 | N46: =G46+K46 -> 0 | P46: =M46 -> 0 | Q46: =O46*P46 -> 0 | R46: =N46-Q46 -> 0 | T46: =J46-M46 -> 0
B47: =TB!B84 -> M038 | C47: =TB!C84 -> Anchovies | D47: =SUMIF(GL!$D$5:$D$6446,B47,GL!$G$5:$G$6446) -> 0 | E47: =SUMIF(GL!$D$6:$D$6484,B47,GL!$H$6:$H$6484) -> 0 | F47: =SUMIF(GL!$D$6:$D$6484,B47,GL!$I$6:$I$6484) -> 0 | G47: =IF(E47>F47,E47-F47,0) -> 0 | H47: =IF(F47>E47,F47-E47,0) -> 0 | N47: =G47+K47 -> 0 | P47: =M47 -> 0 | Q47: =O47*P47 -> 0 | R47: =N47-Q47 -> 0 | T47: =J47-M47 -> 0
B48: =TB!B85 -> M039 | C48: =TB!C85 -> Tenderloin | D48: =SUMIF(GL!$D$5:$D$6446,B48,GL!$G$5:$G$6446) -> 7.44 | E48: =SUMIF(GL!$D$6:$D$6484,B48,GL!$H$6:$H$6484) -> 1621920 | F48: =SUMIF(GL!$D$6:$D$6484,B48,GL!$I$6:$I$6484) -> 0 | G48: =IF(E48>F48,E48-F48,0) -> 1621920 | H48: =IF(F48>E48,F48-E48,0) -> 0 | I48: 5.79 | J48: 177770 | K48: 1029287 | L48: =D48+I48 -> 13.23 | M48: =(G48+K48)/L48 -> 200393.58 | N48: =G48+K48 -> 2651207 | O48: 5.49 | P48: =M48 -> 200393.58 | Q48: =O48*P48 -> 1100160.7 | R48: =N48-Q48 -> 1551046.3 | S48: KENAIKAN HARGA | T48: =J48-M48 -> -22623.575
B49: =TB!B86 -> M040 | C49: =TB!C86 -> Snapper Fillet | D49: =SUMIF(GL!$D$5:$D$6446,B49,GL!$G$5:$G$6446) -> 3.3 | E49: =SUMIF(GL!$D$6:$D$6484,B49,GL!$H$6:$H$6484) -> 396000 | F49: =SUMIF(GL!$D$6:$D$6484,B49,GL!$I$6:$I$6484) -> 0 | G49: =IF(E49>F49,E49-F49,0) -> 396000 | H49: =IF(F49>E49,F49-E49,0) -> 0 | I49: 3.78 | J49: 125397 | K49: 474002 | L49: =D49+I49 -> 7.08 | M49: =(G49+K49)/L49 -> 122881.64 | N49: =G49+K49 -> 870002 | O49: 6 | P49: =M49 -> 122881.64 | Q49: =O49*P49 -> 737289.83 | R49: =N49-Q49 -> 132712.17 | T49: =J49-M49 -> 2515.3616
B50: =TB!B87 -> M041 | C50: =TB!C87 -> Udang/Prawn 25" | D50: =SUMIF(GL!$D$5:$D$6446,B50,GL!$G$5:$G$6446) -> 40 | E50: =SUMIF(GL!$D$6:$D$6484,B50,GL!$H$6:$H$6484) -> 6450000 | F50: =SUMIF(GL!$D$6:$D$6484,B50,GL!$I$6:$I$6484) -> 0 | G50: =IF(E50>F50,E50-F50,0) -> 6450000 | H50: =IF(F50>E50,F50-E50,0) -> 0 | I50: 4.55 | J50: 160592 | K50: 730694 | L50: =D50+I50 -> 44.55 | M50: =(G50+K50)/L50 -> 161182.81 | N50: =G50+K50 -> 7180694 | O50: 13.57 | P50: =M50 -> 161182.81 | Q50: =O50*P50 -> 2187250.7 | R50: =N50-Q50 -> 4993443.3 | T50: =J50-M50 -> -590.80584
B51: =TB!B88 -> M042 | C51: =TB!C88 -> Baby Lobster | D51: =SUMIF(GL!$D$5:$D$6446,B51,GL!$G$5:$G$6446) -> 0 | E51: =SUMIF(GL!$D$6:$D$6484,B51,GL!$H$6:$H$6484) -> 0 | F51: =SUMIF(GL!$D$6:$D$6484,B51,GL!$I$6:$I$6484) -> 0 | G51: =IF(E51>F51,E51-F51,0) -> 0 | H51: =IF(F51>E51,F51-E51,0) -> 0 | N51: =G51+K51 -> 0 | P51: =M51 -> 0 | Q51: =O51*P51 -> 0 | R51: =N51-Q51 -> 0 | T51: =J51-M51 -> 0
B52: =TB!B89 -> M043 | C52: =TB!C89 -> Pork Loin | D52: =SUMIF(GL!$D$5:$D$6446,B52,GL!$G$5:$G$6446) -> 0 | E52: =SUMIF(GL!$D$6:$D$6484,B52,GL!$H$6:$H$6484) -> 0 | F52: =SUMIF(GL!$D$6:$D$6484,B52,GL!$I$6:$I$6484) -> 0 | G52: =IF(E52>F52,E52-F52,0) -> 0 | H52: =IF(F52>E52,F52-E52,0) -> 0 | I52: 4.17 | J52: 120331 | K52: 501779 | L52: =D52+I52 -> 4.17 | M52: =(G52+K52)/L52 -> 120330.7 | N52: =G52+K52 -> 501779 | O52: 4.43 | P52: =M52 -> 120330.7 | Q52: =O52*P52 -> 533064.98 | R52: =N52-Q52 -> -31285.981 | T52: =J52-M52 -> 0.30455635
B53: =TB!B90 -> M044 | C53: =TB!C90 -> Dori | D53: =SUMIF(GL!$D$5:$D$6446,B53,GL!$G$5:$G$6446) -> 0 | E53: =SUMIF(GL!$D$6:$D$6484,B53,GL!$H$6:$H$6484) -> 0 | F53: =SUMIF(GL!$D$6:$D$6484,B53,GL!$I$6:$I$6484) -> 0 | G53: =IF(E53>F53,E53-F53,0) -> 0 | H53: =IF(F53>E53,F53-E53,0) -> 0 | N53: =G53+K53 -> 0 | P53: =M53 -> 0 | Q53: =O53*P53 -> 0 | R53: =N53-Q53 -> 0 | T53: =J53-M53 -> 0
B54: =TB!B91 -> M045 | C54: =TB!C91 -> Salmon Steak | D54: =SUMIF(GL!$D$5:$D$6446,B54,GL!$G$5:$G$6446) -> 5 | E54: =SUMIF(GL!$D$6:$D$6484,B54,GL!$H$6:$H$6484) -> 1445000 | F54: =SUMIF(GL!$D$6:$D$6484,B54,GL!$I$6:$I$6484) -> 0 | G54: =IF(E54>F54,E54-F54,0) -> 1445000 | H54: =IF(F54>E54,F54-E54,0) -> 0 | I54: 1.03 | J54: 260012 | K54: 267813 | L54: =D54+I54 -> 6.03 | M54: =(G54+K54)/L54 -> 284048.59 | N54: =G54+K54 -> 1712813 | O54: 2 | P54: =M54 -> 284048.59 | Q54: =O54*P54 -> 568097.18 | R54: =N54-Q54 -> 1144715.8 | S54: BEDA SUPPLIER | T54: =J54-M54 -> -24036.59
B55: =TB!B92 -> M046 | C55: =TB!C92 -> Belly Skin On | D55: =SUMIF(GL!$D$5:$D$6446,B55,GL!$G$5:$G$6446) -> 0 | E55: =SUMIF(GL!$D$6:$D$6484,B55,GL!$H$6:$H$6484) -> 0 | F55: =SUMIF(GL!$D$6:$D$6484,B55,GL!$I$6:$I$6484) -> 0 | G55: =IF(E55>F55,E55-F55,0) -> 0 | H55: =IF(F55>E55,F55-E55,0) -> 0 | N55: =G55+K55 -> 0 | P55: =M55 -> 0 | Q55: =O55*P55 -> 0 | R55: =N55-Q55 -> 0 | T55: =J55-M55 -> 0
B56: =TB!B93 -> M047 | C56: =TB!C93 -> Pork Toulouse | D56: =SUMIF(GL!$D$5:$D$6446,B56,GL!$G$5:$G$6446) -> 8.16 | E56: =SUMIF(GL!$D$6:$D$6484,B56,GL!$H$6:$H$6484) -> 1168032 | F56: =SUMIF(GL!$D$6:$D$6484,B56,GL!$I$6:$I$6484) -> 0 | G56: =IF(E56>F56,E56-F56,0) -> 1168032 | H56: =IF(F56>E56,F56-E56,0) -> 0 | I56: 3.5 | J56: 149045 | K56: 521657 | L56: =D56+I56 -> 11.66 | M56: =(G56+K56)/L56 -> 144913.29 | N56: =G56+K56 -> 1689689 | O56: 3.04 | P56: =M56 -> 144913.29 | Q56: =O56*P56 -> 440536.41 | R56: =N56-Q56 -> 1249152.6 | T56: =J56-M56 -> 4131.7067
B57: =TB!B94 -> M048 | C57: =TB!C94 -> Beef Toulouse | D57: =SUMIF(GL!$D$5:$D$6446,B57,GL!$G$5:$G$6446) -> 5.03 | E57: =SUMIF(GL!$D$6:$D$6484,B57,GL!$H$6:$H$6484) -> 829950 | F57: =SUMIF(GL!$D$6:$D$6484,B57,GL!$I$6:$I$6484) -> 0 | G57: =IF(E57>F57,E57-F57,0) -> 829950 | H57: =IF(F57>E57,F57-E57,0) -> 0 | I57: 4.87 | J57: 165012 | K57: 803607 | L57: =D57+I57 -> 9.9 | M57: =(G57+K57)/L57 -> 165005.76 | N57: =G57+K57 -> 1633557 | O57: 4.44 | P57: =M57 -> 165005.76 | Q57: =O57*P57 -> 732625.56 | R57: =N57-Q57 -> 900931.44 | T57: =J57-M57 -> 6.2424242
B58: =TB!B95 -> M049 | C58: =TB!C95 -> Chicken Toulouse | D58: =SUMIF(GL!$D$5:$D$6446,B58,GL!$G$5:$G$6446) -> 7.52 | E58: =SUMIF(GL!$D$6:$D$6484,B58,GL!$H$6:$H$6484) -> 1013872 | F58: =SUMIF(GL!$D$6:$D$6484,B58,GL!$I$6:$I$6484) -> 0 | G58: =IF(E58>F58,E58-F58,0) -> 1013872 | H58: =IF(F58>E58,F58-E58,0) -> 0 | I58: 2.1 | J58: 154137 | K58: 323689 | L58: =D58+I58 -> 9.62 | M58: =(G58+K58)/L58 -> 139039.6 | N58: =G58+K58 -> 1337561 | O58: 2.85 | P58: =M58 -> 139039.6 | Q58: =O58*P58 -> 396262.87 | R58: =N58-Q58 -> 941298.13 | T58: =J58-M58 -> 15097.395
B59: =TB!B96 -> M050 | C59: =TB!C96 -> Beef Loin | D59: =SUMIF(GL!$D$5:$D$6446,B59,GL!$G$5:$G$6446) -> 0 | E59: =SUMIF(GL!$D$6:$D$6484,B59,GL!$H$6:$H$6484) -> 0 | F59: =SUMIF(GL!$D$6:$D$6484,B59,GL!$I$6:$I$6484) -> 0 | G59: =IF(E59>F59,E59-F59,0) -> 0 | H59: =IF(F59>E59,F59-E59,0) -> 0 | N59: =G59+K59 -> 0 | P59: =M59 -> 0 | Q59: =O59*P59 -> 0 | R59: =N59-Q59 -> 0 | T59: =J59-M59 -> 0
B60: =TB!B97 -> M051 | C60: =TB!C97 -> Tuna Can | D60: =SUMIF(GL!$D$5:$D$6446,B60,GL!$G$5:$G$6446) -> 0 | E60: =SUMIF(GL!$D$6:$D$6484,B60,GL!$H$6:$H$6484) -> 0 | F60: =SUMIF(GL!$D$6:$D$6484,B60,GL!$I$6:$I$6484) -> 0 | G60: =IF(E60>F60,E60-F60,0) -> 0 | H60: =IF(F60>E60,F60-E60,0) -> 0 | N60: =G60+K60 -> 0 | P60: =M60 -> 0 | Q60: =O60*P60 -> 0 | R60: =N60-Q60 -> 0 | T60: =J60-M60 -> 0
B61: =TB!B98 -> M052 | C61: =TB!C98 -> Top Side Scolopin | D61: =SUMIF(GL!$D$5:$D$6446,B61,GL!$G$5:$G$6446) -> 0 | E61: =SUMIF(GL!$D$6:$D$6484,B61,GL!$H$6:$H$6484) -> 0 | F61: =SUMIF(GL!$D$6:$D$6484,B61,GL!$I$6:$I$6484) -> 0 | G61: =IF(E61>F61,E61-F61,0) -> 0 | H61: =IF(F61>E61,F61-E61,0) -> 0 | N61: =G61+K61 -> 0 | P61: =M61 -> 0 | Q61: =O61*P61 -> 0 | R61: =N61-Q61 -> 0 | T61: =J61-M61 -> 0
B62: =TB!B99 -> M053 | C62: =TB!C99 -> Pork Belly Skin Off | D62: =SUMIF(GL!$D$5:$D$6446,B62,GL!$G$5:$G$6446) -> 0 | E62: =SUMIF(GL!$D$6:$D$6484,B62,GL!$H$6:$H$6484) -> 0 | F62: =SUMIF(GL!$D$6:$D$6484,B62,GL!$I$6:$I$6484) -> 0 | G62: =IF(E62>F62,E62-F62,0) -> 0 | H62: =IF(F62>E62,F62-E62,0) -> 0 | N62: =G62+K62 -> 0 | P62: =M62 -> 0 | Q62: =O62*P62 -> 0 | R62: =N62-Q62 -> 0 | T62: =J62-M62 -> 0
B63: =TB!B100 -> M053A | C63: =TB!C100 -> Tulang Sapi | D63: =SUMIF(GL!$D$5:$D$6446,B63,GL!$G$5:$G$6446) -> 5 | E63: =SUMIF(GL!$D$6:$D$6484,B63,GL!$H$6:$H$6484) -> 125000 | F63: =SUMIF(GL!$D$6:$D$6484,B63,GL!$I$6:$I$6484) -> 0 | G63: =IF(E63>F63,E63-F63,0) -> 125000 | H63: =IF(F63>E63,F63-E63,0) -> 0 | I63: 2.69 | J63: 25000 | K63: 67250 | L63: =D63+I63 -> 7.69 | M63: =(G63+K63)/L63 -> 25000 | N63: =G63+K63 -> 192250 | O63: 3.43 | P63: =M63 -> 25000 | Q63: =O63*P63 -> 85750 | R63: =N63-Q63 -> 106500 | T63: =J63-M63 -> 0
B64: =TB!B101 -> 0 | C64: =TB!C101 | D64: =SUMIF(GL!$D$5:$D$6446,B64,GL!$G$5:$G$6446) -> 0 | E64: =SUMIF(GL!$D$6:$D$6484,B64,GL!$H$6:$H$6484) -> 0 | F64: =SUMIF(GL!$D$6:$D$6484,B64,GL!$I$6:$I$6484) -> 0 | G64: =IF(E64>F64,E64-F64,0) -> 0 | H64: =IF(F64>E64,F64-E64,0) -> 0 | N64: =G64+K64 -> 0 | P64: =M64 -> 0 | Q64: =O64*P64 -> 0 | R64: =N64-Q64 -> 0 | T64: =J64-M64 -> 0
D65: =SUMIF(GL!$D$5:$D$6446,B65,GL!$G$5:$G$6446) -> 0 | E65: =SUMIF(GL!$D$6:$D$6484,B65,GL!$H$6:$H$6484) -> 0 | F65: =SUMIF(GL!$D$6:$D$6484,B65,GL!$I$6:$I$6484) -> 0 | G65: =IF(E65>F65,E65-F65,0) -> 0 | H65: =IF(F65>E65,F65-E65,0) -> 0 | N65: =G65+K65 -> 0 | P65: =M65 -> 0 | Q65: =O65*P65 -> 0 | R65: =N65-Q65 -> 0 | T65: =J65-M65 -> 0
D66: =SUMIF(GL!$D$5:$D$6446,B66,GL!$G$5:$G$6446) -> 0 | E66: =SUMIF(GL!$D$6:$D$6484,B66,GL!$H$6:$H$6484) -> 0 | F66: =SUMIF(GL!$D$6:$D$6484,B66,GL!$I$6:$I$6484) -> 0 | G66: =IF(E66>F66,E66-F66,0) -> 0 | H66: =IF(F66>E66,F66-E66,0) -> 0 | N66: =G66+K66 -> 0 | P66: =M66 -> 0 | Q66: =O66*P66 -> 0 | R66: =N66-Q66 -> 0 | T66: =J66-M66 -> 0
C67: VEGETABLE & FRUIT | D67: =SUMIF(GL!$D$5:$D$6446,B67,GL!$G$5:$G$6446) -> 0 | E67: =SUMIF(GL!$D$6:$D$6484,B67,GL!$H$6:$H$6484) -> 0 | F67: =SUMIF(GL!$D$6:$D$6484,B67,GL!$I$6:$I$6484) -> 0 | G67: =IF(E67>F67,E67-F67,0) -> 0 | H67: =IF(F67>E67,F67-E67,0) -> 0 | N67: =G67+K67 -> 0 | P67: =M67 -> 0 | Q67: =O67*P67 -> 0 | R67: =N67-Q67 -> 0 | T67: =J67-M67 -> 0
B68: =TB!B104 -> V001 | C68: =TB!C104 -> Great Chilli / Lombok Besar | D68: =SUMIF(GL!$D$5:$D$6446,B68,GL!$G$5:$G$6446) -> 4.37 | E68: =SUMIF(GL!$D$6:$D$6484,B68,GL!$H$6:$H$6484) -> 214000 | F68: =SUMIF(GL!$D$6:$D$6484,B68,GL!$I$6:$I$6484) -> 0 | G68: =IF(E68>F68,E68-F68,0) -> 214000 | H68: =IF(F68>E68,F68-E68,0) -> 0 | I68: 0.33 | J68: 52879 | K68: 17450 | L68: =D68+I68 -> 4.7 | M68: =(G68+K68)/L68 -> 49244.681 | N68: =G68+K68 -> 231450 | O68: 0.6 | P68: =M68 -> 49244.681 | Q68: =O68*P68 -> 29546.809 | R68: =N68-Q68 -> 201903.19 | T68: =J68-M68 -> 3634.3191
B69: =TB!B105 -> V002 | C69: =TB!C105 -> Tomato 1 Kg | D69: =SUMIF(GL!$D$5:$D$6446,B69,GL!$G$5:$G$6446) -> 19.2 | E69: =SUMIF(GL!$D$6:$D$6484,B69,GL!$H$6:$H$6484) -> 381000 | F69: =SUMIF(GL!$D$6:$D$6484,B69,GL!$I$6:$I$6484) -> 0 | G69: =IF(E69>F69,E69-F69,0) -> 381000 | H69: =IF(F69>E69,F69-E69,0) -> 0 | I69: 2.26 | J69: 20176 | K69: 45598 | L69: =D69+I69 -> 21.46 | M69: =(G69+K69)/L69 -> 19878.751 | N69: =G69+K69 -> 426598 | O69: 3.1 | P69: =M69 -> 19878.751 | Q69: =O69*P69 -> 61624.129 | R69: =N69-Q69 -> 364973.87 | T69: =J69-M69 -> 297.24884
B70: =TB!B106 -> V003 | C70: =TB!C106 -> Japanese Cucumber/Timun | D70: =SUMIF(GL!$D$5:$D$6446,B70,GL!$G$5:$G$6446) -> 20 | E70: =SUMIF(GL!$D$6:$D$6484,B70,GL!$H$6:$H$6484) -> 260000 | F70: =SUMIF(GL!$D$6:$D$6484,B70,GL!$I$6:$I$6484) -> 0 | G70: =IF(E70>F70,E70-F70,0) -> 260000 | H70: =IF(F70>E70,F70-E70,0) -> 0 | I70: 0.31 | J70: 10000 | K70: 3100 | L70: =D70+I70 -> 20.31 | M70: =(G70+K70)/L70 -> 12954.21 | N70: =G70+K70 -> 263100 | O70: 1.5 | P70: =M70 -> 12954.21 | Q70: =O70*P70 -> 19431.315 | R70: =N70-Q70 -> 243668.69 | T70: =J70-M70 -> -2954.2097
B71: =TB!B107 -> V004 | C71: =TB!C107 -> Garlic/Bawang Putih | D71: =SUMIF(GL!$D$5:$D$6446,B71,GL!$G$5:$G$6446) -> 3.933 | E71: =SUMIF(GL!$D$6:$D$6484,B71,GL!$H$6:$H$6484) -> 168000 | F71: =SUMIF(GL!$D$6:$D$6484,B71,GL!$I$6:$I$6484) -> 0 | G71: =IF(E71>F71,E71-F71,0) -> 168000 | H71: =IF(F71>E71,F71-E71,0) -> 0 | I71: 0.37 | J71: 41265 | K71: 15268 | L71: =D71+I71 -> 4.303 | M71: =(G71+K71)/L71 -> 42590.751 | N71: =G71+K71 -> 183268 | O71: 0.37 | P71: =M71 -> 42590.751 | Q71: =O71*P71 -> 15758.578 | R71: =N71-Q71 -> 167509.42 | T71: =J71-M71 -> -1325.7506
B72: =TB!B108 -> V005 | C72: =TB!C108 -> Shallot/Bawang Merah | D72: =SUMIF(GL!$D$5:$D$6446,B72,GL!$G$5:$G$6446) -> 3.25 | E72: =SUMIF(GL!$D$6:$D$6484,B72,GL!$H$6:$H$6484) -> 170750 | F72: =SUMIF(GL!$D$6:$D$6484,B72,GL!$I$6:$I$6484) -> 0 | G72: =IF(E72>F72,E72-F72,0) -> 170750 | H72: =IF(F72>E72,F72-E72,0) -> 0 | I72: 0.36 | J72: 45005 | K72: 16202 | L72: =D72+I72 -> 3.61 | M72: =(G72+K72)/L72 -> 51787.258 | N72: =G72+K72 -> 186952 | O72: 0.68 | P72: =M72 -> 51787.258 | Q72: =O72*P72 -> 35215.335 | R72: =N72-Q72 -> 151736.66 | T72: =J72-M72 -> -6782.2576
B73: =TB!B109 -> V006 | C73: =TB!C109 -> Onion/Bombay | D73: =SUMIF(GL!$D$5:$D$6446,B73,GL!$G$5:$G$6446) -> 13.85 | E73: =SUMIF(GL!$D$6:$D$6484,B73,GL!$H$6:$H$6484) -> 332600 | F73: =SUMIF(GL!$D$6:$D$6484,B73,GL!$I$6:$I$6484) -> 0 | G73: =IF(E73>F73,E73-F73,0) -> 332600 | H73: =IF(F73>E73,F73-E73,0) -> 0 | I73: 2.3 | J73: 23268 | K73: 53517 | L73: =D73+I73 -> 16.15 | M73: =(G73+K73)/L73 -> 23908.173 | N73: =G73+K73 -> 386117 | O73: 1 | P73: =M73 -> 23908.173 | Q73: =O73*P73 -> 23908.173 | R73: =N73-Q73 -> 362208.83 | T73: =J73-M73 -> -640.17337
